Workbook
Name CONEAU_EV_ID: Ref_EV!$A$2:$A$53
Name CONEAU_EV_EST: Ref_EV!$B$2:$B$53
Name CONEAU_EV_DESC: Ref_EV!$C$2:$C$53

Sheet Leeme
A1: SGC · Plantilla de carga por escuela
A2: Versión 0.6, 20-10-2026. Propuesta [CP] para las Escuelas de Tecnología Médica, Enfermería y Obstetricia · Facultad de Medicina, UNMSM
A4: Para qué sirve | B4: Cada escuela carga aquí sus mediciones, el estado de sus evidencias y su alcance. El tablero HTML consolida los archivos de las tres escuelas (y el de la Facultad) y calcula estados, alertas y trazabilidad.
A5: Qué se llena | B5: Solo las celdas azules sobre fondo amarillo claro. Hojas: Portada (1 vez), Carga_Indicadores (una fila por indicador, periodo y área), Evidencias (EV1 a EV52 por área), Alcance (qué indicadores se vigilan), Criterios (53 criterios del modelo; «sin dato» hasta que haya informe) y Valores_informe (29 ID; solo referencia).
A6: Qué NO se toca | B6: Catalogo, Listas y Relaciones son de consulta. Parametros, Reglas_alertas y Metas_Umbrales las edita el comité de calidad de la Facultad: si cambias algo, cambia la fecha_parametros.
A7: Regla de oro | B7: Todo dato lleva su fuente (columna fuente_dato). Una fila sin fuente no se muestra como dato en el tablero. Una meta propuesta lleva su fuente_meta; sin fuente se ignora.
A8: Periodos | B8: Anual 2025 · semestre 2025-S1 · trimestre 2025-T2 · mes 2026-02. El tablero compara por la fecha de cierre del periodo. El calendario académico de la UNMSM está por confirmar [CP].
A9: Avance esperado | B9: Para indicadores que se acumulan en el año (en Metas_Umbrales, tipo_avance = Acumulado en el año), el tablero compara con lo esperado a la fecha de corte y no con la meta anual, para evitar falsos rojos con datos parciales. Si tienes el esperado a la fecha (por ejemplo, lo programado acumulado en el plan operativo), escríbelo en esperado_a_fecha con su fuente_esperado. Si no lo traes, en los indicadores del PE FM el tablero usa el programado acumulado al corte del POI mensual de la Facultad (no el 0,5 del año); sin POI mensual vinculado el indicador queda «En seguimiento», no en rojo. Los indicadores Puntuales se comparan directo con la meta.
A10: Regla de cumplimiento | B10: En Metas_Umbrales, regla_cumplimiento: «Razón al esperado» (lo habitual); en los tiempos ID25 e ID26 cumple si el valor es menor o igual al referencial; en la variación ID6 cumple si no es negativa. La ficha del Modelo dice «menor a» en ID25 e ID26: el caso de igualdad está por confirmar con la OCAA.
A11: Formatos oficiales | B11: Esta plantilla es una propuesta de carga: no es un formato oficial de la UNMSM ni de la Facultad, y no lleva código de formato. Donde exista un formato oficial (Manual FM, UPPR) se usará y se citará su código. Códigos y formato por confirmar con la UPPR.
A12: Valor | B12: Escribe numerador y denominador (el valor se calcula, ×100 si la unidad es %) o escribe el valor directo. No escribas el signo %.
A13: Estado de validación | B13: Borrador (recién cargado) · Observado (con reparo) · Validado (revisado por quien corresponde; indica quién y cuándo).
A14: Evidencia | B14: Código EV del modelo CONEAU (lista desplegable) y la referencia del archivo o enlace donde está. Sin evidencia, el tablero genera una alerta.
A15: Datos de ejemplo | B15: Las filas con origen EJEMPLO son inventadas para probar el tablero. El interruptor del tablero las apaga. Bórralas antes de cargar datos reales.
... A18: Fuentes | B18: A4 modelo CONEAU 2026; A8 MAGPROF; A11 PE FM 2024-2027; A12 PEI UNMSM 2026-2030; A14, A15, A16 reportes del POI. Claves completas en el tablero.

Sheet Portada
A1: Portada del archivo de carga
A2: Se llena una vez por archivo.
A4: campo | B4: valor | C4: ayuda
A5: version_plantilla | B5: 0.6 | C5: No se cambia. El tablero la lee para saber si el archivo es compatible.
A6: escuela_id | B6: OBS | C6: Elige ENF, OBS, TM o FAC (Facultad, marco común).
A7: nombre_escuela | B7: =IFERROR(INDEX(Listas!$G$2:$G$5,MATCH(B6,Listas!$F$2:$F$5,0)),"") | C7: Se calcula.
A8: responsable_calidad | B8: EJEMPLO Coordinación de calidad | C8: Persona que entrega el archivo. Cargo, no datos personales sensibles.
A9: fecha_entrega | B9: 46309 | C9: Fecha en que se entrega el archivo.
A10: nota | B10: EJEMPLO: datos inventados para probar el tablero | C10: Libre.

Sheet Carga_Indicadores
A1: Carga de indicadores
A2: Una fila por indicador, periodo y área. Amarillo: se llena. Gris: se calcula. Sin fuente_dato, la fila no se muestra como dato en el tablero.
A4: periodo | B4: area_id | C4: indicador_id | D4: numerador | E4: denominador | F4: valor_directo | G4: meta_propuesta | H4: fuente_meta | I4: fuente_dato | J4: evidencia_ev | K4: evidencia_ref | L4: responsable_carga | M4: fecha_carga | N4: estado_validacion | O4: validado_por | P4: fecha_validacion | Q4: version_dato | R4: observacion | S4: origen | T4: esperado_a_fecha | U4: fuente_esperado | V4: indicador | W4: unidad | X4: valor_calculado | Y4: control
A5: 2023 | C5: ID1 | D5: 47 | E5: 85 | I5: EJEMPLO Encuesta o registro de la escuela, periodo 2023 | L5: EJEMPLO Coord. de calidad de Obstetricia | M5: 45299 | N5: Validado | O5: EJEMPLO Dirección de Escuela de Obstetricia | P5: 45308 | Q5: 1 | S5: EJEMPLO | V5: =IF(C5="","",IFERROR(INDEX(Catalogo!$C$5:$C$129,MATCH(C5,Catalogo!$A$5:$A$129,0)),"Código no existe")) | W5: =IF(C5="","",IFERROR(INDEX(Catalogo!$G$5:$G$129,MATCH(C5,Catalogo!$A$5:$A$129,0)),"")) | X5: =IF(C5="","",IF(ISNUMBER(F5),F5,IF(AND(ISNUMBER(D5),ISNUMBER(E5),E5>0),D5/E5*IF(W5="%",100,1),IF(ISNUMBER(D5),D5,"")))) | Y5: =IF(C5="","",IF(A5="","Falta periodo",IF(COUNTIF(Listas!$A$2:$A$134,A5)=0,"Periodo no válido",IF(X5="","Falta valor",IF(I5="","Falta fuente: no se mostrará",IF(AND(J5="",K5=""),"Sin evidencia",IF(N5<>"Validado","Sin validar","OK")))))))
A6: 2024 | C6: ID1 | D6: 75 | E6: 120 | I6: EJEMPLO Encuesta o registro de la escuela, periodo 2024 | J6: EV41 | K6: EJEMPLO_ID1_2024.pdf | L6: EJEMPLO Coord. de calidad de Obstetricia | M6: 45673 | N6: Observado | Q6: 1 | S6: EJEMPLO | V6: =IF(C6="","",IFERROR(INDEX(Catalogo!$C$5:$C$129,MATCH(C6,Catalogo!$A$5:$A$129,0)),"Código no existe")) | W6: =IF(C6="","",IFERROR(INDEX(Catalogo!$G$5:$G$129,MATCH(C6,Catalogo!$A$5:$A$129,0)),"")) | X6: =IF(C6="","",IF(ISNUMBER(F6),F6,IF(AND(ISNUMBER(D6),ISNUMBER(E6),E6>0),D6/E6*IF(W6="%",100,1),IF(ISNUMBER(D6),D6,"")))) | Y6: =IF(C6="","",IF(A6="","Falta periodo",IF(COUNTIF(Listas!$A$2:$A$134,A6)=0,"Periodo no válido",IF(X6="","Falta valor",IF(I6="","Falta fuente: no se mostrará",IF(AND(J6="",K6=""),"Sin evidencia",IF(N6<>"Validado","Sin validar","OK")))))))
A7: 2025 | C7: ID1 | D7: 88 | E7: 150 | I7: EJEMPLO Encuesta o registro de la escuela, periodo 2025 | J7: EV13 | K7: EJEMPLO_ID1_2025.pdf | L7: EJEMPLO Coord. de calidad de Obstetricia | M7: 46036 | N7: Validado | O7: EJEMPLO Dirección de Escuela de Obstetricia | P7: 46044 | Q7: 1 | S7: EJEMPLO | V7: =IF(C7="","",IFERROR(INDEX(Catalogo!$C$5:$C$129,MATCH(C7,Catalogo!$A$5:$A$129,0)),"Código no existe")) | W7: =IF(C7="","",IFERROR(INDEX(Catalogo!$G$5:$G$129,MATCH(C7,Catalogo!$A$5:$A$129,0)),"")) | X7: =IF(C7="","",IF(ISNUMBER(F7),F7,IF(AND(ISNUMBER(D7),ISNUMBER(E7),E7>0),D7/E7*IF(W7="%",100,1),IF(ISNUMBER(D7),D7,"")))) | Y7: =IF(C7="","",IF(A7="","Falta periodo",IF(COUNTIF(Listas!$A$2:$A$134,A7)=0,"Periodo no válido",IF(X7="","Falta valor",IF(I7="","Falta fuente: no se mostrará",IF(AND(J7="",K7=""),"Sin evidencia",IF(N7<>"Validado","Sin validar","OK")))))))
A8: 2023 | C8: ID2 | D8: 205 | E8: 320 | I8: EJEMPLO Encuesta o registro de la escuela, periodo 2023 | J8: EV38 | K8: EJEMPLO_ID2_2023.pdf | L8: EJEMPLO Coord. de calidad de Obstetricia | M8: 45318 | N8: Validado | O8: EJEMPLO Dirección de Escuela de Obstetricia | P8: 45324 | Q8: 1 | S8: EJEMPLO | V8: =IF(C8="","",IFERROR(INDEX(Catalogo!$C$5:$C$129,MATCH(C8,Catalogo!$A$5:$A$129,0)),"Código no existe")) | W8: =IF(C8="","",IFERROR(INDEX(Catalogo!$G$5:$G$129,MATCH(C8,Catalogo!$A$5:$A$129,0)),"")) | X8: =IF(C8="","",IF(ISNUMBER(F8),F8,IF(AND(ISNUMBER(D8),ISNUMBER(E8),E8>0),D8/E8*IF(W8="%",100,1),IF(ISNUMBER(D8),D8,"")))) | Y8: =IF(C8="","",IF(A8="","Falta periodo",IF(COUNTIF(Listas!$A$2:$A$134,A8)=0,"Periodo no válido",IF(X8="","Falta valor",IF(I8="","Falta fuente: no se mostrará",IF(AND(J8="",K8=""),"Sin evidencia",IF(N8<>"Validado","Sin validar","OK")))))))
A9: 2024 | C9: ID2 | D9: 146 | E9: 210 | I9: EJEMPLO Encuesta o registro de la escuela, periodo 2024 | J9: EV41 | K9: EJEMPLO_ID2_2024.pdf | L9: EJEMPLO Coord. de calidad de Obstetricia | M9: 45676 | N9: Validado | O9: EJEMPLO Dirección de Escuela de Obstetricia | P9: 45678 | Q9: 1 | S9: EJEMPLO | V9: =IF(C9="","",IFERROR(INDEX(Catalogo!$C$5:$C$129,MATCH(C9,Catalogo!$A$5:$A$129,0)),"Código no existe")) | W9: =IF(C9="","",IFERROR(INDEX(Catalogo!$G$5:$G$129,MATCH(C9,Catalogo!$A$5:$A$129,0)),"")) | X9: =IF(C9="","",IF(ISNUMBER(F9),F9,IF(AND(ISNUMBER(D9),ISNUMBER(E9),E9>0),D9/E9*IF(W9="%",100,1),IF(ISNUMBER(D9),D9,"")))) | Y9: =IF(C9="","",IF(A9="","Falta periodo",IF(COUNTIF(Listas!$A$2:$A$134,A9)=0,"Periodo no válido",IF(X9="","Falta valor",IF(I9="","Falta fuente: no se mostrará",IF(AND(J9="",K9=""),"Sin evidencia",IF(N9<>"Validado","Sin validar","OK")))))))
A10: 2025 | C10: ID2 | D10: 33 | E10: 48 | I10: EJEMPLO Encuesta o registro de la escuela, periodo 2025 | J10: EV13 | K10: EJEMPLO_ID2_2025.pdf | L10: EJEMPLO Coord. de calidad de Obstetricia | M10: 46044 | N10: Validado | O10: EJEMPLO Dirección de Escuela de Obstetricia | P10: 46045 | Q10: 1 | S10: EJEMPLO | V10: =IF(C10="","",IFERROR(INDEX(Catalogo!$C$5:$C$129,MATCH(C10,Catalogo!$A$5:$A$129,0)),"Código no existe")) | W10: =IF(C10="","",IFERROR(INDEX(Catalogo!$G$5:$G$129,MATCH(C10,Catalogo!$A$5:$A$129,0)),"")) | X10: =IF(C10="","",IF(ISNUMBER(F10),F10,IF(AND(ISNUMBER(D10),ISNUMBER(E10),E10>0),D10/E10*IF(W10="%",100,1),IF(ISNUMBER(D10),D10,"")))) | Y10: =IF(C10="","",IF(A10="","Falta periodo",IF(COUNTIF(Listas!$A$2:$A$134,A10)=0,"Periodo no válido",IF(X10="","Falta valor",IF(I10="","Falta fuente: no se mostrará",IF(AND(J10="",K10=""),"Sin evidencia",IF(N10<>"Validado","Sin validar","OK")))))))
A11: 2023 | C11: ID3 | D11: 42 | E11: 85 | I11: EJEMPLO Encuesta o registro de la escuela, periodo 2023 | J11: EV21 | K11: EJEMPLO_ID3_2023.pdf | L11: EJEMPLO Coord. de calidad de Obstetricia | M11: 45314 | N11: Validado | O11: EJEMPLO Dirección de Escuela de Obstetricia | P11: 45319 | Q11: 1 | S11: EJEMPLO | V11: =IF(C11="","",IFERROR(INDEX(Catalogo!$C$5:$C$129,MATCH(C11,Catalogo!$A$5:$A$129,0)),"Código no existe")) | W11: =IF(C11="","",IFERROR(INDEX(Catalogo!$G$5:$G$129,MATCH(C11,Catalogo!$A$5:$A$129,0)),"")) | X11: =IF(C11="","",IF(ISNUMBER(F11),F11,IF(AND(ISNUMBER(D11),ISNUMBER(E11),E11>0),D11/E11*IF(W11="%",100,1),IF(ISNUMBER(D11),D11,"")))) | Y11: =IF(C11="","",IF(A11="","Falta periodo",IF(COUNTIF(Listas!$A$2:$A$134,A11)=0,"Periodo no válido",IF(X11="","Falta valor",IF(I11="","Falta fuente: no se mostrará",IF(AND(J11="",K11=""),"Sin evidencia",IF(N11<>"Validado","Sin validar","OK")))))))
A12: 2024 | C12: ID3 | D12: 27 | E12: 60 | I12: EJEMPLO Encuesta o registro de la escuela, periodo 2024 | J12: EV38 | K12: EJEMPLO_ID3_2024.pdf | L12: EJEMPLO Coord. de calidad de Obstetricia | M12: 45680 | N12: Validado | O12: EJEMPLO Dirección de Escuela de Obstetricia | P12: 45683 | Q12: 1 | S12: EJEMPLO | V12: =IF(C12="","",IFERROR(INDEX(Catalogo!$C$5:$C$129,MATCH(C12,Catalogo!$A$5:$A$129,0)),"Código no existe")) | W12: =IF(C12="","",IFERROR(INDEX(Catalogo!$G$5:$G$129,MATCH(C12,Catalogo!$A$5:$A$129,0)),"")) | X12: =IF(C12="","",IF(ISNUMBER(F12),F12,IF(AND(ISNUMBER(D12),ISNUMBER(E12),E12>0),D12/E12*IF(W12="%",100,1),IF(ISNUMBER(D12),D12,"")))) | Y12: =IF(C12="","",IF(A12="","Falta periodo",IF(COUNTIF(Listas!$A$2:$A$134,A12)=0,"Periodo no válido",IF(X12="","Falta valor",IF(I12="","Falta fuente: no se mostrará",IF(AND(J12="",K12=""),"Sin evidencia",IF(N12<>"Validado","Sin validar","OK")))))))
A13: 2025 | C13: ID3 | D13: 70 | E13: 150 | I13: EJEMPLO Encuesta o registro de la escuela, periodo 2025 | J13: EV41 | K13: EJEMPLO_ID3_2025.pdf | L13: EJEMPLO Coord. de calidad de Obstetricia | M13: 46032 | N13: Validado | O13: EJEMPLO Dirección de Escuela de Obstetricia | P13: 46036 | Q13: 1 | S13: EJEMPLO | V13: =IF(C13="","",IFERROR(INDEX(Catalogo!$C$5:$C$129,MATCH(C13,Catalogo!$A$5:$A$129,0)),"Código no existe")) | W13: =IF(C13="","",IFERROR(INDEX(Catalogo!$G$5:$G$129,MATCH(C13,Catalogo!$A$5:$A$129,0)),"")) | X13: =IF(C13="","",IF(ISNUMBER(F13),F13,IF(AND(ISNUMBER(D13),ISNUMBER(E13),E13>0),D13/E13*IF(W13="%",100,1),IF(ISNUMBER(D13),D13,"")))) | Y13: =IF(C13="","",IF(A13="","Falta periodo",IF(COUNTIF(Listas!$A$2:$A$134,A13)=0,"Periodo no válido",IF(X13="","Falta valor",IF(I13="","Falta fuente: no se mostrará",IF(AND(J13="",K13=""),"Sin evidencia",IF(N13<>"Validado","Sin validar","OK")))))))
A14: 2023 | C14: ID4 | D14: 154 | E14: 320 | I14: EJEMPLO Encuesta o registro de la escuela, periodo 2023 | L14: EJEMPLO Coord. de calidad de Obstetricia | M14: 45315 | N14: Observado | Q14: 1 | S14: EJEMPLO | V14: =IF(C14="","",IFERROR(INDEX(Catalogo!$C$5:$C$129,MATCH(C14,Catalogo!$A$5:$A$129,0)),"Código no existe")) | W14: =IF(C14="","",IFERROR(INDEX(Catalogo!$G$5:$G$129,MATCH(C14,Catalogo!$A$5:$A$129,0)),"")) | X14: =IF(C14="","",IF(ISNUMBER(F14),F14,IF(AND(ISNUMBER(D14),ISNUMBER(E14),E14>0),D14/E14*IF(W14="%",100,1),IF(ISNUMBER(D14),D14,"")))) | Y14: =IF(C14="","",IF(A14="","Falta periodo",IF(COUNTIF(Listas!$A$2:$A$134,A14)=0,"Periodo no válido",IF(X14="","Falta valor",IF(I14="","Falta fuente: no se mostrará",IF(AND(J14="",K14=""),"Sin evidencia",IF(N14<>"Validado","Sin validar","OK")))))))
A15: 2024 | C15: ID4 | D15: 111 | E15: 210 | I15: EJEMPLO Encuesta o registro de la escuela, periodo 2024 | J15: EV41 | K15: EJEMPLO_ID4_2024.pdf | L15: EJEMPLO Coord. de calidad de Obstetricia | M15: 45663 | N15: Borrador | Q15: 1 | S15: EJEMPLO | V15: =IF(C15="","",IFERROR(INDEX(Catalogo!$C$5:$C$129,MATCH(C15,Catalogo!$A$5:$A$129,0)),"Código no existe")) | W15: =IF(C15="","",IFERROR(INDEX(Catalogo!$G$5:$G$129,MATCH(C15,Catalogo!$A$5:$A$129,0)),"")) | X15: =IF(C15="","",IF(ISNUMBER(F15),F15,IF(AND(ISNUMBER(D15),ISNUMBER(E15),E15>0),D15/E15*IF(W15="%",100,1),IF(ISNUMBER(D15),D15,"")))) | Y15: =IF(C15="","",IF(A15="","Falta periodo",IF(COUNTIF(Listas!$A$2:$A$134,A15)=0,"Periodo no válido",IF(X15="","Falta valor",IF(I15="","Falta fuente: no se mostrará",IF(AND(J15="",K15=""),"Sin evidencia",IF(N15<>"Validado","Sin validar","OK")))))))
A16: 2025 | C16: ID4 | D16: 32 | E16: 60 | I16: EJEMPLO Encuesta o registro de la escuela, periodo 2025 | J16: EV21 | K16: EJEMPLO_ID4_2025.pdf | L16: EJEMPLO Coord. de calidad de Obstetricia | M16: 46050 | N16: Validado | O16: EJEMPLO Dirección de Escuela de Obstetricia | P16: 46058 | Q16: 1 | S16: EJEMPLO | V16: =IF(C16="","",IFERROR(INDEX(Catalogo!$C$5:$C$129,MATCH(C16,Catalogo!$A$5:$A$129,0)),"Código no existe")) | W16: =IF(C16="","",IFERROR(INDEX(Catalogo!$G$5:$G$129,MATCH(C16,Catalogo!$A$5:$A$129,0)),"")) | X16: =IF(C16="","",IF(ISNUMBER(F16),F16,IF(AND(ISNUMBER(D16),ISNUMBER(E16),E16>0),D16/E16*IF(W16="%",100,1),IF(ISNUMBER(D16),D16,"")))) | Y16: =IF(C16="","",IF(A16="","Falta periodo",IF(COUNTIF(Listas!$A$2:$A$134,A16)=0,"Periodo no válido",IF(X16="","Falta valor",IF(I16="","Falta fuente: no se mostrará",IF(AND(J16="",K16=""),"Sin evidencia",IF(N16<>"Validado","Sin validar","OK")))))))
A17: 2024-S2 | C17: ID5 | D17: 224 | E17: 320 | I17: EJEMPLO Encuesta o registro de la escuela, periodo 2024-S2 | J17: EV38 | K17: EJEMPLO_ID5_2024-S2.pdf | L17: EJEMPLO Coord. de calidad de Obstetricia | M17: 45674 | N17: Validado | O17: EJEMPLO Dirección de Escuela de Obstetricia | P17: 45677 | Q17: 1 | S17: EJEMPLO | V17: =IF(C17="","",IFERROR(INDEX(Catalogo!$C$5:$C$129,MATCH(C17,Catalogo!$A$5:$A$129,0)),"Código no existe")) | W17: =IF(C17="","",IFERROR(INDEX(Catalogo!$G$5:$G$129,MATCH(C17,Catalogo!$A$5:$A$129,0)),"")) | X17: =IF(C17="","",IF(ISNUMBER(F17),F17,IF(AND(ISNUMBER(D17),ISNUMBER(E17),E17>0),D17/E17*IF(W17="%",100,1),IF(ISNUMBER(D17),D17,"")))) | Y17: =IF(C17="","",IF(A17="","Falta periodo",IF(COUNTIF(Listas!$A$2:$A$134,A17)=0,"Periodo no válido",IF(X17="","Falta valor",IF(I17="","Falta fuente: no se mostrará",IF(AND(J17="",K17=""),"Sin evidencia",IF(N17<>"Validado","Sin validar","OK")))))))
A18: 2025-S1 | C18: ID5 | D18: 88 | E18: 120 | I18: EJEMPLO Encuesta o registro de la escuela, periodo 2025-S1 | J18: EV38 | K18: EJEMPLO_ID5_2025-S1.pdf | L18: EJEMPLO Coord. de calidad de Obstetricia | M18: 45850 | N18: Validado | O18: EJEMPLO Dirección de Escuela de Obstetricia | P18: 45854 | Q18: 1 | S18: EJEMPLO | V18: =IF(C18="","",IFERROR(INDEX(Catalogo!$C$5:$C$129,MATCH(C18,Catalogo!$A$5:$A$129,0)),"Código no existe")) | W18: =IF(C18="","",IFERROR(INDEX(Catalogo!$G$5:$G$129,MATCH(C18,Catalogo!$A$5:$A$129,0)),"")) | X18: =IF(C18="","",IF(ISNUMBER(F18),F18,IF(AND(ISNUMBER(D18),ISNUMBER(E18),E18>0),D18/E18*IF(W18="%",100,1),IF(ISNUMBER(D18),D18,"")))) | Y18: =IF(C18="","",IF(A18="","Falta periodo",IF(COUNTIF(Listas!$A$2:$A$134,A18)=0,"Periodo no válido",IF(X18="","Falta valor",IF(I18="","Falta fuente: no se mostrará",IF(AND(J18="",K18=""),"Sin evidencia",IF(N18<>"Validado","Sin validar","OK")))))))
A19: 2025-S2 | C19: ID5 | D19: 107 | E19: 150 | I19: EJEMPLO Encuesta o registro de la escuela, periodo 2025-S2 | J19: EV21 | K19: EJEMPLO_ID5_2025-S2.pdf | L19: EJEMPLO Coord. de calidad de Obstetricia | M19: 46034 | N19: Borrador | Q19: 1 | S19: EJEMPLO | V19: =IF(C19="","",IFERROR(INDEX(Catalogo!$C$5:$C$129,MATCH(C19,Catalogo!$A$5:$A$129,0)),"Código no existe")) | W19: =IF(C19="","",IFERROR(INDEX(Catalogo!$G$5:$G$129,MATCH(C19,Catalogo!$A$5:$A$129,0)),"")) | X19: =IF(C19="","",IF(ISNUMBER(F19),F19,IF(AND(ISNUMBER(D19),ISNUMBER(E19),E19>0),D19/E19*IF(W19="%",100,1),IF(ISNUMBER(D19),D19,"")))) | Y19: =IF(C19="","",IF(A19="","Falta periodo",IF(COUNTIF(Listas!$A$2:$A$134,A19)=0,"Periodo no válido",IF(X19="","Falta valor",IF(I19="","Falta fuente: no se mostrará",IF(AND(J19="",K19=""),"Sin evidencia",IF(N19<>"Validado","Sin validar","OK")))))))
A20: 2023 | C20: ID6 | D20: 3 | E20: 320 | I20: EJEMPLO Encuesta o registro de la escuela, periodo 2023 | J20: EV44 | K20: EJEMPLO_ID6_2023.pdf | L20: EJEMPLO Coord. de calidad de Obstetricia | M20: 45298 | N20: Validado | O20: EJEMPLO Dirección de Escuela de Obstetricia | P20: 45303 | Q20: 1 | S20: EJEMPLO | V20: =IF(C20="","",IFERROR(INDEX(Catalogo!$C$5:$C$129,MATCH(C20,Catalogo!$A$5:$A$129,0)),"Código no existe")) | W20: =IF(C20="","",IFERROR(INDEX(Catalogo!$G$5:$G$129,MATCH(C20,Catalogo!$A$5:$A$129,0)),"")) | X20: =IF(C20="","",IF(ISNUMBER(F20),F20,IF(AND(ISNUMBER(D20),ISNUMBER(E20),E20>0),D20/E20*IF(W20="%",100,1),IF(ISNUMBER(D20),D20,"")))) | Y20: =IF(C20="","",IF(A20="","Falta periodo",IF(COUNTIF(Listas!$A$2:$A$134,A20)=0,"Periodo no válido",IF(X20="","Falta valor",IF(I20="","Falta fuente: no se mostrará",IF(AND(J20="",K20=""),"Sin evidencia",IF(N20<>"Validado","Sin validar","OK")))))))
A21: 2024 | C21: ID6 | D21: 1 | E21: 60 | I21: EJEMPLO Encuesta o registro de la escuela, periodo 2024 | J21: EV21 | K21: EJEMPLO_ID6_2024.pdf | L21: EJEMPLO Coord. de calidad de Obstetricia | M21: 45679 | N21: Validado | O21: EJEMPLO Dirección de Escuela de Obstetricia | P21: 45681 | Q21: 1 | S21: EJEMPLO | V21: =IF(C21="","",IFERROR(INDEX(Catalogo!$C$5:$C$129,MATCH(C21,Catalogo!$A$5:$A$129,0)),"Código no existe")) | W21: =IF(C21="","",IFERROR(INDEX(Catalogo!$G$5:$G$129,MATCH(C21,Catalogo!$A$5:$A$129,0)),"")) | X21: =IF(C21="","",IF(ISNUMBER(F21),F21,IF(AND(ISNUMBER(D21),ISNUMBER(E21),E21>0),D21/E21*IF(W21="%",100,1),IF(ISNUMBER(D21),D21,"")))) | Y21: =IF(C21="","",IF(A21="","Falta periodo",IF(COUNTIF(Listas!$A$2:$A$134,A21)=0,"Periodo no válido",IF(X21="","Falta valor",IF(I21="","Falta fuente: no se mostrará",IF(AND(J21="",K21=""),"Sin evidencia",IF(N21<>"Validado","Sin validar","OK")))))))
A22: 2025 | C22: ID6 | D22: 2 | E22: 210 | I22: EJEMPLO Encuesta o registro de la escuela, periodo 2025 | J22: EV38 | K22: EJEMPLO_ID6_2025.pdf | L22: EJEMPLO Coord. de calidad de Obstetricia | M22: 46047 | N22: Validado | O22: EJEMPLO Dirección de Escuela de Obstetricia | P22: 46048 | Q22: 1 | S22: EJEMPLO | V22: =IF(C22="","",IFERROR(INDEX(Catalogo!$C$5:$C$129,MATCH(C22,Catalogo!$A$5:$A$129,0)),"Código no existe")) | W22: =IF(C22="","",IFERROR(INDEX(Catalogo!$G$5:$G$129,MATCH(C22,Catalogo!$A$5:$A$129,0)),"")) | X22: =IF(C22="","",IF(ISNUMBER(F22),F22,IF(AND(ISNUMBER(D22),ISNUMBER(E22),E22>0),D22/E22*IF(W22="%",100,1),IF(ISNUMBER(D22),D22,"")))) | Y22: =IF(C22="","",IF(A22="","Falta periodo",IF(COUNTIF(Listas!$A$2:$A$134,A22)=0,"Periodo no válido",IF(X22="","Falta valor",IF(I22="","Falta fuente: no se mostrará",IF(AND(J22="",K22=""),"Sin evidencia",IF(N22<>"Validado","Sin validar","OK")))))))
A23: 2023 | C23: ID7 | D23: 96 | E23: 210 | I23: EJEMPLO Encuesta o registro de la escuela, periodo 2023 | J23: EV38 | K23: EJEMPLO_ID7_2023.pdf | L23: EJEMPLO Coord. de calidad de Obstetricia | M23: 45308 | N23: Validado | O23: EJEMPLO Dirección de Escuela de Obstetricia | P23: 45310 | Q23: 1 | S23: EJEMPLO | V23: =IF(C23="","",IFERROR(INDEX(Catalogo!$C$5:$C$129,MATCH(C23,Catalogo!$A$5:$A$129,0)),"Código no existe")) | W23: =IF(C23="","",IFERROR(INDEX(Catalogo!$G$5:$G$129,MATCH(C23,Catalogo!$A$5:$A$129,0)),"")) | X23: =IF(C23="","",IF(ISNUMBER(F23),F23,IF(AND(ISNUMBER(D23),ISNUMBER(E23),E23>0),D23/E23*IF(W23="%",100,1),IF(ISNUMBER(D23),D23,"")))) | Y23: =IF(C23="","",IF(A23="","Falta periodo",IF(COUNTIF(Listas!$A$2:$A$134,A23)=0,"Periodo no válido",IF(X23="","Falta valor",IF(I23="","Falta fuente: no se mostrará",IF(AND(J23="",K23=""),"Sin evidencia",IF(N23<>"Validado","Sin validar","OK")))))))
A24: 2024 | C24: ID7 | D24: 38 | E24: 85 | I24: EJEMPLO Encuesta o registro de la escuela, periodo 2024 | J24: EV13 | K24: EJEMPLO_ID7_2024.pdf | L24: EJEMPLO Coord. de calidad de Obstetricia | M24: 45668 | N24: Observado | Q24: 1 | S24: EJEMPLO | V24: =IF(C24="","",IFERROR(INDEX(Catalogo!$C$5:$C$129,MATCH(C24,Catalogo!$A$5:$A$129,0)),"Código no existe")) | W24: =IF(C24="","",IFERROR(INDEX(Catalogo!$G$5:$G$129,MATCH(C24,Catalogo!$A$5:$A$129,0)),"")) | X24: =IF(C24="","",IF(ISNUMBER(F24),F24,IF(AND(ISNUMBER(D24),ISNUMBER(E24),E24>0),D24/E24*IF(W24="%",100,1),IF(ISNUMBER(D24),D24,"")))) | Y24: =IF(C24="","",IF(A24="","Falta periodo",IF(COUNTIF(Listas!$A$2:$A$134,A24)=0,"Periodo no válido",IF(X24="","Falta valor",IF(I24="","Falta fuente: no se mostrará",IF(AND(J24="",K24=""),"Sin evidencia",IF(N24<>"Validado","Sin validar","OK")))))))
A25: 2025 | C25: ID7 | D25: 94 | E25: 210 | I25: EJEMPLO Encuesta o registro de la escuela, periodo 2025 | J25: EV30 | K25: EJEMPLO_ID7_2025.pdf | L25: EJEMPLO Coord. de calidad de Obstetricia | M25: 46036 | N25: Validado | O25: EJEMPLO Dirección de Escuela de Obstetricia | P25: 46040 | Q25: 1 | S25: EJEMPLO | V25: =IF(C25="","",IFERROR(INDEX(Catalogo!$C$5:$C$129,MATCH(C25,Catalogo!$A$5:$A$129,0)),"Código no existe")) | W25: =IF(C25="","",IFERROR(INDEX(Catalogo!$G$5:$G$129,MATCH(C25,Catalogo!$A$5:$A$129,0)),"")) | X25: =IF(C25="","",IF(ISNUMBER(F25),F25,IF(AND(ISNUMBER(D25),ISNUMBER(E25),E25>0),D25/E25*IF(W25="%",100,1),IF(ISNUMBER(D25),D25,"")))) | Y25: =IF(C25="","",IF(A25="","Falta periodo",IF(COUNTIF(Listas!$A$2:$A$134,A25)=0,"Periodo no válido",IF(X25="","Falta valor",IF(I25="","Falta fuente: no se mostrará",IF(AND(J25="",K25=""),"Sin evidencia",IF(N25<>"Validado","Sin validar","OK")))))))
A26: 2024-S2 | C26: ID10 | D26: 31 | E26: 48 | I26: EJEMPLO Encuesta o registro de la escuela, periodo 2024-S2 | J26: EV21 | K26: EJEMPLO_ID10_2024-S2.pdf | L26: EJEMPLO Coord. de calidad de Obstetricia | M26: 45674 | N26: Validado | O26: EJEMPLO Dirección de Escuela de Obstetricia | P26: 45678 | Q26: 1 | S26: EJEMPLO | V26: =IF(C26="","",IFERROR(INDEX(Catalogo!$C$5:$C$129,MATCH(C26,Catalogo!$A$5:$A$129,0)),"Código no existe")) | W26: =IF(C26="","",IFERROR(INDEX(Catalogo!$G$5:$G$129,MATCH(C26,Catalogo!$A$5:$A$129,0)),"")) | X26: =IF(C26="","",IF(ISNUMBER(F26),F26,IF(AND(ISNUMBER(D26),ISNUMBER(E26),E26>0),D26/E26*IF(W26="%",100,1),IF(ISNUMBER(D26),D26,"")))) | Y26: =IF(C26="","",IF(A26="","Falta periodo",IF(COUNTIF(Listas!$A$2:$A$134,A26)=0,"Periodo no válido",IF(X26="","Falta valor",IF(I26="","Falta fuente: no se mostrará",IF(AND(J26="",K26=""),"Sin evidencia",IF(N26<>"Validado","Sin validar","OK")))))))
A27: 2025-S1 | C27: ID10 | D27: 60 | E27: 85 | I27: EJEMPLO Encuesta o registro de la escuela, periodo 2025-S1 | J27: EV44 | K27: EJEMPLO_ID10_2025-S1.pdf | L27: EJEMPLO Coord. de calidad de Obstetricia | M27: 45856 | N27: Validado | O27: EJEMPLO Dirección de Escuela de Obstetricia | P27: 45861 | Q27: 1 | S27: EJEMPLO | V27: =IF(C27="","",IFERROR(INDEX(Catalogo!$C$5:$C$129,MATCH(C27,Catalogo!$A$5:$A$129,0)),"Código no existe")) | W27: =IF(C27="","",IFERROR(INDEX(Catalogo!$G$5:$G$129,MATCH(C27,Catalogo!$A$5:$A$129,0)),"")) | X27: =IF(C27="","",IF(ISNUMBER(F27),F27,IF(AND(ISNUMBER(D27),ISNUMBER(E27),E27>0),D27/E27*IF(W27="%",100,1),IF(ISNUMBER(D27),D27,"")))) | Y27: =IF(C27="","",IF(A27="","Falta periodo",IF(COUNTIF(Listas!$A$2:$A$134,A27)=0,"Periodo no válido",IF(X27="","Falta valor",IF(I27="","Falta fuente: no se mostrará",IF(AND(J27="",K27=""),"Sin evidencia",IF(N27<>"Validado","Sin validar","OK")))))))
A28: 2025-S2 | C28: ID10 | D28: 32 | E28: 48 | I28: EJEMPLO Encuesta o registro de la escuela, periodo 2025-S2 | L28: EJEMPLO Coord. de calidad de Obstetricia | M28: 46046 | N28: Validado | O28: EJEMPLO Dirección de Escuela de Obstetricia | P28: 46047 | Q28: 1 | S28: EJEMPLO | V28: =IF(C28="","",IFERROR(INDEX(Catalogo!$C$5:$C$129,MATCH(C28,Catalogo!$A$5:$A$129,0)),"Código no existe")) | W28: =IF(C28="","",IFERROR(INDEX(Catalogo!$G$5:$G$129,MATCH(C28,Catalogo!$A$5:$A$129,0)),"")) | X28: =IF(C28="","",IF(ISNUMBER(F28),F28,IF(AND(ISNUMBER(D28),ISNUMBER(E28),E28>0),D28/E28*IF(W28="%",100,1),IF(ISNUMBER(D28),D28,"")))) | Y28: =IF(C28="","",IF(A28="","Falta periodo",IF(COUNTIF(Listas!$A$2:$A$134,A28)=0,"Periodo no válido",IF(X28="","Falta valor",IF(I28="","Falta fuente: no se mostrará",IF(AND(J28="",K28=""),"Sin evidencia",IF(N28<>"Validado","Sin validar","OK")))))))
A29: 2026-S1 | C29: ID10 | D29: 211 | E29: 320 | I29: EJEMPLO Encuesta o registro de la escuela, periodo 2026-S1 | J29: EV43 | K29: EJEMPLO_ID10_2026-S1.pdf | L29: EJEMPLO Coord. de calidad de Obstetricia | M29: 46223 | N29: Borrador | Q29: 1 | S29: EJEMPLO | V29: =IF(C29="","",IFERROR(INDEX(Catalogo!$C$5:$C$129,MATCH(C29,Catalogo!$A$5:$A$129,0)),"Código no existe")) | W29: =IF(C29="","",IFERROR(INDEX(Catalogo!$G$5:$G$129,MATCH(C29,Catalogo!$A$5:$A$129,0)),"")) | X29: =IF(C29="","",IF(ISNUMBER(F29),F29,IF(AND(ISNUMBER(D29),ISNUMBER(E29),E29>0),D29/E29*IF(W29="%",100,1),IF(ISNUMBER(D29),D29,"")))) | Y29: =IF(C29="","",IF(A29="","Falta periodo",IF(COUNTIF(Listas!$A$2:$A$134,A29)=0,"Periodo no válido",IF(X29="","Falta valor",IF(I29="","Falta fuente: no se mostrará",IF(AND(J29="",K29=""),"Sin evidencia",IF(N29<>"Validado","Sin validar","OK")))))))
A30: 2025-S1 | C30: ID11 | D30: 257 | E30: 320 | I30: EJEMPLO Encuesta o registro de la escuela, periodo 2025-S1 | J30: EV21 | K30: EJEMPLO_ID11_2025-S1.pdf | L30: EJEMPLO Coord. de calidad de Obstetricia | M30: 45845 | N30: Validado | O30: EJEMPLO Dirección de Escuela de Obstetricia | P30: 45847 | Q30: 1 | S30: EJEMPLO | V30: =IF(C30="","",IFERROR(INDEX(Catalogo!$C$5:$C$129,MATCH(C30,Catalogo!$A$5:$A$129,0)),"Código no existe")) | W30: =IF(C30="","",IFERROR(INDEX(Catalogo!$G$5:$G$129,MATCH(C30,Catalogo!$A$5:$A$129,0)),"")) | X30: =IF(C30="","",IF(ISNUMBER(F30),F30,IF(AND(ISNUMBER(D30),ISNUMBER(E30),E30>0),D30/E30*IF(W30="%",100,1),IF(ISNUMBER(D30),D30,"")))) | Y30: =IF(C30="","",IF(A30="","Falta periodo",IF(COUNTIF(Listas!$A$2:$A$134,A30)=0,"Periodo no válido",IF(X30="","Falta valor",IF(I30="","Falta fuente: no se mostrará",IF(AND(J30="",K30=""),"Sin evidencia",IF(N30<>"Validado","Sin validar","OK")))))))
A31: 2025-S2 | C31: ID11 | D31: 109 | E31: 150 | I31: EJEMPLO Encuesta o registro de la escuela, periodo 2025-S2 | J31: EV35 | K31: EJEMPLO_ID11_2025-S2.pdf | L31: EJEMPLO Coord. de calidad de Obstetricia | M31: 46048 | N31: Observado | Q31: 1 | S31: EJEMPLO | V31: =IF(C31="","",IFERROR(INDEX(Catalogo!$C$5:$C$129,MATCH(C31,Catalogo!$A$5:$A$129,0)),"Código no existe")) | W31: =IF(C31="","",IFERROR(INDEX(Catalogo!$G$5:$G$129,MATCH(C31,Catalogo!$A$5:$A$129,0)),"")) | X31: =IF(C31="","",IF(ISNUMBER(F31),F31,IF(AND(ISNUMBER(D31),ISNUMBER(E31),E31>0),D31/E31*IF(W31="%",100,1),IF(ISNUMBER(D31),D31,"")))) | Y31: =IF(C31="","",IF(A31="","Falta periodo",IF(COUNTIF(Listas!$A$2:$A$134,A31)=0,"Periodo no válido",IF(X31="","Falta valor",IF(I31="","Falta fuente: no se mostrará",IF(AND(J31="",K31=""),"Sin evidencia",IF(N31<>"Validado","Sin validar","OK")))))))
A32: 2026-S1 | C32: ID11 | D32: 159 | E32: 210 | I32: EJEMPLO Encuesta o registro de la escuela, periodo 2026-S1 | J32: EV44 | K32: EJEMPLO_ID11_2026-S1.pdf | L32: EJEMPLO Coord. de calidad de Obstetricia | M32: 46215 | N32: Validado | O32: EJEMPLO Dirección de Escuela de Obstetricia | P32: 46219 | Q32: 1 | S32: EJEMPLO | V32: =IF(C32="","",IFERROR(INDEX(Catalogo!$C$5:$C$129,MATCH(C32,Catalogo!$A$5:$A$129,0)),"Código no existe")) | W32: =IF(C32="","",IFERROR(INDEX(Catalogo!$G$5:$G$129,MATCH(C32,Catalogo!$A$5:$A$129,0)),"")) | X32: =IF(C32="","",IF(ISNUMBER(F32),F32,IF(AND(ISNUMBER(D32),ISNUMBER(E32),E32>0),D32/E32*IF(W32="%",100,1),IF(ISNUMBER(D32),D32,"")))) | Y32: =IF(C32="","",IF(A32="","Falta periodo",IF(COUNTIF(Listas!$A$2:$A$134,A32)=0,"Periodo no válido",IF(X32="","Falta valor",IF(I32="","Falta fuente: no se mostrará",IF(AND(J32="",K32=""),"Sin evidencia",IF(N32<>"Validado","Sin validar","OK")))))))
A33: 2024 | C33: ID12 | D33: 60 | E33: 120 | I33: EJEMPLO Encuesta o registro de la escuela, periodo 2024 | J33: EV43 | K33: EJEMPLO_ID12_2024.pdf | L33: EJEMPLO Coord. de calidad de Obstetricia | M33: 45668 | N33: Validado | O33: EJEMPLO Dirección de Escuela de Obstetricia | P33: 45669 | Q33: 1 | S33: EJEMPLO | V33: =IF(C33="","",IFERROR(INDEX(Catalogo!$C$5:$C$129,MATCH(C33,Catalogo!$A$5:$A$129,0)),"Código no existe")) | W33: =IF(C33="","",IFERROR(INDEX(Catalogo!$G$5:$G$129,MATCH(C33,Catalogo!$A$5:$A$129,0)),"")) | X33: =IF(C33="","",IF(ISNUMBER(F33),F33,IF(AND(ISNUMBER(D33),ISNUMBER(E33),E33>0),D33/E33*IF(W33="%",100,1),IF(ISNUMBER(D33),D33,"")))) | Y33: =IF(C33="","",IF(A33="","Falta periodo",IF(COUNTIF(Listas!$A$2:$A$134,A33)=0,"Periodo no válido",IF(X33="","Falta valor",IF(I33="","Falta fuente: no se mostrará",IF(AND(J33="",K33=""),"Sin evidencia",IF(N33<>"Validado","Sin validar","OK")))))))
A34: 2025 | C34: ID12 | D34: 75 | E34: 150 | I34: EJEMPLO Encuesta o registro de la escuela, periodo 2025 | J34: EV30 | K34: EJEMPLO_ID12_2025.pdf | L34: EJEMPLO Coord. de calidad de Obstetricia | M34: 46041 | N34: Borrador | Q34: 1 | S34: EJEMPLO | V34: =IF(C34="","",IFERROR(INDEX(Catalogo!$C$5:$C$129,MATCH(C34,Catalogo!$A$5:$A$129,0)),"Código no existe")) | W34: =IF(C34="","",IFERROR(INDEX(Catalogo!$G$5:$G$129,MATCH(C34,Catalogo!$A$5:$A$129,0)),"")) | X34: =IF(C34="","",IF(ISNUMBER(F34),F34,IF(AND(ISNUMBER(D34),ISNUMBER(E34),E34>0),D34/E34*IF(W34="%",100,1),IF(ISNUMBER(D34),D34,"")))) | Y34: =IF(C34="","",IF(A34="","Falta periodo",IF(COUNTIF(Listas!$A$2:$A$134,A34)=0,"Periodo no válido",IF(X34="","Falta valor",IF(I34="","Falta fuente: no se mostrará",IF(AND(J34="",K34=""),"Sin evidencia",IF(N34<>"Validado","Sin validar","OK")))))))
A35: 2023 | C35: ID13 | D35: 8 | E35: 120 | I35: EJEMPLO Encuesta o registro de la escuela, periodo 2023 | L35: EJEMPLO Coord. de calidad de Obstetricia | M35: 45313 | N35: Validado | O35: EJEMPLO Dirección de Escuela de Obstetricia | P35: 45318 | Q35: 1 | S35: EJEMPLO | V35: =IF(C35="","",IFERROR(INDEX(Catalogo!$C$5:$C$129,MATCH(C35,Catalogo!$A$5:$A$129,0)),"Código no existe")) | W35: =IF(C35="","",IFERROR(INDEX(Catalogo!$G$5:$G$129,MATCH(C35,Catalogo!$A$5:$A$129,0)),"")) | X35: =IF(C35="","",IF(ISNUMBER(F35),F35,IF(AND(ISNUMBER(D35),ISNUMBER(E35),E35>0),D35/E35*IF(W35="%",100,1),IF(ISNUMBER(D35),D35,"")))) | Y35: =IF(C35="","",IF(A35="","Falta periodo",IF(COUNTIF(Listas!$A$2:$A$134,A35)=0,"Periodo no válido",IF(X35="","Falta valor",IF(I35="","Falta fuente: no se mostrará",IF(AND(J35="",K35=""),"Sin evidencia",IF(N35<>"Validado","Sin validar","OK")))))))
A36: 2024 | C36: ID13 | D36: 15 | E36: 210 | I36: EJEMPLO Encuesta o registro de la escuela, periodo 2024 | L36: EJEMPLO Coord. de calidad de Obstetricia | M36: 45670 | N36: Validado | O36: EJEMPLO Dirección de Escuela de Obstetricia | P36: 45677 | Q36: 1 | S36: EJEMPLO | V36: =IF(C36="","",IFERROR(INDEX(Catalogo!$C$5:$C$129,MATCH(C36,Catalogo!$A$5:$A$129,0)),"Código no existe")) | W36: =IF(C36="","",IFERROR(INDEX(Catalogo!$G$5:$G$129,MATCH(C36,Catalogo!$A$5:$A$129,0)),"")) | X36: =IF(C36="","",IF(ISNUMBER(F36),F36,IF(AND(ISNUMBER(D36),ISNUMBER(E36),E36>0),D36/E36*IF(W36="%",100,1),IF(ISNUMBER(D36),D36,"")))) | Y36: =IF(C36="","",IF(A36="","Falta periodo",IF(COUNTIF(Listas!$A$2:$A$134,A36)=0,"Periodo no válido",IF(X36="","Falta valor",IF(I36="","Falta fuente: no se mostrará",IF(AND(J36="",K36=""),"Sin evidencia",IF(N36<>"Validado","Sin validar","OK")))))))
A37: 2025 | C37: ID13 | D37: 24 | E37: 320 | I37: EJEMPLO Encuesta o registro de la escuela, periodo 2025 | J37: EV35 | K37: EJEMPLO_ID13_2025.pdf | L37: EJEMPLO Coord. de calidad de Obstetricia | M37: 46030 | N37: Validado | O37: EJEMPLO Dirección de Escuela de Obstetricia | P37: 46032 | Q37: 1 | S37: EJEMPLO | V37: =IF(C37="","",IFERROR(INDEX(Catalogo!$C$5:$C$129,MATCH(C37,Catalogo!$A$5:$A$129,0)),"Código no existe")) | W37: =IF(C37="","",IFERROR(INDEX(Catalogo!$G$5:$G$129,MATCH(C37,Catalogo!$A$5:$A$129,0)),"")) | X37: =IF(C37="","",IF(ISNUMBER(F37),F37,IF(AND(ISNUMBER(D37),ISNUMBER(E37),E37>0),D37/E37*IF(W37="%",100,1),IF(ISNUMBER(D37),D37,"")))) | Y37: =IF(C37="","",IF(A37="","Falta periodo",IF(COUNTIF(Listas!$A$2:$A$134,A37)=0,"Periodo no válido",IF(X37="","Falta valor",IF(I37="","Falta fuente: no se mostrará",IF(AND(J37="",K37=""),"Sin evidencia",IF(N37<>"Validado","Sin validar","OK")))))))
A38: 2023 | C38: ID14 | D38: 48 | E38: 210 | I38: EJEMPLO Encuesta o registro de la escuela, periodo 2023 | J38: EV13 | K38: EJEMPLO_ID14_2023.pdf | L38: EJEMPLO Coord. de calidad de Obstetricia | M38: 45300 | N38: Validado | O38: EJEMPLO Dirección de Escuela de Obstetricia | P38: 45305 | Q38: 1 | S38: EJEMPLO | V38: =IF(C38="","",IFERROR(INDEX(Catalogo!$C$5:$C$129,MATCH(C38,Catalogo!$A$5:$A$129,0)),"Código no existe")) | W38: =IF(C38="","",IFERROR(INDEX(Catalogo!$G$5:$G$129,MATCH(C38,Catalogo!$A$5:$A$129,0)),"")) | X38: =IF(C38="","",IF(ISNUMBER(F38),F38,IF(AND(ISNUMBER(D38),ISNUMBER(E38),E38>0),D38/E38*IF(W38="%",100,1),IF(ISNUMBER(D38),D38,"")))) | Y38: =IF(C38="","",IF(A38="","Falta periodo",IF(COUNTIF(Listas!$A$2:$A$134,A38)=0,"Periodo no válido",IF(X38="","Falta valor",IF(I38="","Falta fuente: no se mostrará",IF(AND(J38="",K38=""),"Sin evidencia",IF(N38<>"Validado","Sin validar","OK")))))))
A39: 2024 | C39: ID14 | D39: 11 | E39: 48 | I39: EJEMPLO Encuesta o registro de la escuela, periodo 2024 | J39: EV35 | K39: EJEMPLO_ID14_2024.pdf | L39: EJEMPLO Coord. de calidad de Obstetricia | M39: 45675 | N39: Validado | O39: EJEMPLO Dirección de Escuela de Obstetricia | P39: 45678 | Q39: 1 | S39: EJEMPLO | V39: =IF(C39="","",IFERROR(INDEX(Catalogo!$C$5:$C$129,MATCH(C39,Catalogo!$A$5:$A$129,0)),"Código no existe")) | W39: =IF(C39="","",IFERROR(INDEX(Catalogo!$G$5:$G$129,MATCH(C39,Catalogo!$A$5:$A$129,0)),"")) | X39: =IF(C39="","",IF(ISNUMBER(F39),F39,IF(AND(ISNUMBER(D39),ISNUMBER(E39),E39>0),D39/E39*IF(W39="%",100,1),IF(ISNUMBER(D39),D39,"")))) | Y39: =IF(C39="","",IF(A39="","Falta periodo",IF(COUNTIF(Listas!$A$2:$A$134,A39)=0,"Periodo no válido",IF(X39="","Falta valor",IF(I39="","Falta fuente: no se mostrará",IF(AND(J39="",K39=""),"Sin evidencia",IF(N39<>"Validado","Sin validar","OK")))))))
A40: 2025 | C40: ID14 | D40: 18 | E40: 85 | I40: EJEMPLO Encuesta o registro de la escuela, periodo 2025 | J40: EV21 | K40: EJEMPLO_ID14_2025.pdf | L40: EJEMPLO Coord. de calidad de Obstetricia | M40: 46029 | N40: Validado | O40: EJEMPLO Dirección de Escuela de Obstetricia | P40: 46030 | Q40: 1 | S40: EJEMPLO | V40: =IF(C40="","",IFERROR(INDEX(Catalogo!$C$5:$C$129,MATCH(C40,Catalogo!$A$5:$A$129,0)),"Código no existe")) | W40: =IF(C40="","",IFERROR(INDEX(Catalogo!$G$5:$G$129,MATCH(C40,Catalogo!$A$5:$A$129,0)),"")) | X40: =IF(C40="","",IF(ISNUMBER(F40),F40,IF(AND(ISNUMBER(D40),ISNUMBER(E40),E40>0),D40/E40*IF(W40="%",100,1),IF(ISNUMBER(D40),D40,"")))) | Y40: =IF(C40="","",IF(A40="","Falta periodo",IF(COUNTIF(Listas!$A$2:$A$134,A40)=0,"Periodo no válido",IF(X40="","Falta valor",IF(I40="","Falta fuente: no se mostrará",IF(AND(J40="",K40=""),"Sin evidencia",IF(N40<>"Validado","Sin validar","OK")))))))
A41: 2023 | C41: ID16 | D41: 32 | E41: 60 | I41: EJEMPLO Encuesta o registro de la escuela, periodo 2023 | J41: EV42 | K41: EJEMPLO_ID16_2023.pdf | L41: EJEMPLO Coord. de calidad de Obstetricia | M41: 45319 | N41: Validado | O41: EJEMPLO Dirección de Escuela de Obstetricia | P41: 45327 | Q41: 1 | S41: EJEMPLO | V41: =IF(C41="","",IFERROR(INDEX(Catalogo!$C$5:$C$129,MATCH(C41,Catalogo!$A$5:$A$129,0)),"Código no existe")) | W41: =IF(C41="","",IFERROR(INDEX(Catalogo!$G$5:$G$129,MATCH(C41,Catalogo!$A$5:$A$129,0)),"")) | X41: =IF(C41="","",IF(ISNUMBER(F41),F41,IF(AND(ISNUMBER(D41),ISNUMBER(E41),E41>0),D41/E41*IF(W41="%",100,1),IF(ISNUMBER(D41),D41,"")))) | Y41: =IF(C41="","",IF(A41="","Falta periodo",IF(COUNTIF(Listas!$A$2:$A$134,A41)=0,"Periodo no válido",IF(X41="","Falta valor",IF(I41="","Falta fuente: no se mostrará",IF(AND(J41="",K41=""),"Sin evidencia",IF(N41<>"Validado","Sin validar","OK")))))))
A42: 2024 | C42: ID16 | D42: 32 | E42: 60 | I42: EJEMPLO Encuesta o registro de la escuela, periodo 2024 | L42: EJEMPLO Coord. de calidad de Obstetricia | M42: 45673 | N42: Validado | O42: EJEMPLO Dirección de Escuela de Obstetricia | P42: 45677 | Q42: 1 | S42: EJEMPLO | V42: =IF(C42="","",IFERROR(INDEX(Catalogo!$C$5:$C$129,MATCH(C42,Catalogo!$A$5:$A$129,0)),"Código no existe")) | W42: =IF(C42="","",IFERROR(INDEX(Catalogo!$G$5:$G$129,MATCH(C42,Catalogo!$A$5:$A$129,0)),"")) | X42: =IF(C42="","",IF(ISNUMBER(F42),F42,IF(AND(ISNUMBER(D42),ISNUMBER(E42),E42>0),D42/E42*IF(W42="%",100,1),IF(ISNUMBER(D42),D42,"")))) | Y42: =IF(C42="","",IF(A42="","Falta periodo",IF(COUNTIF(Listas!$A$2:$A$134,A42)=0,"Periodo no válido",IF(X42="","Falta valor",IF(I42="","Falta fuente: no se mostrará",IF(AND(J42="",K42=""),"Sin evidencia",IF(N42<>"Validado","Sin validar","OK")))))))
A43: 2025 | C43: ID16 | D43: 161 | E43: 320 | I43: EJEMPLO Encuesta o registro de la escuela, periodo 2025 | J43: EV21 | K43: EJEMPLO_ID16_2025.pdf | L43: EJEMPLO Coord. de calidad de Obstetricia | M43: 46043 | N43: Validado | O43: EJEMPLO Dirección de Escuela de Obstetricia | P43: 46048 | Q43: 1 | S43: EJEMPLO | V43: =IF(C43="","",IFERROR(INDEX(Catalogo!$C$5:$C$129,MATCH(C43,Catalogo!$A$5:$A$129,0)),"Código no existe")) | W43: =IF(C43="","",IFERROR(INDEX(Catalogo!$G$5:$G$129,MATCH(C43,Catalogo!$A$5:$A$129,0)),"")) | X43: =IF(C43="","",IF(ISNUMBER(F43),F43,IF(AND(ISNUMBER(D43),ISNUMBER(E43),E43>0),D43/E43*IF(W43="%",100,1),IF(ISNUMBER(D43),D43,"")))) | Y43: =IF(C43="","",IF(A43="","Falta periodo",IF(COUNTIF(Listas!$A$2:$A$134,A43)=0,"Periodo no válido",IF(X43="","Falta valor",IF(I43="","Falta fuente: no se mostrará",IF(AND(J43="",K43=""),"Sin evidencia",IF(N43<>"Validado","Sin validar","OK")))))))
A44: 2024-S2 | C44: ID19 | D44: 82 | E44: 120 | I44: EJEMPLO Encuesta o registro de la escuela, periodo 2024-S2 | J44: EV38 | K44: EJEMPLO_ID19_2024-S2.pdf | L44: EJEMPLO Coord. de calidad de Obstetricia | M44: 45670 | N44: Validado | O44: EJEMPLO Dirección de Escuela de Obstetricia | P44: 45674 | Q44: 1 | S44: EJEMPLO | V44: =IF(C44="","",IFERROR(INDEX(Catalogo!$C$5:$C$129,MATCH(C44,Catalogo!$A$5:$A$129,0)),"Código no existe")) | W44: =IF(C44="","",IFERROR(INDEX(Catalogo!$G$5:$G$129,MATCH(C44,Catalogo!$A$5:$A$129,0)),"")) | X44: =IF(C44="","",IF(ISNUMBER(F44),F44,IF(AND(ISNUMBER(D44),ISNUMBER(E44),E44>0),D44/E44*IF(W44="%",100,1),IF(ISNUMBER(D44),D44,"")))) | Y44: =IF(C44="","",IF(A44="","Falta periodo",IF(COUNTIF(Listas!$A$2:$A$134,A44)=0,"Periodo no válido",IF(X44="","Falta valor",IF(I44="","Falta fuente: no se mostrará",IF(AND(J44="",K44=""),"Sin evidencia",IF(N44<>"Validado","Sin validar","OK")))))))
A45: 2025-S1 | C45: ID19 | D45: 232 | E45: 320 | I45: EJEMPLO Encuesta o registro de la escuela, periodo 2025-S1 | L45: EJEMPLO Coord. de calidad de Obstetricia | M45: 45856 | N45: Borrador | Q45: 1 | S45: EJEMPLO | V45: =IF(C45="","",IFERROR(INDEX(Catalogo!$C$5:$C$129,MATCH(C45,Catalogo!$A$5:$A$129,0)),"Código no existe")) | W45: =IF(C45="","",IFERROR(INDEX(Catalogo!$G$5:$G$129,MATCH(C45,Catalogo!$A$5:$A$129,0)),"")) | X45: =IF(C45="","",IF(ISNUMBER(F45),F45,IF(AND(ISNUMBER(D45),ISNUMBER(E45),E45>0),D45/E45*IF(W45="%",100,1),IF(ISNUMBER(D45),D45,"")))) | Y45: =IF(C45="","",IF(A45="","Falta periodo",IF(COUNTIF(Listas!$A$2:$A$134,A45)=0,"Periodo no válido",IF(X45="","Falta valor",IF(I45="","Falta fuente: no se mostrará",IF(AND(J45="",K45=""),"Sin evidencia",IF(N45<>"Validado","Sin validar","OK")))))))
A46: 2025-S2 | C46: ID19 | D46: 32 | E46: 48 | I46: EJEMPLO Encuesta o registro de la escuela, periodo 2025-S2 | L46: EJEMPLO Coord. de calidad de Obstetricia | M46: 46049 | N46: Validado | O46: EJEMPLO Dirección de Escuela de Obstetricia | P46: 46053 | Q46: 1 | S46: EJEMPLO | V46: =IF(C46="","",IFERROR(INDEX(Catalogo!$C$5:$C$129,MATCH(C46,Catalogo!$A$5:$A$129,0)),"Código no existe")) | W46: =IF(C46="","",IFERROR(INDEX(Catalogo!$G$5:$G$129,MATCH(C46,Catalogo!$A$5:$A$129,0)),"")) | X46: =IF(C46="","",IF(ISNUMBER(F46),F46,IF(AND(ISNUMBER(D46),ISNUMBER(E46),E46>0),D46/E46*IF(W46="%",100,1),IF(ISNUMBER(D46),D46,"")))) | Y46: =IF(C46="","",IF(A46="","Falta periodo",IF(COUNTIF(Listas!$A$2:$A$134,A46)=0,"Periodo no válido",IF(X46="","Falta valor",IF(I46="","Falta fuente: no se mostrará",IF(AND(J46="",K46=""),"Sin evidencia",IF(N46<>"Validado","Sin validar","OK")))))))
A47: 2026-S1 | C47: ID19 | D47: 131 | E47: 210 | I47: EJEMPLO Encuesta o registro de la escuela, periodo 2026-S1 | J47: EV38 | K47: EJEMPLO_ID19_2026-S1.pdf | L47: EJEMPLO Coord. de calidad de Obstetricia | M47: 46217 | N47: Validado | O47: EJEMPLO Dirección de Escuela de Obstetricia | P47: 46222 | Q47: 1 | S47: EJEMPLO | V47: =IF(C47="","",IFERROR(INDEX(Catalogo!$C$5:$C$129,MATCH(C47,Catalogo!$A$5:$A$129,0)),"Código no existe")) | W47: =IF(C47="","",IFERROR(INDEX(Catalogo!$G$5:$G$129,MATCH(C47,Catalogo!$A$5:$A$129,0)),"")) | X47: =IF(C47="","",IF(ISNUMBER(F47),F47,IF(AND(ISNUMBER(D47),ISNUMBER(E47),E47>0),D47/E47*IF(W47="%",100,1),IF(ISNUMBER(D47),D47,"")))) | Y47: =IF(C47="","",IF(A47="","Falta periodo",IF(COUNTIF(Listas!$A$2:$A$134,A47)=0,"Periodo no válido",IF(X47="","Falta valor",IF(I47="","Falta fuente: no se mostrará",IF(AND(J47="",K47=""),"Sin evidencia",IF(N47<>"Validado","Sin validar","OK")))))))
A48: 2024 | C48: ID20 | D48: 31 | E48: 48 | I48: EJEMPLO Encuesta o registro de la escuela, periodo 2024 | J48: EV13 | K48: EJEMPLO_ID20_2024.pdf | L48: EJEMPLO Coord. de calidad de Obstetricia | M48: 45675 | N48: Validado | O48: EJEMPLO Dirección de Escuela de Obstetricia | P48: 45684 | Q48: 1 | S48: EJEMPLO | V48: =IF(C48="","",IFERROR(INDEX(Catalogo!$C$5:$C$129,MATCH(C48,Catalogo!$A$5:$A$129,0)),"Código no existe")) | W48: =IF(C48="","",IFERROR(INDEX(Catalogo!$G$5:$G$129,MATCH(C48,Catalogo!$A$5:$A$129,0)),"")) | X48: =IF(C48="","",IF(ISNUMBER(F48),F48,IF(AND(ISNUMBER(D48),ISNUMBER(E48),E48>0),D48/E48*IF(W48="%",100,1),IF(ISNUMBER(D48),D48,"")))) | Y48: =IF(C48="","",IF(A48="","Falta periodo",IF(COUNTIF(Listas!$A$2:$A$134,A48)=0,"Periodo no válido",IF(X48="","Falta valor",IF(I48="","Falta fuente: no se mostrará",IF(AND(J48="",K48=""),"Sin evidencia",IF(N48<>"Validado","Sin validar","OK")))))))
A49: 2025 | C49: ID20 | D49: 91 | E49: 150 | I49: EJEMPLO Encuesta o registro de la escuela, periodo 2025 | J49: EV35 | K49: EJEMPLO_ID20_2025.pdf | L49: EJEMPLO Coord. de calidad de Obstetricia | M49: 46047 | N49: Borrador | Q49: 1 | S49: EJEMPLO | V49: =IF(C49="","",IFERROR(INDEX(Catalogo!$C$5:$C$129,MATCH(C49,Catalogo!$A$5:$A$129,0)),"Código no existe")) | W49: =IF(C49="","",IFERROR(INDEX(Catalogo!$G$5:$G$129,MATCH(C49,Catalogo!$A$5:$A$129,0)),"")) | X49: =IF(C49="","",IF(ISNUMBER(F49),F49,IF(AND(ISNUMBER(D49),ISNUMBER(E49),E49>0),D49/E49*IF(W49="%",100,1),IF(ISNUMBER(D49),D49,"")))) | Y49: =IF(C49="","",IF(A49="","Falta periodo",IF(COUNTIF(Listas!$A$2:$A$134,A49)=0,"Periodo no válido",IF(X49="","Falta valor",IF(I49="","Falta fuente: no se mostrará",IF(AND(J49="",K49=""),"Sin evidencia",IF(N49<>"Validado","Sin validar","OK")))))))
A50: 2023 | C50: ID21 | D50: 38 | E50: 60 | I50: EJEMPLO Encuesta o registro de la escuela, periodo 2023 | J50: EV35 | K50: EJEMPLO_ID21_2023.pdf | L50: EJEMPLO Coord. de calidad de Obstetricia | M50: 45316 | N50: Validado | O50: EJEMPLO Dirección de Escuela de Obstetricia | P50: 45322 | Q50: 1 | S50: EJEMPLO | V50: =IF(C50="","",IFERROR(INDEX(Catalogo!$C$5:$C$129,MATCH(C50,Catalogo!$A$5:$A$129,0)),"Código no existe")) | W50: =IF(C50="","",IFERROR(INDEX(Catalogo!$G$5:$G$129,MATCH(C50,Catalogo!$A$5:$A$129,0)),"")) | X50: =IF(C50="","",IF(ISNUMBER(F50),F50,IF(AND(ISNUMBER(D50),ISNUMBER(E50),E50>0),D50/E50*IF(W50="%",100,1),IF(ISNUMBER(D50),D50,"")))) | Y50: =IF(C50="","",IF(A50="","Falta periodo",IF(COUNTIF(Listas!$A$2:$A$134,A50)=0,"Periodo no válido",IF(X50="","Falta valor",IF(I50="","Falta fuente: no se mostrará",IF(AND(J50="",K50=""),"Sin evidencia",IF(N50<>"Validado","Sin validar","OK")))))))
A51: 2024 | C51: ID21 | D51: 86 | E51: 150 | I51: EJEMPLO Encuesta o registro de la escuela, periodo 2024 | J51: EV42 | K51: EJEMPLO_ID21_2024.pdf | L51: EJEMPLO Coord. de calidad de Obstetricia | M51: 45684 | N51: Validado | O51: EJEMPLO Dirección de Escuela de Obstetricia | P51: 45691 | Q51: 1 | S51: EJEMPLO | V51: =IF(C51="","",IFERROR(INDEX(Catalogo!$C$5:$C$129,MATCH(C51,Catalogo!$A$5:$A$129,0)),"Código no existe")) | W51: =IF(C51="","",IFERROR(INDEX(Catalogo!$G$5:$G$129,MATCH(C51,Catalogo!$A$5:$A$129,0)),"")) | X51: =IF(C51="","",IF(ISNUMBER(F51),F51,IF(AND(ISNUMBER(D51),ISNUMBER(E51),E51>0),D51/E51*IF(W51="%",100,1),IF(ISNUMBER(D51),D51,"")))) | Y51: =IF(C51="","",IF(A51="","Falta periodo",IF(COUNTIF(Listas!$A$2:$A$134,A51)=0,"Periodo no válido",IF(X51="","Falta valor",IF(I51="","Falta fuente: no se mostrará",IF(AND(J51="",K51=""),"Sin evidencia",IF(N51<>"Validado","Sin validar","OK")))))))
A52: 2025 | C52: ID21 | D52: 36 | E52: 60 | I52: EJEMPLO Encuesta o registro de la escuela, periodo 2025 | J52: EV38 | K52: EJEMPLO_ID21_2025.pdf | L52: EJEMPLO Coord. de calidad de Obstetricia | M52: 46032 | N52: Borrador | Q52: 1 | S52: EJEMPLO | V52: =IF(C52="","",IFERROR(INDEX(Catalogo!$C$5:$C$129,MATCH(C52,Catalogo!$A$5:$A$129,0)),"Código no existe")) | W52: =IF(C52="","",IFERROR(INDEX(Catalogo!$G$5:$G$129,MATCH(C52,Catalogo!$A$5:$A$129,0)),"")) | X52: =IF(C52="","",IF(ISNUMBER(F52),F52,IF(AND(ISNUMBER(D52),ISNUMBER(E52),E52>0),D52/E52*IF(W52="%",100,1),IF(ISNUMBER(D52),D52,"")))) | Y52: =IF(C52="","",IF(A52="","Falta periodo",IF(COUNTIF(Listas!$A$2:$A$134,A52)=0,"Periodo no válido",IF(X52="","Falta valor",IF(I52="","Falta fuente: no se mostrará",IF(AND(J52="",K52=""),"Sin evidencia",IF(N52<>"Validado","Sin validar","OK")))))))
A53: 2024 | C53: ID22 | D53: 56 | E53: 85 | I53: EJEMPLO Encuesta o registro de la escuela, periodo 2024 | J53: EV43 | K53: EJEMPLO_ID22_2024.pdf | L53: EJEMPLO Coord. de calidad de Obstetricia | M53: 45664 | N53: Validado | O53: EJEMPLO Dirección de Escuela de Obstetricia | P53: 45665 | Q53: 1 | S53: EJEMPLO | V53: =IF(C53="","",IFERROR(INDEX(Catalogo!$C$5:$C$129,MATCH(C53,Catalogo!$A$5:$A$129,0)),"Código no existe")) | W53: =IF(C53="","",IFERROR(INDEX(Catalogo!$G$5:$G$129,MATCH(C53,Catalogo!$A$5:$A$129,0)),"")) | X53: =IF(C53="","",IF(ISNUMBER(F53),F53,IF(AND(ISNUMBER(D53),ISNUMBER(E53),E53>0),D53/E53*IF(W53="%",100,1),IF(ISNUMBER(D53),D53,"")))) | Y53: =IF(C53="","",IF(A53="","Falta periodo",IF(COUNTIF(Listas!$A$2:$A$134,A53)=0,"Periodo no válido",IF(X53="","Falta valor",IF(I53="","Falta fuente: no se mostrará",IF(AND(J53="",K53=""),"Sin evidencia",IF(N53<>"Validado","Sin validar","OK")))))))
A54: 2025 | C54: ID22 | D54: 37 | E54: 60 | I54: EJEMPLO Encuesta o registro de la escuela, periodo 2025 | J54: EV30 | K54: EJEMPLO_ID22_2025.pdf | L54: EJEMPLO Coord. de calidad de Obstetricia | M54: 46035 | N54: Validado | O54: EJEMPLO Dirección de Escuela de Obstetricia | P54: 46037 | Q54: 1 | S54: EJEMPLO | V54: =IF(C54="","",IFERROR(INDEX(Catalogo!$C$5:$C$129,MATCH(C54,Catalogo!$A$5:$A$129,0)),"Código no existe")) | W54: =IF(C54="","",IFERROR(INDEX(Catalogo!$G$5:$G$129,MATCH(C54,Catalogo!$A$5:$A$129,0)),"")) | X54: =IF(C54="","",IF(ISNUMBER(F54),F54,IF(AND(ISNUMBER(D54),ISNUMBER(E54),E54>0),D54/E54*IF(W54="%",100,1),IF(ISNUMBER(D54),D54,"")))) | Y54: =IF(C54="","",IF(A54="","Falta periodo",IF(COUNTIF(Listas!$A$2:$A$134,A54)=0,"Periodo no válido",IF(X54="","Falta valor",IF(I54="","Falta fuente: no se mostrará",IF(AND(J54="",K54=""),"Sin evidencia",IF(N54<>"Validado","Sin validar","OK")))))))
A55: 2023 | C55: ID23 | D55: 115 | E55: 150 | I55: EJEMPLO Encuesta o registro de la escuela, periodo 2023 | J55: EV30 | K55: EJEMPLO_ID23_2023.pdf | L55: EJEMPLO Coord. de calidad de Obstetricia | M55: 45308 | N55: Validado | O55: EJEMPLO Dirección de Escuela de Obstetricia | P55: 45311 | Q55: 1 | S55: EJEMPLO | V55: =IF(C55="","",IFERROR(INDEX(Catalogo!$C$5:$C$129,MATCH(C55,Catalogo!$A$5:$A$129,0)),"Código no existe")) | W55: =IF(C55="","",IFERROR(INDEX(Catalogo!$G$5:$G$129,MATCH(C55,Catalogo!$A$5:$A$129,0)),"")) | X55: =IF(C55="","",IF(ISNUMBER(F55),F55,IF(AND(ISNUMBER(D55),ISNUMBER(E55),E55>0),D55/E55*IF(W55="%",100,1),IF(ISNUMBER(D55),D55,"")))) | Y55: =IF(C55="","",IF(A55="","Falta periodo",IF(COUNTIF(Listas!$A$2:$A$134,A55)=0,"Periodo no válido",IF(X55="","Falta valor",IF(I55="","Falta fuente: no se mostrará",IF(AND(J55="",K55=""),"Sin evidencia",IF(N55<>"Validado","Sin validar","OK")))))))
A56: 2024 | C56: ID23 | D56: 162 | E56: 210 | I56: EJEMPLO Encuesta o registro de la escuela, periodo 2024 | J56: EV43 | K56: EJEMPLO_ID23_2024.pdf | L56: EJEMPLO Coord. de calidad de Obstetricia | M56: 45680 | N56: Validado | O56: EJEMPLO Dirección de Escuela de Obstetricia | P56: 45688 | Q56: 1 | S56: EJEMPLO | V56: =IF(C56="","",IFERROR(INDEX(Catalogo!$C$5:$C$129,MATCH(C56,Catalogo!$A$5:$A$129,0)),"Código no existe")) | W56: =IF(C56="","",IFERROR(INDEX(Catalogo!$G$5:$G$129,MATCH(C56,Catalogo!$A$5:$A$129,0)),"")) | X56: =IF(C56="","",IF(ISNUMBER(F56),F56,IF(AND(ISNUMBER(D56),ISNUMBER(E56),E56>0),D56/E56*IF(W56="%",100,1),IF(ISNUMBER(D56),D56,"")))) | Y56: =IF(C56="","",IF(A56="","Falta periodo",IF(COUNTIF(Listas!$A$2:$A$134,A56)=0,"Periodo no válido",IF(X56="","Falta valor",IF(I56="","Falta fuente: no se mostrará",IF(AND(J56="",K56=""),"Sin evidencia",IF(N56<>"Validado","Sin validar","OK")))))))
A57: 2025 | C57: ID23 | D57: 47 | E57: 60 | I57: EJEMPLO Encuesta o registro de la escuela, periodo 2025 | J57: EV21 | K57: EJEMPLO_ID23_2025.pdf | L57: EJEMPLO Coord. de calidad de Obstetricia | M57: 46030 | N57: Borrador | Q57: 1 | S57: EJEMPLO | V57: =IF(C57="","",IFERROR(INDEX(Catalogo!$C$5:$C$129,MATCH(C57,Catalogo!$A$5:$A$129,0)),"Código no existe")) | W57: =IF(C57="","",IFERROR(INDEX(Catalogo!$G$5:$G$129,MATCH(C57,Catalogo!$A$5:$A$129,0)),"")) | X57: =IF(C57="","",IF(ISNUMBER(F57),F57,IF(AND(ISNUMBER(D57),ISNUMBER(E57),E57>0),D57/E57*IF(W57="%",100,1),IF(ISNUMBER(D57),D57,"")))) | Y57: =IF(C57="","",IF(A57="","Falta periodo",IF(COUNTIF(Listas!$A$2:$A$134,A57)=0,"Periodo no válido",IF(X57="","Falta valor",IF(I57="","Falta fuente: no se mostrará",IF(AND(J57="",K57=""),"Sin evidencia",IF(N57<>"Validado","Sin validar","OK")))))))
A58: 2023 | C58: ID24 | D58: 34 | E58: 48 | I58: EJEMPLO Encuesta o registro de la escuela, periodo 2023 | J58: EV30 | K58: EJEMPLO_ID24_2023.pdf | L58: EJEMPLO Coord. de calidad de Obstetricia | M58: 45317 | N58: Validado | O58: EJEMPLO Dirección de Escuela de Obstetricia | P58: 45319 | Q58: 1 | S58: EJEMPLO | V58: =IF(C58="","",IFERROR(INDEX(Catalogo!$C$5:$C$129,MATCH(C58,Catalogo!$A$5:$A$129,0)),"Código no existe")) | W58: =IF(C58="","",IFERROR(INDEX(Catalogo!$G$5:$G$129,MATCH(C58,Catalogo!$A$5:$A$129,0)),"")) | X58: =IF(C58="","",IF(ISNUMBER(F58),F58,IF(AND(ISNUMBER(D58),ISNUMBER(E58),E58>0),D58/E58*IF(W58="%",100,1),IF(ISNUMBER(D58),D58,"")))) | Y58: =IF(C58="","",IF(A58="","Falta periodo",IF(COUNTIF(Listas!$A$2:$A$134,A58)=0,"Periodo no válido",IF(X58="","Falta valor",IF(I58="","Falta fuente: no se mostrará",IF(AND(J58="",K58=""),"Sin evidencia",IF(N58<>"Validado","Sin validar","OK")))))))
A59: 2024 | C59: ID24 | D59: 62 | E59: 85 | I59: EJEMPLO Encuesta o registro de la escuela, periodo 2024 | J59: EV21 | K59: EJEMPLO_ID24_2024.pdf | L59: EJEMPLO Coord. de calidad de Obstetricia | M59: 45674 | N59: Validado | O59: EJEMPLO Dirección de Escuela de Obstetricia | P59: 45678 | Q59: 1 | S59: EJEMPLO | V59: =IF(C59="","",IFERROR(INDEX(Catalogo!$C$5:$C$129,MATCH(C59,Catalogo!$A$5:$A$129,0)),"Código no existe")) | W59: =IF(C59="","",IFERROR(INDEX(Catalogo!$G$5:$G$129,MATCH(C59,Catalogo!$A$5:$A$129,0)),"")) | X59: =IF(C59="","",IF(ISNUMBER(F59),F59,IF(AND(ISNUMBER(D59),ISNUMBER(E59),E59>0),D59/E59*IF(W59="%",100,1),IF(ISNUMBER(D59),D59,"")))) | Y59: =IF(C59="","",IF(A59="","Falta periodo",IF(COUNTIF(Listas!$A$2:$A$134,A59)=0,"Periodo no válido",IF(X59="","Falta valor",IF(I59="","Falta fuente: no se mostrará",IF(AND(J59="",K59=""),"Sin evidencia",IF(N59<>"Validado","Sin validar","OK")))))))
A60: 2025 | C60: ID24 | D60: 104 | E60: 150 | I60: EJEMPLO Encuesta o registro de la escuela, periodo 2025 | J60: EV38 | K60: EJEMPLO_ID24_2025.pdf | L60: EJEMPLO Coord. de calidad de Obstetricia | M60: 46034 | N60: Validado | O60: EJEMPLO Dirección de Escuela de Obstetricia | P60: 46039 | Q60: 1 | S60: EJEMPLO | V60: =IF(C60="","",IFERROR(INDEX(Catalogo!$C$5:$C$129,MATCH(C60,Catalogo!$A$5:$A$129,0)),"Código no existe")) | W60: =IF(C60="","",IFERROR(INDEX(Catalogo!$G$5:$G$129,MATCH(C60,Catalogo!$A$5:$A$129,0)),"")) | X60: =IF(C60="","",IF(ISNUMBER(F60),F60,IF(AND(ISNUMBER(D60),ISNUMBER(E60),E60>0),D60/E60*IF(W60="%",100,1),IF(ISNUMBER(D60),D60,"")))) | Y60: =IF(C60="","",IF(A60="","Falta periodo",IF(COUNTIF(Listas!$A$2:$A$134,A60)=0,"Periodo no válido",IF(X60="","Falta valor",IF(I60="","Falta fuente: no se mostrará",IF(AND(J60="",K60=""),"Sin evidencia",IF(N60<>"Validado","Sin validar","OK")))))))
A61: 2023 | C61: ID25 | F61: 2.99 | I61: EJEMPLO Encuesta o registro de la escuela, periodo 2023 | J61: EV42 | K61: EJEMPLO_ID25_2023.pdf | L61: EJEMPLO Coord. de calidad de Obstetricia | M61: 45307 | N61: Validado | O61: EJEMPLO Dirección de Escuela de Obstetricia | P61: 45308 | Q61: 1 | S61: EJEMPLO | V61: =IF(C61="","",IFERROR(INDEX(Catalogo!$C$5:$C$129,MATCH(C61,Catalogo!$A$5:$A$129,0)),"Código no existe")) | W61: =IF(C61="","",IFERROR(INDEX(Catalogo!$G$5:$G$129,MATCH(C61,Catalogo!$A$5:$A$129,0)),"")) | X61: =IF(C61="","",IF(ISNUMBER(F61),F61,IF(AND(ISNUMBER(D61),ISNUMBER(E61),E61>0),D61/E61*IF(W61="%",100,1),IF(ISNUMBER(D61),D61,"")))) | Y61: =IF(C61="","",IF(A61="","Falta periodo",IF(COUNTIF(Listas!$A$2:$A$134,A61)=0,"Periodo no válido",IF(X61="","Falta valor",IF(I61="","Falta fuente: no se mostrará",IF(AND(J61="",K61=""),"Sin evidencia",IF(N61<>"Validado","Sin validar","OK")))))))
A62: 2024 | C62: ID25 | F62: 2.8 | I62: EJEMPLO Encuesta o registro de la escuela, periodo 2024 | J62: EV42 | K62: EJEMPLO_ID25_2024.pdf | L62: EJEMPLO Coord. de calidad de Obstetricia | M62: 45675 | N62: Borrador | Q62: 1 | S62: EJEMPLO | V62: =IF(C62="","",IFERROR(INDEX(Catalogo!$C$5:$C$129,MATCH(C62,Catalogo!$A$5:$A$129,0)),"Código no existe")) | W62: =IF(C62="","",IFERROR(INDEX(Catalogo!$G$5:$G$129,MATCH(C62,Catalogo!$A$5:$A$129,0)),"")) | X62: =IF(C62="","",IF(ISNUMBER(F62),F62,IF(AND(ISNUMBER(D62),ISNUMBER(E62),E62>0),D62/E62*IF(W62="%",100,1),IF(ISNUMBER(D62),D62,"")))) | Y62: =IF(C62="","",IF(A62="","Falta periodo",IF(COUNTIF(Listas!$A$2:$A$134,A62)=0,"Periodo no válido",IF(X62="","Falta valor",IF(I62="","Falta fuente: no se mostrará",IF(AND(J62="",K62=""),"Sin evidencia",IF(N62<>"Validado","Sin validar","OK")))))))
A63: 2025 | C63: ID25 | F63: 2.89 | I63: EJEMPLO Encuesta o registro de la escuela, periodo 2025 | J63: EV30 | K63: EJEMPLO_ID25_2025.pdf | L63: EJEMPLO Coord. de calidad de Obstetricia | M63: 46043 | N63: Validado | O63: EJEMPLO Dirección de Escuela de Obstetricia | P63: 46047 | Q63: 1 | S63: EJEMPLO | V63: =IF(C63="","",IFERROR(INDEX(Catalogo!$C$5:$C$129,MATCH(C63,Catalogo!$A$5:$A$129,0)),"Código no existe")) | W63: =IF(C63="","",IFERROR(INDEX(Catalogo!$G$5:$G$129,MATCH(C63,Catalogo!$A$5:$A$129,0)),"")) | X63: =IF(C63="","",IF(ISNUMBER(F63),F63,IF(AND(ISNUMBER(D63),ISNUMBER(E63),E63>0),D63/E63*IF(W63="%",100,1),IF(ISNUMBER(D63),D63,"")))) | Y63: =IF(C63="","",IF(A63="","Falta periodo",IF(COUNTIF(Listas!$A$2:$A$134,A63)=0,"Periodo no válido",IF(X63="","Falta valor",IF(I63="","Falta fuente: no se mostrará",IF(AND(J63="",K63=""),"Sin evidencia",IF(N63<>"Validado","Sin validar","OK")))))))
A64: 2023 | C64: ID26 | F64: 1.11 | I64: EJEMPLO Encuesta o registro de la escuela, periodo 2023 | L64: EJEMPLO Coord. de calidad de Obstetricia | M64: 45307 | N64: Validado | O64: EJEMPLO Dirección de Escuela de Obstetricia | P64: 45309 | Q64: 1 | S64: EJEMPLO | V64: =IF(C64="","",IFERROR(INDEX(Catalogo!$C$5:$C$129,MATCH(C64,Catalogo!$A$5:$A$129,0)),"Código no existe")) | W64: =IF(C64="","",IFERROR(INDEX(Catalogo!$G$5:$G$129,MATCH(C64,Catalogo!$A$5:$A$129,0)),"")) | X64: =IF(C64="","",IF(ISNUMBER(F64),F64,IF(AND(ISNUMBER(D64),ISNUMBER(E64),E64>0),D64/E64*IF(W64="%",100,1),IF(ISNUMBER(D64),D64,"")))) | Y64: =IF(C64="","",IF(A64="","Falta periodo",IF(COUNTIF(Listas!$A$2:$A$134,A64)=0,"Periodo no válido",IF(X64="","Falta valor",IF(I64="","Falta fuente: no se mostrará",IF(AND(J64="",K64=""),"Sin evidencia",IF(N64<>"Validado","Sin validar","OK")))))))
A65: 2024 | C65: ID26 | F65: 1.02 | I65: EJEMPLO Encuesta o registro de la escuela, periodo 2024 | J65: EV43 | K65: EJEMPLO_ID26_2024.pdf | L65: EJEMPLO Coord. de calidad de Obstetricia | M65: 45672 | N65: Validado | O65: EJEMPLO Dirección de Escuela de Obstetricia | P65: 45677 | Q65: 1 | S65: EJEMPLO | V65: =IF(C65="","",IFERROR(INDEX(Catalogo!$C$5:$C$129,MATCH(C65,Catalogo!$A$5:$A$129,0)),"Código no existe")) | W65: =IF(C65="","",IFERROR(INDEX(Catalogo!$G$5:$G$129,MATCH(C65,Catalogo!$A$5:$A$129,0)),"")) | X65: =IF(C65="","",IF(ISNUMBER(F65),F65,IF(AND(ISNUMBER(D65),ISNUMBER(E65),E65>0),D65/E65*IF(W65="%",100,1),IF(ISNUMBER(D65),D65,"")))) | Y65: =IF(C65="","",IF(A65="","Falta periodo",IF(COUNTIF(Listas!$A$2:$A$134,A65)=0,"Periodo no válido",IF(X65="","Falta valor",IF(I65="","Falta fuente: no se mostrará",IF(AND(J65="",K65=""),"Sin evidencia",IF(N65<>"Validado","Sin validar","OK")))))))
A66: 2025 | C66: ID26 | F66: 1 | I66: EJEMPLO Encuesta o registro de la escuela, periodo 2025 | J66: EV42 | K66: EJEMPLO_ID26_2025.pdf | L66: EJEMPLO Coord. de calidad de Obstetricia | M66: 46038 | N66: Validado | O66: EJEMPLO Dirección de Escuela de Obstetricia | P66: 46044 | Q66: 1 | S66: EJEMPLO | V66: =IF(C66="","",IFERROR(INDEX(Catalogo!$C$5:$C$129,MATCH(C66,Catalogo!$A$5:$A$129,0)),"Código no existe")) | W66: =IF(C66="","",IFERROR(INDEX(Catalogo!$G$5:$G$129,MATCH(C66,Catalogo!$A$5:$A$129,0)),"")) | X66: =IF(C66="","",IF(ISNUMBER(F66),F66,IF(AND(ISNUMBER(D66),ISNUMBER(E66),E66>0),D66/E66*IF(W66="%",100,1),IF(ISNUMBER(D66),D66,"")))) | Y66: =IF(C66="","",IF(A66="","Falta periodo",IF(COUNTIF(Listas!$A$2:$A$134,A66)=0,"Periodo no válido",IF(X66="","Falta valor",IF(I66="","Falta fuente: no se mostrará",IF(AND(J66="",K66=""),"Sin evidencia",IF(N66<>"Validado","Sin validar","OK")))))))
A67: 2023 | C67: ID28 | D67: 51 | E67: 85 | I67: EJEMPLO Encuesta o registro de la escuela, periodo 2023 | L67: EJEMPLO Coord. de calidad de Obstetricia | M67: 45310 | N67: Validado | O67: EJEMPLO Dirección de Escuela de Obstetricia | P67: 45314 | Q67: 1 | S67: EJEMPLO | V67: =IF(C67="","",IFERROR(INDEX(Catalogo!$C$5:$C$129,MATCH(C67,Catalogo!$A$5:$A$129,0)),"Código no existe")) | W67: =IF(C67="","",IFERROR(INDEX(Catalogo!$G$5:$G$129,MATCH(C67,Catalogo!$A$5:$A$129,0)),"")) | X67: =IF(C67="","",IF(ISNUMBER(F67),F67,IF(AND(ISNUMBER(D67),ISNUMBER(E67),E67>0),D67/E67*IF(W67="%",100,1),IF(ISNUMBER(D67),D67,"")))) | Y67: =IF(C67="","",IF(A67="","Falta periodo",IF(COUNTIF(Listas!$A$2:$A$134,A67)=0,"Periodo no válido",IF(X67="","Falta valor",IF(I67="","Falta fuente: no se mostrará",IF(AND(J67="",K67=""),"Sin evidencia",IF(N67<>"Validado","Sin validar","OK")))))))
A68: 2024 | C68: ID28 | D68: 132 | E68: 210 | I68: EJEMPLO Encuesta o registro de la escuela, periodo 2024 | J68: EV43 | K68: EJEMPLO_ID28_2024.pdf | L68: EJEMPLO Coord. de calidad de Obstetricia | M68: 45664 | N68: Validado | O68: EJEMPLO Dirección de Escuela de Obstetricia | P68: 45667 | Q68: 1 | S68: EJEMPLO | V68: =IF(C68="","",IFERROR(INDEX(Catalogo!$C$5:$C$129,MATCH(C68,Catalogo!$A$5:$A$129,0)),"Código no existe")) | W68: =IF(C68="","",IFERROR(INDEX(Catalogo!$G$5:$G$129,MATCH(C68,Catalogo!$A$5:$A$129,0)),"")) | X68: =IF(C68="","",IF(ISNUMBER(F68),F68,IF(AND(ISNUMBER(D68),ISNUMBER(E68),E68>0),D68/E68*IF(W68="%",100,1),IF(ISNUMBER(D68),D68,"")))) | Y68: =IF(C68="","",IF(A68="","Falta periodo",IF(COUNTIF(Listas!$A$2:$A$134,A68)=0,"Periodo no válido",IF(X68="","Falta valor",IF(I68="","Falta fuente: no se mostrará",IF(AND(J68="",K68=""),"Sin evidencia",IF(N68<>"Validado","Sin validar","OK")))))))
A69: 2024 | C69: ID29 | D69: 25 | E69: 48 | I69: EJEMPLO Encuesta o registro de la escuela, periodo 2024 | J69: EV41 | K69: EJEMPLO_ID29_2024.pdf | L69: EJEMPLO Coord. de calidad de Obstetricia | M69: 45668 | N69: Validado | O69: EJEMPLO Dirección de Escuela de Obstetricia | P69: 45676 | Q69: 1 | S69: EJEMPLO | V69: =IF(C69="","",IFERROR(INDEX(Catalogo!$C$5:$C$129,MATCH(C69,Catalogo!$A$5:$A$129,0)),"Código no existe")) | W69: =IF(C69="","",IFERROR(INDEX(Catalogo!$G$5:$G$129,MATCH(C69,Catalogo!$A$5:$A$129,0)),"")) | X69: =IF(C69="","",IF(ISNUMBER(F69),F69,IF(AND(ISNUMBER(D69),ISNUMBER(E69),E69>0),D69/E69*IF(W69="%",100,1),IF(ISNUMBER(D69),D69,"")))) | Y69: =IF(C69="","",IF(A69="","Falta periodo",IF(COUNTIF(Listas!$A$2:$A$134,A69)=0,"Periodo no válido",IF(X69="","Falta valor",IF(I69="","Falta fuente: no se mostrará",IF(AND(J69="",K69=""),"Sin evidencia",IF(N69<>"Validado","Sin validar","OK")))))))
A70: 2025 | C70: ID29 | D70: 102 | E70: 210 | I70: EJEMPLO Encuesta o registro de la escuela, periodo 2025 | J70: EV44 | K70: EJEMPLO_ID29_2025.pdf | L70: EJEMPLO Coord. de calidad de Obstetricia | M70: 46046 | N70: Validado | O70: EJEMPLO Dirección de Escuela de Obstetricia | P70: 46052 | Q70: 1 | S70: EJEMPLO | V70: =IF(C70="","",IFERROR(INDEX(Catalogo!$C$5:$C$129,MATCH(C70,Catalogo!$A$5:$A$129,0)),"Código no existe")) | W70: =IF(C70="","",IFERROR(INDEX(Catalogo!$G$5:$G$129,MATCH(C70,Catalogo!$A$5:$A$129,0)),"")) | X70: =IF(C70="","",IF(ISNUMBER(F70),F70,IF(AND(ISNUMBER(D70),ISNUMBER(E70),E70>0),D70/E70*IF(W70="%",100,1),IF(ISNUMBER(D70),D70,"")))) | Y70: =IF(C70="","",IF(A70="","Falta periodo",IF(COUNTIF(Listas!$A$2:$A$134,A70)=0,"Periodo no válido",IF(X70="","Falta valor",IF(I70="","Falta fuente: no se mostrará",IF(AND(J70="",K70=""),"Sin evidencia",IF(N70<>"Validado","Sin validar","OK")))))))
A71: 2023 | C71: ME04-I2 | F71: 67.44 | I71: EJEMPLO Registro del proceso ME04, periodo 2023 | J71: EV42 | K71: EJEMPLO_ME04-I2_2023.pdf | L71: EJEMPLO Coord. de calidad de Obstetricia | M71: 45311 | N71: Validado | O71: EJEMPLO Dirección de Escuela de Obstetricia | P71: 45317 | Q71: 1 | S71: EJEMPLO | V71: =IF(C71="","",IFERROR(INDEX(Catalogo!$C$5:$C$129,MATCH(C71,Catalogo!$A$5:$A$129,0)),"Código no existe")) | W71: =IF(C71="","",IFERROR(INDEX(Catalogo!$G$5:$G$129,MATCH(C71,Catalogo!$A$5:$A$129,0)),"")) | X71: =IF(C71="","",IF(ISNUMBER(F71),F71,IF(AND(ISNUMBER(D71),ISNUMBER(E71),E71>0),D71/E71*IF(W71="%",100,1),IF(ISNUMBER(D71),D71,"")))) | Y71: =IF(C71="","",IF(A71="","Falta periodo",IF(COUNTIF(Listas!$A$2:$A$134,A71)=0,"Periodo no válido",IF(X71="","Falta valor",IF(I71="","Falta fuente: no se mostrará",IF(AND(J71="",K71=""),"Sin evidencia",IF(N71<>"Validado","Sin validar","OK")))))))
A72: 2024 | C72: ME04-I2 | F72: 50.89 | I72: EJEMPLO Registro del proceso ME04, periodo 2024 | L72: EJEMPLO Coord. de calidad de Obstetricia | M72: 45674 | N72: Observado | Q72: 1 | S72: EJEMPLO | V72: =IF(C72="","",IFERROR(INDEX(Catalogo!$C$5:$C$129,MATCH(C72,Catalogo!$A$5:$A$129,0)),"Código no existe")) | W72: =IF(C72="","",IFERROR(INDEX(Catalogo!$G$5:$G$129,MATCH(C72,Catalogo!$A$5:$A$129,0)),"")) | X72: =IF(C72="","",IF(ISNUMBER(F72),F72,IF(AND(ISNUMBER(D72),ISNUMBER(E72),E72>0),D72/E72*IF(W72="%",100,1),IF(ISNUMBER(D72),D72,"")))) | Y72: =IF(C72="","",IF(A72="","Falta periodo",IF(COUNTIF(Listas!$A$2:$A$134,A72)=0,"Periodo no válido",IF(X72="","Falta valor",IF(I72="","Falta fuente: no se mostrará",IF(AND(J72="",K72=""),"Sin evidencia",IF(N72<>"Validado","Sin validar","OK")))))))
A73: 2025 | C73: ME04-I2 | F73: 72.45 | I73: EJEMPLO Registro del proceso ME04, periodo 2025 | J73: EV21 | K73: EJEMPLO_ME04-I2_2025.pdf | L73: EJEMPLO Coord. de calidad de Obstetricia | M73: 46033 | N73: Borrador | Q73: 1 | S73: EJEMPLO | V73: =IF(C73="","",IFERROR(INDEX(Catalogo!$C$5:$C$129,MATCH(C73,Catalogo!$A$5:$A$129,0)),"Código no existe")) | W73: =IF(C73="","",IFERROR(INDEX(Catalogo!$G$5:$G$129,MATCH(C73,Catalogo!$A$5:$A$129,0)),"")) | X73: =IF(C73="","",IF(ISNUMBER(F73),F73,IF(AND(ISNUMBER(D73),ISNUMBER(E73),E73>0),D73/E73*IF(W73="%",100,1),IF(ISNUMBER(D73),D73,"")))) | Y73: =IF(C73="","",IF(A73="","Falta periodo",IF(COUNTIF(Listas!$A$2:$A$134,A73)=0,"Periodo no válido",IF(X73="","Falta valor",IF(I73="","Falta fuente: no se mostrará",IF(AND(J73="",K73=""),"Sin evidencia",IF(N73<>"Validado","Sin validar","OK")))))))
A74: 2023 | C74: PE02-I3 | D74: 85 | E74: 150 | I74: EJEMPLO Registro del proceso PE02, periodo 2023 | J74: EV44 | K74: EJEMPLO_PE02-I3_2023.pdf | L74: EJEMPLO Coord. de calidad de Obstetricia | M74: 45313 | N74: Observado | Q74: 1 | S74: EJEMPLO | V74: =IF(C74="","",IFERROR(INDEX(Catalogo!$C$5:$C$129,MATCH(C74,Catalogo!$A$5:$A$129,0)),"Código no existe")) | W74: =IF(C74="","",IFERROR(INDEX(Catalogo!$G$5:$G$129,MATCH(C74,Catalogo!$A$5:$A$129,0)),"")) | X74: =IF(C74="","",IF(ISNUMBER(F74),F74,IF(AND(ISNUMBER(D74),ISNUMBER(E74),E74>0),D74/E74*IF(W74="%",100,1),IF(ISNUMBER(D74),D74,"")))) | Y74: =IF(C74="","",IF(A74="","Falta periodo",IF(COUNTIF(Listas!$A$2:$A$134,A74)=0,"Periodo no válido",IF(X74="","Falta valor",IF(I74="","Falta fuente: no se mostrará",IF(AND(J74="",K74=""),"Sin evidencia",IF(N74<>"Validado","Sin validar","OK")))))))
A75: 2024 | C75: PE02-I3 | D75: 92 | E75: 120 | I75: EJEMPLO Registro del proceso PE02, periodo 2024 | J75: EV30 | K75: EJEMPLO_PE02-I3_2024.pdf | L75: EJEMPLO Coord. de calidad de Obstetricia | M75: 45671 | N75: Validado | O75: EJEMPLO Dirección de Escuela de Obstetricia | P75: 45677 | Q75: 1 | S75: EJEMPLO | V75: =IF(C75="","",IFERROR(INDEX(Catalogo!$C$5:$C$129,MATCH(C75,Catalogo!$A$5:$A$129,0)),"Código no existe")) | W75: =IF(C75="","",IFERROR(INDEX(Catalogo!$G$5:$G$129,MATCH(C75,Catalogo!$A$5:$A$129,0)),"")) | X75: =IF(C75="","",IF(ISNUMBER(F75),F75,IF(AND(ISNUMBER(D75),ISNUMBER(E75),E75>0),D75/E75*IF(W75="%",100,1),IF(ISNUMBER(D75),D75,"")))) | Y75: =IF(C75="","",IF(A75="","Falta periodo",IF(COUNTIF(Listas!$A$2:$A$134,A75)=0,"Periodo no válido",IF(X75="","Falta valor",IF(I75="","Falta fuente: no se mostrará",IF(AND(J75="",K75=""),"Sin evidencia",IF(N75<>"Validado","Sin validar","OK")))))))
A76: 2025 | C76: PE02-I3 | F76: 58.96 | I76: EJEMPLO Registro del proceso PE02, periodo 2025 | J76: EV21 | K76: EJEMPLO_PE02-I3_2025.pdf | L76: EJEMPLO Coord. de calidad de Obstetricia | M76: 46031 | N76: Validado | O76: EJEMPLO Dirección de Escuela de Obstetricia | P76: 46036 | Q76: 1 | S76: EJEMPLO | V76: =IF(C76="","",IFERROR(INDEX(Catalogo!$C$5:$C$129,MATCH(C76,Catalogo!$A$5:$A$129,0)),"Código no existe")) | W76: =IF(C76="","",IFERROR(INDEX(Catalogo!$G$5:$G$129,MATCH(C76,Catalogo!$A$5:$A$129,0)),"")) | X76: =IF(C76="","",IF(ISNUMBER(F76),F76,IF(AND(ISNUMBER(D76),ISNUMBER(E76),E76>0),D76/E76*IF(W76="%",100,1),IF(ISNUMBER(D76),D76,"")))) | Y76: =IF(C76="","",IF(A76="","Falta periodo",IF(COUNTIF(Listas!$A$2:$A$134,A76)=0,"Periodo no válido",IF(X76="","Falta valor",IF(I76="","Falta fuente: no se mostrará",IF(AND(J76="",K76=""),"Sin evidencia",IF(N76<>"Validado","Sin validar","OK")))))))
A77: 2024 | C77: PE02-I4 | D77: 18 | E77: 85 | I77: EJEMPLO Registro del proceso PE02, periodo 2024 | J77: EV41 | K77: EJEMPLO_PE02-I4_2024.pdf | L77: EJEMPLO Coord. de calidad de Obstetricia | M77: 45664 | N77: Borrador | Q77: 1 | S77: EJEMPLO | V77: =IF(C77="","",IFERROR(INDEX(Catalogo!$C$5:$C$129,MATCH(C77,Catalogo!$A$5:$A$129,0)),"Código no existe")) | W77: =IF(C77="","",IFERROR(INDEX(Catalogo!$G$5:$G$129,MATCH(C77,Catalogo!$A$5:$A$129,0)),"")) | X77: =IF(C77="","",IF(ISNUMBER(F77),F77,IF(AND(ISNUMBER(D77),ISNUMBER(E77),E77>0),D77/E77*IF(W77="%",100,1),IF(ISNUMBER(D77),D77,"")))) | Y77: =IF(C77="","",IF(A77="","Falta periodo",IF(COUNTIF(Listas!$A$2:$A$134,A77)=0,"Periodo no válido",IF(X77="","Falta valor",IF(I77="","Falta fuente: no se mostrará",IF(AND(J77="",K77=""),"Sin evidencia",IF(N77<>"Validado","Sin validar","OK")))))))
A78: 2025 | C78: PE02-I4 | D78: 19 | E78: 85 | I78: EJEMPLO Registro del proceso PE02, periodo 2025 | J78: EV38 | K78: EJEMPLO_PE02-I4_2025.pdf | L78: EJEMPLO Coord. de calidad de Obstetricia | M78: 46041 | N78: Validado | O78: EJEMPLO Dirección de Escuela de Obstetricia | P78: 46045 | Q78: 1 | S78: EJEMPLO | V78: =IF(C78="","",IFERROR(INDEX(Catalogo!$C$5:$C$129,MATCH(C78,Catalogo!$A$5:$A$129,0)),"Código no existe")) | W78: =IF(C78="","",IFERROR(INDEX(Catalogo!$G$5:$G$129,MATCH(C78,Catalogo!$A$5:$A$129,0)),"")) | X78: =IF(C78="","",IF(ISNUMBER(F78),F78,IF(AND(ISNUMBER(D78),ISNUMBER(E78),E78>0),D78/E78*IF(W78="%",100,1),IF(ISNUMBER(D78),D78,"")))) | Y78: =IF(C78="","",IF(A78="","Falta periodo",IF(COUNTIF(Listas!$A$2:$A$134,A78)=0,"Periodo no válido",IF(X78="","Falta valor",IF(I78="","Falta fuente: no se mostrará",IF(AND(J78="",K78=""),"Sin evidencia",IF(N78<>"Validado","Sin validar","OK")))))))
A79: 2024 | C79: PE04-I1 | D79: 27 | E79: 48 | I79: EJEMPLO Registro del proceso PE04, periodo 2024 | L79: EJEMPLO Coord. de calidad de Obstetricia | M79: 45679 | N79: Observado | Q79: 1 | S79: EJEMPLO | V79: =IF(C79="","",IFERROR(INDEX(Catalogo!$C$5:$C$129,MATCH(C79,Catalogo!$A$5:$A$129,0)),"Código no existe")) | W79: =IF(C79="","",IFERROR(INDEX(Catalogo!$G$5:$G$129,MATCH(C79,Catalogo!$A$5:$A$129,0)),"")) | X79: =IF(C79="","",IF(ISNUMBER(F79),F79,IF(AND(ISNUMBER(D79),ISNUMBER(E79),E79>0),D79/E79*IF(W79="%",100,1),IF(ISNUMBER(D79),D79,"")))) | Y79: =IF(C79="","",IF(A79="","Falta periodo",IF(COUNTIF(Listas!$A$2:$A$134,A79)=0,"Periodo no válido",IF(X79="","Falta valor",IF(I79="","Falta fuente: no se mostrará",IF(AND(J79="",K79=""),"Sin evidencia",IF(N79<>"Validado","Sin validar","OK")))))))
A80: 2025 | C80: PE04-I1 | F80: 64.91 | I80: EJEMPLO Registro del proceso PE04, periodo 2025 | J80: EV13 | K80: EJEMPLO_PE04-I1_2025.pdf | L80: EJEMPLO Coord. de calidad de Obstetricia | M80: 46042 | N80: Validado | O80: EJEMPLO Dirección de Escuela de Obstetricia | P80: 46051 | Q80: 1 | S80: EJEMPLO | V80: =IF(C80="","",IFERROR(INDEX(Catalogo!$C$5:$C$129,MATCH(C80,Catalogo!$A$5:$A$129,0)),"Código no existe")) | W80: =IF(C80="","",IFERROR(INDEX(Catalogo!$G$5:$G$129,MATCH(C80,Catalogo!$A$5:$A$129,0)),"")) | X80: =IF(C80="","",IF(ISNUMBER(F80),F80,IF(AND(ISNUMBER(D80),ISNUMBER(E80),E80>0),D80/E80*IF(W80="%",100,1),IF(ISNUMBER(D80),D80,"")))) | Y80: =IF(C80="","",IF(A80="","Falta periodo",IF(COUNTIF(Listas!$A$2:$A$134,A80)=0,"Periodo no válido",IF(X80="","Falta valor",IF(I80="","Falta fuente: no se mostrará",IF(AND(J80="",K80=""),"Sin evidencia",IF(N80<>"Validado","Sin validar","OK")))))))
A81: 2024 | C81: PM01-I3 | D81: 150 | E81: 150 | I81: EJEMPLO Registro del proceso PM01, periodo 2024 | J81: EV30 | K81: EJEMPLO_PM01-I3_2024.pdf | L81: EJEMPLO Coord. de calidad de Obstetricia | M81: 45675 | N81: Validado | O81: EJEMPLO Dirección de Escuela de Obstetricia | P81: 45682 | Q81: 1 | S81: EJEMPLO | V81: =IF(C81="","",IFERROR(INDEX(Catalogo!$C$5:$C$129,MATCH(C81,Catalogo!$A$5:$A$129,0)),"Código no existe")) | W81: =IF(C81="","",IFERROR(INDEX(Catalogo!$G$5:$G$129,MATCH(C81,Catalogo!$A$5:$A$129,0)),"")) | X81: =IF(C81="","",IF(ISNUMBER(F81),F81,IF(AND(ISNUMBER(D81),ISNUMBER(E81),E81>0),D81/E81*IF(W81="%",100,1),IF(ISNUMBER(D81),D81,"")))) | Y81: =IF(C81="","",IF(A81="","Falta periodo",IF(COUNTIF(Listas!$A$2:$A$134,A81)=0,"Periodo no válido",IF(X81="","Falta valor",IF(I81="","Falta fuente: no se mostrará",IF(AND(J81="",K81=""),"Sin evidencia",IF(N81<>"Validado","Sin validar","OK")))))))
A82: 2025 | C82: PM01-I3 | D82: 320 | E82: 320 | I82: EJEMPLO Registro del proceso PM01, periodo 2025 | J82: EV21 | K82: EJEMPLO_PM01-I3_2025.pdf | L82: EJEMPLO Coord. de calidad de Obstetricia | M82: 46049 | N82: Validado | O82: EJEMPLO Dirección de Escuela de Obstetricia | P82: 46054 | Q82: 1 | S82: EJEMPLO | V82: =IF(C82="","",IFERROR(INDEX(Catalogo!$C$5:$C$129,MATCH(C82,Catalogo!$A$5:$A$129,0)),"Código no existe")) | W82: =IF(C82="","",IFERROR(INDEX(Catalogo!$G$5:$G$129,MATCH(C82,Catalogo!$A$5:$A$129,0)),"")) | X82: =IF(C82="","",IF(ISNUMBER(F82),F82,IF(AND(ISNUMBER(D82),ISNUMBER(E82),E82>0),D82/E82*IF(W82="%",100,1),IF(ISNUMBER(D82),D82,"")))) | Y82: =IF(C82="","",IF(A82="","Falta periodo",IF(COUNTIF(Listas!$A$2:$A$134,A82)=0,"Periodo no válido",IF(X82="","Falta valor",IF(I82="","Falta fuente: no se mostrará",IF(AND(J82="",K82=""),"Sin evidencia",IF(N82<>"Validado","Sin validar","OK")))))))
A83: 2024 | C83: PM03-I4 | D83: 128 | E83: 210 | I83: EJEMPLO Registro del proceso PM03, periodo 2024 | L83: EJEMPLO Coord. de calidad de Obstetricia | M83: 45675 | N83: Validado | O83: EJEMPLO Dirección de Escuela de Obstetricia | P83: 45684 | Q83: 1 | S83: EJEMPLO | V83: =IF(C83="","",IFERROR(INDEX(Catalogo!$C$5:$C$129,MATCH(C83,Catalogo!$A$5:$A$129,0)),"Código no existe")) | W83: =IF(C83="","",IFERROR(INDEX(Catalogo!$G$5:$G$129,MATCH(C83,Catalogo!$A$5:$A$129,0)),"")) | X83: =IF(C83="","",IF(ISNUMBER(F83),F83,IF(AND(ISNUMBER(D83),ISNUMBER(E83),E83>0),D83/E83*IF(W83="%",100,1),IF(ISNUMBER(D83),D83,"")))) | Y83: =IF(C83="","",IF(A83="","Falta periodo",IF(COUNTIF(Listas!$A$2:$A$134,A83)=0,"Periodo no válido",IF(X83="","Falta valor",IF(I83="","Falta fuente: no se mostrará",IF(AND(J83="",K83=""),"Sin evidencia",IF(N83<>"Validado","Sin validar","OK")))))))
A84: 2025 | C84: PM03-I4 | D84: 135 | E84: 210 | I84: EJEMPLO Registro del proceso PM03, periodo 2025 | J84: EV21 | K84: EJEMPLO_PM03-I4_2025.pdf | L84: EJEMPLO Coord. de calidad de Obstetricia | M84: 46038 | N84: Validado | O84: EJEMPLO Dirección de Escuela de Obstetricia | P84: 46045 | Q84: 1 | S84: EJEMPLO | V84: =IF(C84="","",IFERROR(INDEX(Catalogo!$C$5:$C$129,MATCH(C84,Catalogo!$A$5:$A$129,0)),"Código no existe")) | W84: =IF(C84="","",IFERROR(INDEX(Catalogo!$G$5:$G$129,MATCH(C84,Catalogo!$A$5:$A$129,0)),"")) | X84: =IF(C84="","",IF(ISNUMBER(F84),F84,IF(AND(ISNUMBER(D84),ISNUMBER(E84),E84>0),D84/E84*IF(W84="%",100,1),IF(ISNUMBER(D84),D84,"")))) | Y84: =IF(C84="","",IF(A84="","Falta periodo",IF(COUNTIF(Listas!$A$2:$A$134,A84)=0,"Periodo no válido",IF(X84="","Falta valor",IF(I84="","Falta fuente: no se mostrará",IF(AND(J84="",K84=""),"Sin evidencia",IF(N84<>"Validado","Sin validar","OK")))))))
A85: 2025-T1 | C85: PM04-I3 | F85: 74.95 | I85: EJEMPLO Registro del proceso PM04, periodo 2025-T1 | J85: EV41 | K85: EJEMPLO_PM04-I3_2025-T1.pdf | L85: EJEMPLO Coord. de calidad de Obstetricia | M85: 45758 | N85: Validado | O85: EJEMPLO Dirección de Escuela de Obstetricia | P85: 45765 | Q85: 1 | S85: EJEMPLO | V85: =IF(C85="","",IFERROR(INDEX(Catalogo!$C$5:$C$129,MATCH(C85,Catalogo!$A$5:$A$129,0)),"Código no existe")) | W85: =IF(C85="","",IFERROR(INDEX(Catalogo!$G$5:$G$129,MATCH(C85,Catalogo!$A$5:$A$129,0)),"")) | X85: =IF(C85="","",IF(ISNUMBER(F85),F85,IF(AND(ISNUMBER(D85),ISNUMBER(E85),E85>0),D85/E85*IF(W85="%",100,1),IF(ISNUMBER(D85),D85,"")))) | Y85: =IF(C85="","",IF(A85="","Falta periodo",IF(COUNTIF(Listas!$A$2:$A$134,A85)=0,"Periodo no válido",IF(X85="","Falta valor",IF(I85="","Falta fuente: no se mostrará",IF(AND(J85="",K85=""),"Sin evidencia",IF(N85<>"Validado","Sin validar","OK")))))))
A86: 2025-T2 | C86: PM04-I3 | D86: 128 | E86: 210 | I86: EJEMPLO Registro del proceso PM04, periodo 2025-T2 | J86: EV35 | K86: EJEMPLO_PM04-I3_2025-T2.pdf | L86: EJEMPLO Coord. de calidad de Obstetricia | M86: 45849 | N86: Validado | O86: EJEMPLO Dirección de Escuela de Obstetricia | P86: 45855 | Q86: 1 | S86: EJEMPLO | V86: =IF(C86="","",IFERROR(INDEX(Catalogo!$C$5:$C$129,MATCH(C86,Catalogo!$A$5:$A$129,0)),"Código no existe")) | W86: =IF(C86="","",IFERROR(INDEX(Catalogo!$G$5:$G$129,MATCH(C86,Catalogo!$A$5:$A$129,0)),"")) | X86: =IF(C86="","",IF(ISNUMBER(F86),F86,IF(AND(ISNUMBER(D86),ISNUMBER(E86),E86>0),D86/E86*IF(W86="%",100,1),IF(ISNUMBER(D86),D86,"")))) | Y86: =IF(C86="","",IF(A86="","Falta periodo",IF(COUNTIF(Listas!$A$2:$A$134,A86)=0,"Periodo no válido",IF(X86="","Falta valor",IF(I86="","Falta fuente: no se mostrará",IF(AND(J86="",K86=""),"Sin evidencia",IF(N86<>"Validado","Sin validar","OK")))))))
A87: 2025-T3 | C87: PM04-I3 | F87: 83.54 | I87: EJEMPLO Registro del proceso PM04, periodo 2025-T3 | J87: EV30 | K87: EJEMPLO_PM04-I3_2025-T3.pdf | L87: EJEMPLO Coord. de calidad de Obstetricia | M87: 45942 | N87: Validado | O87: EJEMPLO Dirección de Escuela de Obstetricia | P87: 45946 | Q87: 1 | S87: EJEMPLO | V87: =IF(C87="","",IFERROR(INDEX(Catalogo!$C$5:$C$129,MATCH(C87,Catalogo!$A$5:$A$129,0)),"Código no existe")) | W87: =IF(C87="","",IFERROR(INDEX(Catalogo!$G$5:$G$129,MATCH(C87,Catalogo!$A$5:$A$129,0)),"")) | X87: =IF(C87="","",IF(ISNUMBER(F87),F87,IF(AND(ISNUMBER(D87),ISNUMBER(E87),E87>0),D87/E87*IF(W87="%",100,1),IF(ISNUMBER(D87),D87,"")))) | Y87: =IF(C87="","",IF(A87="","Falta periodo",IF(COUNTIF(Listas!$A$2:$A$134,A87)=0,"Periodo no válido",IF(X87="","Falta valor",IF(I87="","Falta fuente: no se mostrará",IF(AND(J87="",K87=""),"Sin evidencia",IF(N87<>"Validado","Sin validar","OK")))))))
A88: 2025-T4 | C88: PM04-I3 | D88: 83 | E88: 150 | I88: EJEMPLO Registro del proceso PM04, periodo 2025-T4 | J88: EV38 | K88: EJEMPLO_PM04-I3_2025-T4.pdf | L88: EJEMPLO Coord. de calidad de Obstetricia | M88: 46043 | N88: Borrador | Q88: 1 | S88: EJEMPLO | V88: =IF(C88="","",IFERROR(INDEX(Catalogo!$C$5:$C$129,MATCH(C88,Catalogo!$A$5:$A$129,0)),"Código no existe")) | W88: =IF(C88="","",IFERROR(INDEX(Catalogo!$G$5:$G$129,MATCH(C88,Catalogo!$A$5:$A$129,0)),"")) | X88: =IF(C88="","",IF(ISNUMBER(F88),F88,IF(AND(ISNUMBER(D88),ISNUMBER(E88),E88>0),D88/E88*IF(W88="%",100,1),IF(ISNUMBER(D88),D88,"")))) | Y88: =IF(C88="","",IF(A88="","Falta periodo",IF(COUNTIF(Listas!$A$2:$A$134,A88)=0,"Periodo no válido",IF(X88="","Falta valor",IF(I88="","Falta fuente: no se mostrará",IF(AND(J88="",K88=""),"Sin evidencia",IF(N88<>"Validado","Sin validar","OK")))))))
A89: 2025-S1 | C89: ME01-I1 | F89: 22.46 | I89: EJEMPLO Registro del proceso ME01, periodo 2025-S1 | J89: EV35 | K89: EJEMPLO_ME01-I1_2025-S1.pdf | L89: EJEMPLO Coord. de calidad de Obstetricia | M89: 45850 | N89: Validado | O89: EJEMPLO Dirección de Escuela de Obstetricia | P89: 45855 | Q89: 1 | S89: EJEMPLO | V89: =IF(C89="","",IFERROR(INDEX(Catalogo!$C$5:$C$129,MATCH(C89,Catalogo!$A$5:$A$129,0)),"Código no existe")) | W89: =IF(C89="","",IFERROR(INDEX(Catalogo!$G$5:$G$129,MATCH(C89,Catalogo!$A$5:$A$129,0)),"")) | X89: =IF(C89="","",IF(ISNUMBER(F89),F89,IF(AND(ISNUMBER(D89),ISNUMBER(E89),E89>0),D89/E89*IF(W89="%",100,1),IF(ISNUMBER(D89),D89,"")))) | Y89: =IF(C89="","",IF(A89="","Falta periodo",IF(COUNTIF(Listas!$A$2:$A$134,A89)=0,"Periodo no válido",IF(X89="","Falta valor",IF(I89="","Falta fuente: no se mostrará",IF(AND(J89="",K89=""),"Sin evidencia",IF(N89<>"Validado","Sin validar","OK")))))))
A90: 2025-S2 | C90: ME01-I1 | D90: 64 | E90: 320 | I90: EJEMPLO Registro del proceso ME01, periodo 2025-S2 | J90: EV43 | K90: EJEMPLO_ME01-I1_2025-S2.pdf | L90: EJEMPLO Coord. de calidad de Obstetricia | M90: 46037 | N90: Validado | O90: EJEMPLO Dirección de Escuela de Obstetricia | P90: 46044 | Q90: 1 | S90: EJEMPLO | V90: =IF(C90="","",IFERROR(INDEX(Catalogo!$C$5:$C$129,MATCH(C90,Catalogo!$A$5:$A$129,0)),"Código no existe")) | W90: =IF(C90="","",IFERROR(INDEX(Catalogo!$G$5:$G$129,MATCH(C90,Catalogo!$A$5:$A$129,0)),"")) | X90: =IF(C90="","",IF(ISNUMBER(F90),F90,IF(AND(ISNUMBER(D90),ISNUMBER(E90),E90>0),D90/E90*IF(W90="%",100,1),IF(ISNUMBER(D90),D90,"")))) | Y90: =IF(C90="","",IF(A90="","Falta periodo",IF(COUNTIF(Listas!$A$2:$A$134,A90)=0,"Periodo no válido",IF(X90="","Falta valor",IF(I90="","Falta fuente: no se mostrará",IF(AND(J90="",K90=""),"Sin evidencia",IF(N90<>"Validado","Sin validar","OK")))))))
A91: 2026-S1 | C91: ME01-I1 | D91: 16 | E91: 85 | I91: EJEMPLO Registro del proceso ME01, periodo 2026-S1 | J91: EV41 | K91: EJEMPLO_ME01-I1_2026-S1.pdf | L91: EJEMPLO Coord. de calidad de Obstetricia | M91: 46220 | N91: Validado | O91: EJEMPLO Dirección de Escuela de Obstetricia | P91: 46221 | Q91: 1 | S91: EJEMPLO | V91: =IF(C91="","",IFERROR(INDEX(Catalogo!$C$5:$C$129,MATCH(C91,Catalogo!$A$5:$A$129,0)),"Código no existe")) | W91: =IF(C91="","",IFERROR(INDEX(Catalogo!$G$5:$G$129,MATCH(C91,Catalogo!$A$5:$A$129,0)),"")) | X91: =IF(C91="","",IF(ISNUMBER(F91),F91,IF(AND(ISNUMBER(D91),ISNUMBER(E91),E91>0),D91/E91*IF(W91="%",100,1),IF(ISNUMBER(D91),D91,"")))) | Y91: =IF(C91="","",IF(A91="","Falta periodo",IF(COUNTIF(Listas!$A$2:$A$134,A91)=0,"Periodo no válido",IF(X91="","Falta valor",IF(I91="","Falta fuente: no se mostrará",IF(AND(J91="",K91=""),"Sin evidencia",IF(N91<>"Validado","Sin validar","OK")))))))
A92: 2024 | C92: ME01-I2 | F92: 65.35 | I92: EJEMPLO Registro del proceso ME01, periodo 2024 | J92: EV13 | K92: EJEMPLO_ME01-I2_2024.pdf | L92: EJEMPLO Coord. de calidad de Obstetricia | M92: 45685 | N92: Validado | O92: EJEMPLO Dirección de Escuela de Obstetricia | P92: 45691 | Q92: 1 | S92: EJEMPLO | V92: =IF(C92="","",IFERROR(INDEX(Catalogo!$C$5:$C$129,MATCH(C92,Catalogo!$A$5:$A$129,0)),"Código no existe")) | W92: =IF(C92="","",IFERROR(INDEX(Catalogo!$G$5:$G$129,MATCH(C92,Catalogo!$A$5:$A$129,0)),"")) | X92: =IF(C92="","",IF(ISNUMBER(F92),F92,IF(AND(ISNUMBER(D92),ISNUMBER(E92),E92>0),D92/E92*IF(W92="%",100,1),IF(ISNUMBER(D92),D92,"")))) | Y92: =IF(C92="","",IF(A92="","Falta periodo",IF(COUNTIF(Listas!$A$2:$A$134,A92)=0,"Periodo no válido",IF(X92="","Falta valor",IF(I92="","Falta fuente: no se mostrará",IF(AND(J92="",K92=""),"Sin evidencia",IF(N92<>"Validado","Sin validar","OK")))))))
A93: 2025 | C93: ME01-I2 | D93: 220 | E93: 320 | I93: EJEMPLO Registro del proceso ME01, periodo 2025 | J93: EV30 | K93: EJEMPLO_ME01-I2_2025.pdf | L93: EJEMPLO Coord. de calidad de Obstetricia | M93: 46028 | N93: Observado | Q93: 1 | S93: EJEMPLO | V93: =IF(C93="","",IFERROR(INDEX(Catalogo!$C$5:$C$129,MATCH(C93,Catalogo!$A$5:$A$129,0)),"Código no existe")) | W93: =IF(C93="","",IFERROR(INDEX(Catalogo!$G$5:$G$129,MATCH(C93,Catalogo!$A$5:$A$129,0)),"")) | X93: =IF(C93="","",IF(ISNUMBER(F93),F93,IF(AND(ISNUMBER(D93),ISNUMBER(E93),E93>0),D93/E93*IF(W93="%",100,1),IF(ISNUMBER(D93),D93,"")))) | Y93: =IF(C93="","",IF(A93="","Falta periodo",IF(COUNTIF(Listas!$A$2:$A$134,A93)=0,"Periodo no válido",IF(X93="","Falta valor",IF(I93="","Falta fuente: no se mostrará",IF(AND(J93="",K93=""),"Sin evidencia",IF(N93<>"Validado","Sin validar","OK")))))))
A94: 2024 | C94: ME01-I3 | D94: 189 | E94: 210 | I94: EJEMPLO Registro del proceso ME01, periodo 2024 | J94: EV44 | K94: EJEMPLO_ME01-I3_2024.pdf | L94: EJEMPLO Coord. de calidad de Obstetricia | M94: 45684 | N94: Validado | O94: EJEMPLO Dirección de Escuela de Obstetricia | P94: 45690 | Q94: 1 | S94: EJEMPLO | V94: =IF(C94="","",IFERROR(INDEX(Catalogo!$C$5:$C$129,MATCH(C94,Catalogo!$A$5:$A$129,0)),"Código no existe")) | W94: =IF(C94="","",IFERROR(INDEX(Catalogo!$G$5:$G$129,MATCH(C94,Catalogo!$A$5:$A$129,0)),"")) | X94: =IF(C94="","",IF(ISNUMBER(F94),F94,IF(AND(ISNUMBER(D94),ISNUMBER(E94),E94>0),D94/E94*IF(W94="%",100,1),IF(ISNUMBER(D94),D94,"")))) | Y94: =IF(C94="","",IF(A94="","Falta periodo",IF(COUNTIF(Listas!$A$2:$A$134,A94)=0,"Periodo no válido",IF(X94="","Falta valor",IF(I94="","Falta fuente: no se mostrará",IF(AND(J94="",K94=""),"Sin evidencia",IF(N94<>"Validado","Sin validar","OK")))))))
A95: 2025 | C95: ME01-I3 | D95: 147 | E95: 320 | I95: EJEMPLO Registro del proceso ME01, periodo 2025 | J95: EV35 | K95: EJEMPLO_ME01-I3_2025.pdf | L95: EJEMPLO Coord. de calidad de Obstetricia | M95: 46045 | N95: Validado | O95: EJEMPLO Dirección de Escuela de Obstetricia | P95: 46046 | Q95: 1 | S95: EJEMPLO | V95: =IF(C95="","",IFERROR(INDEX(Catalogo!$C$5:$C$129,MATCH(C95,Catalogo!$A$5:$A$129,0)),"Código no existe")) | W95: =IF(C95="","",IFERROR(INDEX(Catalogo!$G$5:$G$129,MATCH(C95,Catalogo!$A$5:$A$129,0)),"")) | X95: =IF(C95="","",IF(ISNUMBER(F95),F95,IF(AND(ISNUMBER(D95),ISNUMBER(E95),E95>0),D95/E95*IF(W95="%",100,1),IF(ISNUMBER(D95),D95,"")))) | Y95: =IF(C95="","",IF(A95="","Falta periodo",IF(COUNTIF(Listas!$A$2:$A$134,A95)=0,"Periodo no válido",IF(X95="","Falta valor",IF(I95="","Falta fuente: no se mostrará",IF(AND(J95="",K95=""),"Sin evidencia",IF(N95<>"Validado","Sin validar","OK")))))))
A96: 2025-S2 | C96: ME03-I1 | F96: 80.89 | I96: EJEMPLO Registro del proceso ME03, periodo 2025-S2 | L96: EJEMPLO Coord. de calidad de Obstetricia | M96: 46049 | N96: Observado | Q96: 1 | S96: EJEMPLO | V96: =IF(C96="","",IFERROR(INDEX(Catalogo!$C$5:$C$129,MATCH(C96,Catalogo!$A$5:$A$129,0)),"Código no existe")) | W96: =IF(C96="","",IFERROR(INDEX(Catalogo!$G$5:$G$129,MATCH(C96,Catalogo!$A$5:$A$129,0)),"")) | X96: =IF(C96="","",IF(ISNUMBER(F96),F96,IF(AND(ISNUMBER(D96),ISNUMBER(E96),E96>0),D96/E96*IF(W96="%",100,1),IF(ISNUMBER(D96),D96,"")))) | Y96: =IF(C96="","",IF(A96="","Falta periodo",IF(COUNTIF(Listas!$A$2:$A$134,A96)=0,"Periodo no válido",IF(X96="","Falta valor",IF(I96="","Falta fuente: no se mostrará",IF(AND(J96="",K96=""),"Sin evidencia",IF(N96<>"Validado","Sin validar","OK")))))))
A97: 2026-S1 | C97: ME03-I1 | D97: 136 | E97: 150 | I97: EJEMPLO Registro del proceso ME03, periodo 2026-S1 | J97: EV21 | K97: EJEMPLO_ME03-I1_2026-S1.pdf | L97: EJEMPLO Coord. de calidad de Obstetricia | M97: 46215 | N97: Validado | O97: EJEMPLO Dirección de Escuela de Obstetricia | P97: 46221 | Q97: 1 | S97: EJEMPLO | V97: =IF(C97="","",IFERROR(INDEX(Catalogo!$C$5:$C$129,MATCH(C97,Catalogo!$A$5:$A$129,0)),"Código no existe")) | W97: =IF(C97="","",IFERROR(INDEX(Catalogo!$G$5:$G$129,MATCH(C97,Catalogo!$A$5:$A$129,0)),"")) | X97: =IF(C97="","",IF(ISNUMBER(F97),F97,IF(AND(ISNUMBER(D97),ISNUMBER(E97),E97>0),D97/E97*IF(W97="%",100,1),IF(ISNUMBER(D97),D97,"")))) | Y97: =IF(C97="","",IF(A97="","Falta periodo",IF(COUNTIF(Listas!$A$2:$A$134,A97)=0,"Periodo no válido",IF(X97="","Falta valor",IF(I97="","Falta fuente: no se mostrará",IF(AND(J97="",K97=""),"Sin evidencia",IF(N97<>"Validado","Sin validar","OK")))))))
A98: 2025 | C98: ID7 | F98: 61 | L98: EJEMPLO Coord. de calidad de Obstetricia | M98: 46266 | N98: Borrador | Q98: 1 | R98: EJEMPLO: fila sin fuente, no debe mostrarse | S98: EJEMPLO | V98: =IF(C98="","",IFERROR(INDEX(Catalogo!$C$5:$C$129,MATCH(C98,Catalogo!$A$5:$A$129,0)),"Código no existe")) | W98: =IF(C98="","",IFERROR(INDEX(Catalogo!$G$5:$G$129,MATCH(C98,Catalogo!$A$5:$A$129,0)),"")) | X98: =IF(C98="","",IF(ISNUMBER(F98),F98,IF(AND(ISNUMBER(D98),ISNUMBER(E98),E98>0),D98/E98*IF(W98="%",100,1),IF(ISNUMBER(D98),D98,"")))) | Y98: =IF(C98="","",IF(A98="","Falta periodo",IF(COUNTIF(Listas!$A$2:$A$134,A98)=0,"Periodo no válido",IF(X98="","Falta valor",IF(I98="","Falta fuente: no se mostrará",IF(AND(J98="",K98=""),"Sin evidencia",IF(N98<>"Validado","Sin validar","OK")))))))
V99: =IF(C99="","",IFERROR(INDEX(Catalogo!$C$5:$C$129,MATCH(C99,Catalogo!$A$5:$A$129,0)),"Código no existe")) | W99: =IF(C99="","",IFERROR(INDEX(Catalogo!$G$5:$G$129,MATCH(C99,Catalogo!$A$5:$A$129,0)),"")) | X99: =IF(C99="","",IF(ISNUMBER(F99),F99,IF(AND(ISNUMBER(D99),ISNUMBER(E99),E99>0),D99/E99*IF(W99="%",100,1),IF(ISNUMBER(D99),D99,"")))) | Y99: =IF(C99="","",IF(A99="","Falta periodo",IF(COUNTIF(Listas!$A$2:$A$134,A99)=0,"Periodo no válido",IF(X99="","Falta valor",IF(I99="","Falta fuente: no se mostrará",IF(AND(J99="",K99=""),"Sin evidencia",IF(N99<>"Validado","Sin validar","OK")))))))
V100: =IF(C100="","",IFERROR(INDEX(Catalogo!$C$5:$C$129,MATCH(C100,Catalogo!$A$5:$A$129,0)),"Código no existe")) | W100: =IF(C100="","",IFERROR(INDEX(Catalogo!$G$5:$G$129,MATCH(C100,Catalogo!$A$5:$A$129,0)),"")) | X100: =IF(C100="","",IF(ISNUMBER(F100),F100,IF(AND(ISNUMBER(D100),ISNUMBER(E100),E100>0),D100/E100*IF(W100="%",100,1),IF(ISNUMBER(D100),D100,"")))) | Y100: =IF(C100="","",IF(A100="","Falta periodo",IF(COUNTIF(Listas!$A$2:$A$134,A100)=0,"Periodo no válido",IF(X100="","Falta valor",IF(I100="","Falta fuente: no se mostrará",IF(AND(J100="",K100=""),"Sin evidencia",IF(N100<>"Validado","Sin validar","OK")))))))
V101: =IF(C101="","",IFERROR(INDEX(Catalogo!$C$5:$C$129,MATCH(C101,Catalogo!$A$5:$A$129,0)),"Código no existe")) | W101: =IF(C101="","",IFERROR(INDEX(Catalogo!$G$5:$G$129,MATCH(C101,Catalogo!$A$5:$A$129,0)),"")) | X101: =IF(C101="","",IF(ISNUMBER(F101),F101,IF(AND(ISNUMBER(D101),ISNUMBER(E101),E101>0),D101/E101*IF(W101="%",100,1),IF(ISNUMBER(D101),D101,"")))) | Y101: =IF(C101="","",IF(A101="","Falta periodo",IF(COUNTIF(Listas!$A$2:$A$134,A101)=0,"Periodo no válido",IF(X101="","Falta valor",IF(I101="","Falta fuente: no se mostrará",IF(AND(J101="",K101=""),"Sin evidencia",IF(N101<>"Validado","Sin validar","OK")))))))
...

Sheet Evidencias
A1: Evidencias del modelo CONEAU por área
A2: EV1 a EV52. Tecnología Médica: una fila por evidencia y por área (Radiología, Terapia Física, Terapia Ocupacional, Laboratorio Clínico y Anatomía Patológica). Enfermería y Obstetricia: área vacía.
A4: ev_id | B4: area_id | C4: estado | D4: ubicacion | E4: responsable | F4: fecha_actualizacion | G4: observacion | H4: origen | I4: estandar | J4: descripcion (paráfrasis)
A5: EV1 | C5: Disponible | D5: EJEMPLO_EV1.pdf | E5: EJEMPLO Coord. de calidad de Obstetricia | F5: 46280 | H5: EJEMPLO | I5: =IF(A5="","",IFERROR(INDEX(CONEAU_EV_EST,MATCH(A5,CONEAU_EV_ID,0)),"")) | J5: =IF(A5="","",IFERROR(INDEX(CONEAU_EV_DESC,MATCH(A5,CONEAU_EV_ID,0)),""))
A6: EV2 | C6: En elaboración | D6: EJEMPLO_EV2.pdf | E6: EJEMPLO Coord. de calidad de Obstetricia | F6: 46280 | H6: EJEMPLO | I6: =IF(A6="","",IFERROR(INDEX(CONEAU_EV_EST,MATCH(A6,CONEAU_EV_ID,0)),"")) | J6: =IF(A6="","",IFERROR(INDEX(CONEAU_EV_DESC,MATCH(A6,CONEAU_EV_ID,0)),""))
A7: EV3 | C7: Validada | D7: EJEMPLO_EV3.pdf | E7: EJEMPLO Coord. de calidad de Obstetricia | F7: 46280 | H7: EJEMPLO | I7: =IF(A7="","",IFERROR(INDEX(CONEAU_EV_EST,MATCH(A7,CONEAU_EV_ID,0)),"")) | J7: =IF(A7="","",IFERROR(INDEX(CONEAU_EV_DESC,MATCH(A7,CONEAU_EV_ID,0)),""))
A8: EV4 | C8: Validada | D8: EJEMPLO_EV4.pdf | E8: EJEMPLO Coord. de calidad de Obstetricia | F8: 46280 | H8: EJEMPLO | I8: =IF(A8="","",IFERROR(INDEX(CONEAU_EV_EST,MATCH(A8,CONEAU_EV_ID,0)),"")) | J8: =IF(A8="","",IFERROR(INDEX(CONEAU_EV_DESC,MATCH(A8,CONEAU_EV_ID,0)),""))
A9: EV5 | C9: Disponible | D9: EJEMPLO_EV5.pdf | E9: EJEMPLO Coord. de calidad de Obstetricia | F9: 46280 | H9: EJEMPLO | I9: =IF(A9="","",IFERROR(INDEX(CONEAU_EV_EST,MATCH(A9,CONEAU_EV_ID,0)),"")) | J9: =IF(A9="","",IFERROR(INDEX(CONEAU_EV_DESC,MATCH(A9,CONEAU_EV_ID,0)),""))
A10: EV6 | C10: En elaboración | D10: EJEMPLO_EV6.pdf | E10: EJEMPLO Coord. de calidad de Obstetricia | F10: 46280 | H10: EJEMPLO | I10: =IF(A10="","",IFERROR(INDEX(CONEAU_EV_EST,MATCH(A10,CONEAU_EV_ID,0)),"")) | J10: =IF(A10="","",IFERROR(INDEX(CONEAU_EV_DESC,MATCH(A10,CONEAU_EV_ID,0)),""))
A11: EV7 | C11: No iniciada | E11: EJEMPLO Coord. de calidad de Obstetricia | H11: EJEMPLO | I11: =IF(A11="","",IFERROR(INDEX(CONEAU_EV_EST,MATCH(A11,CONEAU_EV_ID,0)),"")) | J11: =IF(A11="","",IFERROR(INDEX(CONEAU_EV_DESC,MATCH(A11,CONEAU_EV_ID,0)),""))
A12: EV8 | C12: Validada | D12: EJEMPLO_EV8.pdf | E12: EJEMPLO Coord. de calidad de Obstetricia | F12: 46280 | H12: EJEMPLO | I12: =IF(A12="","",IFERROR(INDEX(CONEAU_EV_EST,MATCH(A12,CONEAU_EV_ID,0)),"")) | J12: =IF(A12="","",IFERROR(INDEX(CONEAU_EV_DESC,MATCH(A12,CONEAU_EV_ID,0)),""))
A13: EV9 | C13: Disponible | D13: EJEMPLO_EV9.pdf | E13: EJEMPLO Coord. de calidad de Obstetricia | F13: 46280 | H13: EJEMPLO | I13: =IF(A13="","",IFERROR(INDEX(CONEAU_EV_EST,MATCH(A13,CONEAU_EV_ID,0)),"")) | J13: =IF(A13="","",IFERROR(INDEX(CONEAU_EV_DESC,MATCH(A13,CONEAU_EV_ID,0)),""))
A14: EV10 | C14: No iniciada | E14: EJEMPLO Coord. de calidad de Obstetricia | H14: EJEMPLO | I14: =IF(A14="","",IFERROR(INDEX(CONEAU_EV_EST,MATCH(A14,CONEAU_EV_ID,0)),"")) | J14: =IF(A14="","",IFERROR(INDEX(CONEAU_EV_DESC,MATCH(A14,CONEAU_EV_ID,0)),""))
A15: EV11 | C15: No iniciada | E15: EJEMPLO Coord. de calidad de Obstetricia | H15: EJEMPLO | I15: =IF(A15="","",IFERROR(INDEX(CONEAU_EV_EST,MATCH(A15,CONEAU_EV_ID,0)),"")) | J15: =IF(A15="","",IFERROR(INDEX(CONEAU_EV_DESC,MATCH(A15,CONEAU_EV_ID,0)),""))
A16: EV12 | C16: No iniciada | E16: EJEMPLO Coord. de calidad de Obstetricia | H16: EJEMPLO | I16: =IF(A16="","",IFERROR(INDEX(CONEAU_EV_EST,MATCH(A16,CONEAU_EV_ID,0)),"")) | J16: =IF(A16="","",IFERROR(INDEX(CONEAU_EV_DESC,MATCH(A16,CONEAU_EV_ID,0)),""))
A17: EV13 | C17: En elaboración | D17: EJEMPLO_EV13.pdf | E17: EJEMPLO Coord. de calidad de Obstetricia | F17: 46280 | H17: EJEMPLO | I17: =IF(A17="","",IFERROR(INDEX(CONEAU_EV_EST,MATCH(A17,CONEAU_EV_ID,0)),"")) | J17: =IF(A17="","",IFERROR(INDEX(CONEAU_EV_DESC,MATCH(A17,CONEAU_EV_ID,0)),""))
A18: EV14 | C18: Validada | D18: EJEMPLO_EV14.pdf | E18: EJEMPLO Coord. de calidad de Obstetricia | F18: 46280 | H18: EJEMPLO | I18: =IF(A18="","",IFERROR(INDEX(CONEAU_EV_EST,MATCH(A18,CONEAU_EV_ID,0)),"")) | J18: =IF(A18="","",IFERROR(INDEX(CONEAU_EV_DESC,MATCH(A18,CONEAU_EV_ID,0)),""))
A19: EV15 | C19: Validada | D19: EJEMPLO_EV15.pdf | E19: EJEMPLO Coord. de calidad de Obstetricia | F19: 46280 | H19: EJEMPLO | I19: =IF(A19="","",IFERROR(INDEX(CONEAU_EV_EST,MATCH(A19,CONEAU_EV_ID,0)),"")) | J19: =IF(A19="","",IFERROR(INDEX(CONEAU_EV_DESC,MATCH(A19,CONEAU_EV_ID,0)),""))
A20: EV16 | C20: Disponible | D20: EJEMPLO_EV16.pdf | E20: EJEMPLO Coord. de calidad de Obstetricia | F20: 46280 | H20: EJEMPLO | I20: =IF(A20="","",IFERROR(INDEX(CONEAU_EV_EST,MATCH(A20,CONEAU_EV_ID,0)),"")) | J20: =IF(A20="","",IFERROR(INDEX(CONEAU_EV_DESC,MATCH(A20,CONEAU_EV_ID,0)),""))
A21: EV17 | C21: Disponible | D21: EJEMPLO_EV17.pdf | E21: EJEMPLO Coord. de calidad de Obstetricia | F21: 46280 | H21: EJEMPLO | I21: =IF(A21="","",IFERROR(INDEX(CONEAU_EV_EST,MATCH(A21,CONEAU_EV_ID,0)),"")) | J21: =IF(A21="","",IFERROR(INDEX(CONEAU_EV_DESC,MATCH(A21,CONEAU_EV_ID,0)),""))
A22: EV18 | C22: Disponible | D22: EJEMPLO_EV18.pdf | E22: EJEMPLO Coord. de calidad de Obstetricia | F22: 46280 | H22: EJEMPLO | I22: =IF(A22="","",IFERROR(INDEX(CONEAU_EV_EST,MATCH(A22,CONEAU_EV_ID,0)),"")) | J22: =IF(A22="","",IFERROR(INDEX(CONEAU_EV_DESC,MATCH(A22,CONEAU_EV_ID,0)),""))
A23: EV19 | C23: En elaboración | D23: EJEMPLO_EV19.pdf | E23: EJEMPLO Coord. de calidad de Obstetricia | F23: 46280 | H23: EJEMPLO | I23: =IF(A23="","",IFERROR(INDEX(CONEAU_EV_EST,MATCH(A23,CONEAU_EV_ID,0)),"")) | J23: =IF(A23="","",IFERROR(INDEX(CONEAU_EV_DESC,MATCH(A23,CONEAU_EV_ID,0)),""))
A24: EV20 | C24: Disponible | D24: EJEMPLO_EV20.pdf | E24: EJEMPLO Coord. de calidad de Obstetricia | F24: 46280 | H24: EJEMPLO | I24: =IF(A24="","",IFERROR(INDEX(CONEAU_EV_EST,MATCH(A24,CONEAU_EV_ID,0)),"")) | J24: =IF(A24="","",IFERROR(INDEX(CONEAU_EV_DESC,MATCH(A24,CONEAU_EV_ID,0)),""))
A25: EV21 | C25: En elaboración | D25: EJEMPLO_EV21.pdf | E25: EJEMPLO Coord. de calidad de Obstetricia | F25: 46280 | H25: EJEMPLO | I25: =IF(A25="","",IFERROR(INDEX(CONEAU_EV_EST,MATCH(A25,CONEAU_EV_ID,0)),"")) | J25: =IF(A25="","",IFERROR(INDEX(CONEAU_EV_DESC,MATCH(A25,CONEAU_EV_ID,0)),""))
A26: EV22 | C26: Disponible | D26: EJEMPLO_EV22.pdf | E26: EJEMPLO Coord. de calidad de Obstetricia | F26: 46280 | H26: EJEMPLO | I26: =IF(A26="","",IFERROR(INDEX(CONEAU_EV_EST,MATCH(A26,CONEAU_EV_ID,0)),"")) | J26: =IF(A26="","",IFERROR(INDEX(CONEAU_EV_DESC,MATCH(A26,CONEAU_EV_ID,0)),""))
A27: EV23 | C27: No iniciada | E27: EJEMPLO Coord. de calidad de Obstetricia | H27: EJEMPLO | I27: =IF(A27="","",IFERROR(INDEX(CONEAU_EV_EST,MATCH(A27,CONEAU_EV_ID,0)),"")) | J27: =IF(A27="","",IFERROR(INDEX(CONEAU_EV_DESC,MATCH(A27,CONEAU_EV_ID,0)),""))
A28: EV24 | C28: Disponible | D28: EJEMPLO_EV24.pdf | E28: EJEMPLO Coord. de calidad de Obstetricia | F28: 46280 | H28: EJEMPLO | I28: =IF(A28="","",IFERROR(INDEX(CONEAU_EV_EST,MATCH(A28,CONEAU_EV_ID,0)),"")) | J28: =IF(A28="","",IFERROR(INDEX(CONEAU_EV_DESC,MATCH(A28,CONEAU_EV_ID,0)),""))
A29: EV25 | C29: En elaboración | D29: EJEMPLO_EV25.pdf | E29: EJEMPLO Coord. de calidad de Obstetricia | F29: 46280 | H29: EJEMPLO | I29: =IF(A29="","",IFERROR(INDEX(CONEAU_EV_EST,MATCH(A29,CONEAU_EV_ID,0)),"")) | J29: =IF(A29="","",IFERROR(INDEX(CONEAU_EV_DESC,MATCH(A29,CONEAU_EV_ID,0)),""))
A30: EV26 | C30: En elaboración | D30: EJEMPLO_EV26.pdf | E30: EJEMPLO Coord. de calidad de Obstetricia | F30: 46280 | H30: EJEMPLO | I30: =IF(A30="","",IFERROR(INDEX(CONEAU_EV_EST,MATCH(A30,CONEAU_EV_ID,0)),"")) | J30: =IF(A30="","",IFERROR(INDEX(CONEAU_EV_DESC,MATCH(A30,CONEAU_EV_ID,0)),""))
A31: EV27 | C31: Disponible | D31: EJEMPLO_EV27.pdf | E31: EJEMPLO Coord. de calidad de Obstetricia | F31: 46280 | H31: EJEMPLO | I31: =IF(A31="","",IFERROR(INDEX(CONEAU_EV_EST,MATCH(A31,CONEAU_EV_ID,0)),"")) | J31: =IF(A31="","",IFERROR(INDEX(CONEAU_EV_DESC,MATCH(A31,CONEAU_EV_ID,0)),""))
A32: EV28 | C32: En elaboración | D32: EJEMPLO_EV28.pdf | E32: EJEMPLO Coord. de calidad de Obstetricia | F32: 46280 | H32: EJEMPLO | I32: =IF(A32="","",IFERROR(INDEX(CONEAU_EV_EST,MATCH(A32,CONEAU_EV_ID,0)),"")) | J32: =IF(A32="","",IFERROR(INDEX(CONEAU_EV_DESC,MATCH(A32,CONEAU_EV_ID,0)),""))
A33: EV29 | C33: Disponible | D33: EJEMPLO_EV29.pdf | E33: EJEMPLO Coord. de calidad de Obstetricia | F33: 46280 | H33: EJEMPLO | I33: =IF(A33="","",IFERROR(INDEX(CONEAU_EV_EST,MATCH(A33,CONEAU_EV_ID,0)),"")) | J33: =IF(A33="","",IFERROR(INDEX(CONEAU_EV_DESC,MATCH(A33,CONEAU_EV_ID,0)),""))
A34: EV30 | C34: En elaboración | D34: EJEMPLO_EV30.pdf | E34: EJEMPLO Coord. de calidad de Obstetricia | F34: 46280 | H34: EJEMPLO | I34: =IF(A34="","",IFERROR(INDEX(CONEAU_EV_EST,MATCH(A34,CONEAU_EV_ID,0)),"")) | J34: =IF(A34="","",IFERROR(INDEX(CONEAU_EV_DESC,MATCH(A34,CONEAU_EV_ID,0)),""))
A35: EV31 | C35: Validada | D35: EJEMPLO_EV31.pdf | E35: EJEMPLO Coord. de calidad de Obstetricia | F35: 46280 | H35: EJEMPLO | I35: =IF(A35="","",IFERROR(INDEX(CONEAU_EV_EST,MATCH(A35,CONEAU_EV_ID,0)),"")) | J35: =IF(A35="","",IFERROR(INDEX(CONEAU_EV_DESC,MATCH(A35,CONEAU_EV_ID,0)),""))
A36: EV32 | C36: Disponible | D36: EJEMPLO_EV32.pdf | E36: EJEMPLO Coord. de calidad de Obstetricia | F36: 46280 | H36: EJEMPLO | I36: =IF(A36="","",IFERROR(INDEX(CONEAU_EV_EST,MATCH(A36,CONEAU_EV_ID,0)),"")) | J36: =IF(A36="","",IFERROR(INDEX(CONEAU_EV_DESC,MATCH(A36,CONEAU_EV_ID,0)),""))
A37: EV33 | C37: Disponible | D37: EJEMPLO_EV33.pdf | E37: EJEMPLO Coord. de calidad de Obstetricia | F37: 46280 | H37: EJEMPLO | I37: =IF(A37="","",IFERROR(INDEX(CONEAU_EV_EST,MATCH(A37,CONEAU_EV_ID,0)),"")) | J37: =IF(A37="","",IFERROR(INDEX(CONEAU_EV_DESC,MATCH(A37,CONEAU_EV_ID,0)),""))
A38: EV34 | C38: En elaboración | D38: EJEMPLO_EV34.pdf | E38: EJEMPLO Coord. de calidad de Obstetricia | F38: 46280 | H38: EJEMPLO | I38: =IF(A38="","",IFERROR(INDEX(CONEAU_EV_EST,MATCH(A38,CONEAU_EV_ID,0)),"")) | J38: =IF(A38="","",IFERROR(INDEX(CONEAU_EV_DESC,MATCH(A38,CONEAU_EV_ID,0)),""))
A39: EV35 | C39: Disponible | D39: EJEMPLO_EV35.pdf | E39: EJEMPLO Coord. de calidad de Obstetricia | F39: 46280 | H39: EJEMPLO | I39: =IF(A39="","",IFERROR(INDEX(CONEAU_EV_EST,MATCH(A39,CONEAU_EV_ID,0)),"")) | J39: =IF(A39="","",IFERROR(INDEX(CONEAU_EV_DESC,MATCH(A39,CONEAU_EV_ID,0)),""))
A40: EV36 | C40: No iniciada | E40: EJEMPLO Coord. de calidad de Obstetricia | H40: EJEMPLO | I40: =IF(A40="","",IFERROR(INDEX(CONEAU_EV_EST,MATCH(A40,CONEAU_EV_ID,0)),"")) | J40: =IF(A40="","",IFERROR(INDEX(CONEAU_EV_DESC,MATCH(A40,CONEAU_EV_ID,0)),""))
A41: EV37 | C41: Disponible | D41: EJEMPLO_EV37.pdf | E41: EJEMPLO Coord. de calidad de Obstetricia | F41: 46280 | H41: EJEMPLO | I41: =IF(A41="","",IFERROR(INDEX(CONEAU_EV_EST,MATCH(A41,CONEAU_EV_ID,0)),"")) | J41: =IF(A41="","",IFERROR(INDEX(CONEAU_EV_DESC,MATCH(A41,CONEAU_EV_ID,0)),""))
A42: EV38 | C42: Disponible | D42: EJEMPLO_EV38.pdf | E42: EJEMPLO Coord. de calidad de Obstetricia | F42: 46280 | H42: EJEMPLO | I42: =IF(A42="","",IFERROR(INDEX(CONEAU_EV_EST,MATCH(A42,CONEAU_EV_ID,0)),"")) | J42: =IF(A42="","",IFERROR(INDEX(CONEAU_EV_DESC,MATCH(A42,CONEAU_EV_ID,0)),""))
A43: EV39 | C43: No iniciada | E43: EJEMPLO Coord. de calidad de Obstetricia | H43: EJEMPLO | I43: =IF(A43="","",IFERROR(INDEX(CONEAU_EV_EST,MATCH(A43,CONEAU_EV_ID,0)),"")) | J43: =IF(A43="","",IFERROR(INDEX(CONEAU_EV_DESC,MATCH(A43,CONEAU_EV_ID,0)),""))
A44: EV40 | C44: Validada | D44: EJEMPLO_EV40.pdf | E44: EJEMPLO Coord. de calidad de Obstetricia | F44: 46280 | H44: EJEMPLO | I44: =IF(A44="","",IFERROR(INDEX(CONEAU_EV_EST,MATCH(A44,CONEAU_EV_ID,0)),"")) | J44: =IF(A44="","",IFERROR(INDEX(CONEAU_EV_DESC,MATCH(A44,CONEAU_EV_ID,0)),""))
A45: EV41 | C45: Validada | D45: EJEMPLO_EV41.pdf | E45: EJEMPLO Coord. de calidad de Obstetricia | F45: 46280 | H45: EJEMPLO | I45: =IF(A45="","",IFERROR(INDEX(CONEAU_EV_EST,MATCH(A45,CONEAU_EV_ID,0)),"")) | J45: =IF(A45="","",IFERROR(INDEX(CONEAU_EV_DESC,MATCH(A45,CONEAU_EV_ID,0)),""))
A46: EV42 | C46: Disponible | D46: EJEMPLO_EV42.pdf | E46: EJEMPLO Coord. de calidad de Obstetricia | F46: 46280 | H46: EJEMPLO | I46: =IF(A46="","",IFERROR(INDEX(CONEAU_EV_EST,MATCH(A46,CONEAU_EV_ID,0)),"")) | J46: =IF(A46="","",IFERROR(INDEX(CONEAU_EV_DESC,MATCH(A46,CONEAU_EV_ID,0)),""))
A47: EV43 | C47: Disponible | D47: EJEMPLO_EV43.pdf | E47: EJEMPLO Coord. de calidad de Obstetricia | F47: 46280 | H47: EJEMPLO | I47: =IF(A47="","",IFERROR(INDEX(CONEAU_EV_EST,MATCH(A47,CONEAU_EV_ID,0)),"")) | J47: =IF(A47="","",IFERROR(INDEX(CONEAU_EV_DESC,MATCH(A47,CONEAU_EV_ID,0)),""))
A48: EV44 | C48: En elaboración | D48: EJEMPLO_EV44.pdf | E48: EJEMPLO Coord. de calidad de Obstetricia | F48: 46280 | H48: EJEMPLO | I48: =IF(A48="","",IFERROR(INDEX(CONEAU_EV_EST,MATCH(A48,CONEAU_EV_ID,0)),"")) | J48: =IF(A48="","",IFERROR(INDEX(CONEAU_EV_DESC,MATCH(A48,CONEAU_EV_ID,0)),""))
A49: EV45 | C49: No iniciada | E49: EJEMPLO Coord. de calidad de Obstetricia | H49: EJEMPLO | I49: =IF(A49="","",IFERROR(INDEX(CONEAU_EV_EST,MATCH(A49,CONEAU_EV_ID,0)),"")) | J49: =IF(A49="","",IFERROR(INDEX(CONEAU_EV_DESC,MATCH(A49,CONEAU_EV_ID,0)),""))
A50: EV46 | C50: Disponible | D50: EJEMPLO_EV46.pdf | E50: EJEMPLO Coord. de calidad de Obstetricia | F50: 46280 | H50: EJEMPLO | I50: =IF(A50="","",IFERROR(INDEX(CONEAU_EV_EST,MATCH(A50,CONEAU_EV_ID,0)),"")) | J50: =IF(A50="","",IFERROR(INDEX(CONEAU_EV_DESC,MATCH(A50,CONEAU_EV_ID,0)),""))
A51: EV47 | C51: Validada | D51: EJEMPLO_EV47.pdf | E51: EJEMPLO Coord. de calidad de Obstetricia | F51: 46280 | H51: EJEMPLO | I51: =IF(A51="","",IFERROR(INDEX(CONEAU_EV_EST,MATCH(A51,CONEAU_EV_ID,0)),"")) | J51: =IF(A51="","",IFERROR(INDEX(CONEAU_EV_DESC,MATCH(A51,CONEAU_EV_ID,0)),""))
A52: EV48 | C52: Validada | D52: EJEMPLO_EV48.pdf | E52: EJEMPLO Coord. de calidad de Obstetricia | F52: 46280 | H52: EJEMPLO | I52: =IF(A52="","",IFERROR(INDEX(CONEAU_EV_EST,MATCH(A52,CONEAU_EV_ID,0)),"")) | J52: =IF(A52="","",IFERROR(INDEX(CONEAU_EV_DESC,MATCH(A52,CONEAU_EV_ID,0)),""))
A53: EV49 | C53: En elaboración | D53: EJEMPLO_EV49.pdf | E53: EJEMPLO Coord. de calidad de Obstetricia | F53: 46280 | H53: EJEMPLO | I53: =IF(A53="","",IFERROR(INDEX(CONEAU_EV_EST,MATCH(A53,CONEAU_EV_ID,0)),"")) | J53: =IF(A53="","",IFERROR(INDEX(CONEAU_EV_DESC,MATCH(A53,CONEAU_EV_ID,0)),""))
A54: EV50 | C54: En elaboración | D54: EJEMPLO_EV50.pdf | E54: EJEMPLO Coord. de calidad de Obstetricia | F54: 46280 | H54: EJEMPLO | I54: =IF(A54="","",IFERROR(INDEX(CONEAU_EV_EST,MATCH(A54,CONEAU_EV_ID,0)),"")) | J54: =IF(A54="","",IFERROR(INDEX(CONEAU_EV_DESC,MATCH(A54,CONEAU_EV_ID,0)),""))
A55: EV51 | C55: En elaboración | D55: EJEMPLO_EV51.pdf | E55: EJEMPLO Coord. de calidad de Obstetricia | F55: 46280 | H55: EJEMPLO | I55: =IF(A55="","",IFERROR(INDEX(CONEAU_EV_EST,MATCH(A55,CONEAU_EV_ID,0)),"")) | J55: =IF(A55="","",IFERROR(INDEX(CONEAU_EV_DESC,MATCH(A55,CONEAU_EV_ID,0)),""))
A56: EV52 | C56: Validada | D56: EJEMPLO_EV52.pdf | E56: EJEMPLO Coord. de calidad de Obstetricia | F56: 46280 | H56: EJEMPLO | I56: =IF(A56="","",IFERROR(INDEX(CONEAU_EV_EST,MATCH(A56,CONEAU_EV_ID,0)),"")) | J56: =IF(A56="","",IFERROR(INDEX(CONEAU_EV_DESC,MATCH(A56,CONEAU_EV_ID,0)),""))
I57: =IF(A57="","",IFERROR(INDEX(CONEAU_EV_EST,MATCH(A57,CONEAU_EV_ID,0)),"")) | J57: =IF(A57="","",IFERROR(INDEX(CONEAU_EV_DESC,MATCH(A57,CONEAU_EV_ID,0)),""))
I58: =IF(A58="","",IFERROR(INDEX(CONEAU_EV_EST,MATCH(A58,CONEAU_EV_ID,0)),"")) | J58: =IF(A58="","",IFERROR(INDEX(CONEAU_EV_DESC,MATCH(A58,CONEAU_EV_ID,0)),""))
I59: =IF(A59="","",IFERROR(INDEX(CONEAU_EV_EST,MATCH(A59,CONEAU_EV_ID,0)),"")) | J59: =IF(A59="","",IFERROR(INDEX(CONEAU_EV_DESC,MATCH(A59,CONEAU_EV_ID,0)),""))
I60: =IF(A60="","",IFERROR(INDEX(CONEAU_EV_EST,MATCH(A60,CONEAU_EV_ID,0)),"")) | J60: =IF(A60="","",IFERROR(INDEX(CONEAU_EV_DESC,MATCH(A60,CONEAU_EV_ID,0)),""))
I61: =IF(A61="","",IFERROR(INDEX(CONEAU_EV_EST,MATCH(A61,CONEAU_EV_ID,0)),"")) | J61: =IF(A61="","",IFERROR(INDEX(CONEAU_EV_DESC,MATCH(A61,CONEAU_EV_ID,0)),""))
I62: =IF(A62="","",IFERROR(INDEX(CONEAU_EV_EST,MATCH(A62,CONEAU_EV_ID,0)),"")) | J62: =IF(A62="","",IFERROR(INDEX(CONEAU_EV_DESC,MATCH(A62,CONEAU_EV_ID,0)),""))
I63: =IF(A63="","",IFERROR(INDEX(CONEAU_EV_EST,MATCH(A63,CONEAU_EV_ID,0)),"")) | J63: =IF(A63="","",IFERROR(INDEX(CONEAU_EV_DESC,MATCH(A63,CONEAU_EV_ID,0)),""))
I64: =IF(A64="","",IFERROR(INDEX(CONEAU_EV_EST,MATCH(A64,CONEAU_EV_ID,0)),"")) | J64: =IF(A64="","",IFERROR(INDEX(CONEAU_EV_DESC,MATCH(A64,CONEAU_EV_ID,0)),""))
I65: =IF(A65="","",IFERROR(INDEX(CONEAU_EV_EST,MATCH(A65,CONEAU_EV_ID,0)),"")) | J65: =IF(A65="","",IFERROR(INDEX(CONEAU_EV_DESC,MATCH(A65,CONEAU_EV_ID,0)),""))
I66: =IF(A66="","",IFERROR(INDEX(CONEAU_EV_EST,MATCH(A66,CONEAU_EV_ID,0)),"")) | J66: =IF(A66="","",IFERROR(INDEX(CONEAU_EV_DESC,MATCH(A66,CONEAU_EV_ID,0)),""))
I67: =IF(A67="","",IFERROR(INDEX(CONEAU_EV_EST,MATCH(A67,CONEAU_EV_ID,0)),"")) | J67: =IF(A67="","",IFERROR(INDEX(CONEAU_EV_DESC,MATCH(A67,CONEAU_EV_ID,0)),""))
I68: =IF(A68="","",IFERROR(INDEX(CONEAU_EV_EST,MATCH(A68,CONEAU_EV_ID,0)),"")) | J68: =IF(A68="","",IFERROR(INDEX(CONEAU_EV_DESC,MATCH(A68,CONEAU_EV_ID,0)),""))
... I264: =IF(A264="","",IFERROR(INDEX(CONEAU_EV_EST,MATCH(A264,CONEAU_EV_ID,0)),"")) | J264: =IF(A264="","",IFERROR(INDEX(CONEAU_EV_DESC,MATCH(A264,CONEAU_EV_ID,0)),""))

Sheet Alcance
A1: Alcance: qué indicadores vigila esta escuela
A2: Sí: el tablero espera datos y alerta si faltan. No: se deja fuera (fase posterior). Valor inicial según 'alcance_inicial' [CP]: indicadores del piloto, de los 9 procesos del 10.2 y los 29 del modelo.
A4: indicador_id | B4: en_seguimiento | C4: responsable_local | D4: nota | E4: nombre
A5: ID1 | B5: Sí | E5: =IFERROR(INDEX(Catalogo!$C$5:$C$129,MATCH(A5,Catalogo!$A$5:$A$129,0)),"")
A6: ID2 | B6: Sí | E6: =IFERROR(INDEX(Catalogo!$C$5:$C$129,MATCH(A6,Catalogo!$A$5:$A$129,0)),"")
A7: ID3 | B7: Sí | E7: =IFERROR(INDEX(Catalogo!$C$5:$C$129,MATCH(A7,Catalogo!$A$5:$A$129,0)),"")
A8: ID4 | B8: Sí | E8: =IFERROR(INDEX(Catalogo!$C$5:$C$129,MATCH(A8,Catalogo!$A$5:$A$129,0)),"")
A9: ID5 | B9: Sí | E9: =IFERROR(INDEX(Catalogo!$C$5:$C$129,MATCH(A9,Catalogo!$A$5:$A$129,0)),"")
A10: ID6 | B10: Sí | E10: =IFERROR(INDEX(Catalogo!$C$5:$C$129,MATCH(A10,Catalogo!$A$5:$A$129,0)),"")
A11: ID7 | B11: Sí | E11: =IFERROR(INDEX(Catalogo!$C$5:$C$129,MATCH(A11,Catalogo!$A$5:$A$129,0)),"")
A12: ID8 | B12: Sí | E12: =IFERROR(INDEX(Catalogo!$C$5:$C$129,MATCH(A12,Catalogo!$A$5:$A$129,0)),"")
A13: ID9 | B13: Sí | E13: =IFERROR(INDEX(Catalogo!$C$5:$C$129,MATCH(A13,Catalogo!$A$5:$A$129,0)),"")
A14: ID10 | B14: Sí | E14: =IFERROR(INDEX(Catalogo!$C$5:$C$129,MATCH(A14,Catalogo!$A$5:$A$129,0)),"")
A15: ID11 | B15: Sí | E15: =IFERROR(INDEX(Catalogo!$C$5:$C$129,MATCH(A15,Catalogo!$A$5:$A$129,0)),"")
A16: ID12 | B16: Sí | E16: =IFERROR(INDEX(Catalogo!$C$5:$C$129,MATCH(A16,Catalogo!$A$5:$A$129,0)),"")
... A129: PEFM-AE.04.02 | B129: Solo Facultad | E129: =IFERROR(INDEX(Catalogo!$C$5:$C$129,MATCH(A129,Catalogo!$A$5:$A$129,0)),"")

Sheet Criterios
A1: Autoevaluación por criterio (53 criterios del modelo CONEAU 2026)
A2: Misma lista para las tres escuelas. Llena lo que diga el informe de autoevaluación de la escuela; sin informe, deja «sin dato». Alimenta las alertas R12 (EV exigidas sin citar) y R13 (matrices pendientes).
A4: escuela | B4: estandar | C4: criterio | D4: resumen | E4: valoracion_informe | F4: ev_exigidas | G4: ev_exigidas_sin_citar | H4: matrices_pendientes | I4: prioridad | J4: indicadores_que_lo_citan | K4: evidencias_citadas | L4: con_enlace | M4: evidencia_que_falta | N4: archivo | O4: fuente | P4: origen
A5: =IF(Portada!$B$7="","",Portada!$B$7) | B5: E1 | C5: 1.1 | D5: Estructura interna pertinente | E5: sin dato | F5: EV1
A6: =IF(Portada!$B$7="","",Portada!$B$7) | B6: E1 | C6: 1.2 | D6: Cuerpo directivo idóneo | E6: sin dato | F6: EV2
A7: =IF(Portada!$B$7="","",Portada!$B$7) | B7: E1 | C7: 1.3 | D7: Planes con objetivos académicos evaluados anualmente | E7: sin dato | F7: EV3 EV4 EV5 EV6
A8: =IF(Portada!$B$7="","",Portada!$B$7) | B8: E1 | C8: 1.4 | D8: Quejas, reclamos y denuncias | E8: sin dato | F8: EV7
A9: =IF(Portada!$B$7="","",Portada!$B$7) | B9: E1 | C9: 1.5 | D9: Satisfacción con servicios administrativos | E9: sin dato | F9: EV7 EV41 EV42 EV43 | J9: ID8 ID18 ID21
A10: =IF(Portada!$B$7="","",Portada!$B$7) | B10: E2 | C10: 2.1 | D10: Componentes mínimos del currículo | E10: sin dato | F10: EV8 | J10: ID1 ID12
A11: =IF(Portada!$B$7="","",Portada!$B$7) | B11: E2 | C11: 2.2 | D11: Perfil de egreso | E11: sin dato | F11: EV8
A12: =IF(Portada!$B$7="","",Portada!$B$7) | B12: E2 | C12: 2.3 | D12: Plan de estudios completo | E12: sin dato | F12: EV8
A13: =IF(Portada!$B$7="","",Portada!$B$7) | B13: E2 | C13: 2.4 | E13: sin dato | F13: EV9
A14: =IF(Portada!$B$7="","",Portada!$B$7) | B14: E2 | C14: 2.5 | D14: Contenido de los sílabos | E14: sin dato | F14: EV9
A15: =IF(Portada!$B$7="","",Portada!$B$7) | B15: E2 | C15: 2.6 | D15: Normas de convalidación | E15: sin dato | F15: EV11
A16: =IF(Portada!$B$7="","",Portada!$B$7) | B16: E2 | C16: 2.7 | D16: Verificación del cumplimiento de sílabos | E16: sin dato | F16: EV10 | J16: ID11
A17: =IF(Portada!$B$7="","",Portada!$B$7) | B17: E3 | C17: 3.1 | D17: Evaluación de la calidad de la enseñanza | E17: sin dato | F17: EV12 | J17: ID1 ID3 ID4 ID10 ID19 ID22
A18: =IF(Portada!$B$7="","",Portada!$B$7) | B18: E3 | C18: 3.2 | D18: Evaluación coherente con el enfoque pedagógico | E18: sin dato | F18: EV13 | J18: ID4
A19: =IF(Portada!$B$7="","",Portada!$B$7) | B19: E3 | C19: 3.3 | D19: Evidencias del logro del perfil | E19: sin dato | F19: EV13 EV17 | J19: ID4 ID20
A20: =IF(Portada!$B$7="","",Portada!$B$7) | B20: E3 | C20: 3.4 | D20: Información oportuna al estudiante | E20: sin dato | F20: EV13 | J20: ID4
A21: =IF(Portada!$B$7="","",Portada!$B$7) | B21: E3 | C21: 3.5 | D21: Tutoría y asesoría | E21: sin dato | F21: EV14 EV15 EV18 | J21: ID5 ID9 ID24
A22: =IF(Portada!$B$7="","",Portada!$B$7) | B22: E3 | C22: 3.6 | D22: Originalidad y rigor de tesis | E22: sin dato | F22: EV16 EV19
A23: =IF(Portada!$B$7="","",Portada!$B$7) | B23: E3 | C23: 3.7 | D23: Autoría del propio estudiante | E23: sin dato | F23: EV16
A24: =IF(Portada!$B$7="","",Portada!$B$7) | B24: E4 | C24: 4.1 | D24: Selección y vinculación transparente | E24: sin dato | F24: EV20 EV22 EV24 | J24: ID4 ID14 ID19
A25: =IF(Portada!$B$7="","",Portada!$B$7) | B25: E4 | C25: 4.2 | D25: Competencias pedagógicas, disciplinares y digitales | E25: sin dato | F25: EV21 EV24 EV25 | J25: ID2 ID19
A26: =IF(Portada!$B$7="","",Portada!$B$7) | B26: E4 | C26: 4.3 | D26: Carga lectiva según perfil docente | E26: sin dato | F26: EV23 EV24 | J26: ID2 ID13 ID14
A27: =IF(Portada!$B$7="","",Portada!$B$7) | B27: E4 | C27: 4.4 | D27: Evaluación periódica del desempeño | E27: sin dato | F27: EV21 EV25 | J27: ID2 ID15 ID16 ID19
A28: =IF(Portada!$B$7="","",Portada!$B$7) | B28: E4 | C28: 4.5 | D28: Fortalecimiento de capacidades | E28: sin dato | F28: EV26 EV27 | J28: ID15 ID16
A29: =IF(Portada!$B$7="","",Portada!$B$7) | B29: E4 | C29: 4.6 | D29: Experiencias en otras instituciones | E29: sin dato | F29: EV28 EV29 | J29: ID14
A30: =IF(Portada!$B$7="","",Portada!$B$7) | B30: E5 | C30: 5.1 | D30: Infraestructura suficiente y adecuada | E30: sin dato | F30: EV30 | J30: ID3 ID17
A31: =IF(Portada!$B$7="","",Portada!$B$7) | B31: E5 | C31: 5.2 | D31: Equipamiento y mobiliario | E31: sin dato | F31: EV30 | J31: ID3 ID17
A32: =IF(Portada!$B$7="","",Portada!$B$7) | B32: E5 | C32: 5.3 | D32: Tecnologías de información | E32: sin dato | F32: EV30 | J32: ID3 ID17
A33: =IF(Portada!$B$7="","",Portada!$B$7) | B33: E5 | C33: 5.4 | D33: Protocolos y manuales | E33: sin dato | F33: EV31
A34: =IF(Portada!$B$7="","",Portada!$B$7) | B34: E5 | C34: 5.5 | D34: Recursos académicos y bases de datos | E34: sin dato | F34: EV32 | J34: ID3 ID17
A35: =IF(Portada!$B$7="","",Portada!$B$7) | B35: E5 | C35: 5.6 | D35: Plan de mantenimiento | E35: sin dato | F35: EV33
A36: =IF(Portada!$B$7="","",Portada!$B$7) | B36: E6 | C36: 6.1 | D36: Currículo con impacto positivo | E36: sin dato | F36: EV34 EV35 | J36: ID10 ID20 ID26 ID27 ID28 ID29
A37: =IF(Portada!$B$7="","",Portada!$B$7) | B37: E6 | C37: 6.2 | D37: Impacto en egresados (cinco años) | E37: sin dato | F37: EV34 | J37: ID20 ID22 ID26 ID27 ID28 ID29
A38: =IF(Portada!$B$7="","",Portada!$B$7) | B38: E6 | C38: 6.3 | D38: Consulta a empleadores | E38: sin dato | F38: EV35 | J38: ID26 ID27 ID28 ID29
A39: =IF(Portada!$B$7="","",Portada!$B$7) | B39: E6 | C39: 6.4 | D39: Planes de mejora | E39: sin dato | F39: EV36
A40: =IF(Portada!$B$7="","",Portada!$B$7) | B40: E6 | C40: 6.5 | D40: Procedimientos en el SGC | E40: sin dato | F40: EV36
A41: =IF(Portada!$B$7="","",Portada!$B$7) | B41: E7 | C41: 7.1 | D41: Programas de bienestar | E41: sin dato | F41: EV37
A42: =IF(Portada!$B$7="","",Portada!$B$7) | B42: E7 | C42: 7.2 | D42: Servicios de apoyo al estudiante | E42: sin dato | F42: EV38 | J42: ID24
A43: =IF(Portada!$B$7="","",Portada!$B$7) | B43: E7 | C43: 7.3 | D43: Personal idóneo y disponibilidad | E43: sin dato | F43: EV37 EV38
A44: =IF(Portada!$B$7="","",Portada!$B$7) | B44: E7 | C44: 7.4 | D44: Evaluación periódica y mejora | E44: sin dato | F44: EV39 | J44: ID7 ID9 ID23 ID24
A45: =IF(Portada!$B$7="","",Portada!$B$7) | B45: E8 | C45: 8.1 | D45: Mecanismos de gestión de la información | E45: sin dato | F45: EV40
A46: =IF(Portada!$B$7="","",Portada!$B$7) | B46: E8 | C46: 8.2 | D46: Información de partes interesadas | E46: sin dato | F46: EV41 EV42 EV43 EV44 | J46: ID1 ID2 ID3 ID4 ID5 ID6 ID7 ID8 ID9 ID12 ID13 ID14 ID15 ID16 ID17 ID18 ID20 ID21 ID22 ID23 ID24 ID26 ID27 ID28 ID29
A47: =IF(Portada!$B$7="","",Portada!$B$7) | B47: E8 | C47: 8.3 | D47: Información de desempeño docente | E47: sin dato | F47: EV42 EV25 | J47: ID2 ID19
A48: =IF(Portada!$B$7="","",Portada!$B$7) | B48: E8 | C48: 8.4 | D48: Información de evaluación del aprendizaje | E48: sin dato | F48: EV41 EV17 | J48: ID4 ID10
A49: =IF(Portada!$B$7="","",Portada!$B$7) | B49: E8 | C49: 8.5 | D49: Información de graduación y titulación | E49: sin dato | F49: EV43 EV17 | J49: ID25 ID28 ID29
A50: =IF(Portada!$B$7="","",Portada!$B$7) | B50: E8 | C50: 8.6 | D50: Información accesible para decidir | E50: sin dato | F50: EV40 EV41 EV42 EV43 EV44
A51: =IF(Portada!$B$7="","",Portada!$B$7) | B51: E9 | C51: 9.1 | D51: Evaluación periódica del currículo | E51: sin dato | F51: EV45 EV46
A52: =IF(Portada!$B$7="","",Portada!$B$7) | B52: E9 | C52: 9.2 | D52: Registro histórico de cambios curriculares | E52: sin dato | F52: EV47
A53: =IF(Portada!$B$7="","",Portada!$B$7) | B53: E9 | C53: 9.3 | D53: Supervisión de actividades lectivas | E53: sin dato | F53: EV48 | J53: ID11
A54: =IF(Portada!$B$7="","",Portada!$B$7) | B54: E10 | C54: 10.1 | D54: Diseño del SGC | E54: sin dato | F54: EV49
A55: =IF(Portada!$B$7="","",Portada!$B$7) | B55: E10 | C55: 10.2 | D55: Procesos mínimos del SGC | E55: sin dato | F55: EV50
A56: =IF(Portada!$B$7="","",Portada!$B$7) | B56: E10 | C56: 10.3 | D56: Registro histórico del SGC | E56: sin dato | F56: EV51
A57: =IF(Portada!$B$7="","",Portada!$B$7) | B57: E10 | C57: 10.4 | D57: Evaluación periódica del SGC | E57: sin dato | F57: EV52

Sheet Valores_informe
A1: Valores de los 29 indicadores en el informe de autoevaluación (solo referencia)
A2: Misma lista para las tres escuelas. Son los valores que trae el informe, sin validar: no intervienen en semáforos, alertas ni gráficos. El referencial es el del Modelo CONEAU 2026 [A4].
A4: escuela | B4: indicador_id | C4: nombre | D4: unidad_modelo | E4: valor_informe | F4: referencial | G4: referencial_texto | H4: fuente_referencial | I4: referencial_en_informe | J4: estado_que_declara_el_informe | K4: calculo | L4: observacion | M4: estado | N4: uso | O4: archivo | P4: fuente | Q4: origen
A5: =IF(Portada!$B$7="","",Portada!$B$7) | B5: ID1 | C5: Porcentaje de estudiantes satisfechos con el currículo | D5: % | F5: 60 | G5: 60% | H5: Modelo CONEAU 2026 [A4] | M5: =IF(E5="","sin dato","Sin dato validado") | N5: Solo referencia: no interviene en semáforos, alertas ni gráficos
A6: =IF(Portada!$B$7="","",Portada!$B$7) | B6: ID2 | C6: Porcentaje de estudiantes satisfechos con el desempeño docente | D6: % | F6: 70 | G6: 70% | H6: Modelo CONEAU 2026 [A4] | M6: =IF(E6="","sin dato","Sin dato validado") | N6: Solo referencia: no interviene en semáforos, alertas ni gráficos
A7: =IF(Portada!$B$7="","",Portada!$B$7) | B7: ID3 | C7: Porcentaje de estudiantes satisfechos con los recursos para la enseñanza-aprendizaje | D7: % | F7: 70 | G7: 70% | H7: Modelo CONEAU 2026 [A4] | M7: =IF(E7="","sin dato","Sin dato validado") | N7: Solo referencia: no interviene en semáforos, alertas ni gráficos
A8: =IF(Portada!$B$7="","",Portada!$B$7) | B8: ID4 | C8: Porcentaje de estudiantes satisfechos con la evaluación del aprendizaje | D8: % | F8: 60 | G8: 60% | H8: Modelo CONEAU 2026 [A4] | M8: =IF(E8="","sin dato","Sin dato validado") | N8: Solo referencia: no interviene en semáforos, alertas ni gráficos
A9: =IF(Portada!$B$7="","",Portada!$B$7) | B9: ID5 | C9: Porcentaje de estudiantes satisfechos con la asesoría o tutoría para la obtención del título | D9: % | F9: 70 | G9: 70% | H9: Modelo CONEAU 2026 [A4] | M9: =IF(E9="","sin dato","Sin dato validado") | N9: Solo referencia: no interviene en semáforos, alertas ni gráficos
A10: =IF(Portada!$B$7="","",Portada!$B$7) | B10: ID6 | C10: Evolución del porcentaje de postulantes al programa | D10: % | F10: 0 | G10: 0% (valor referencial del texto) | H10: Modelo CONEAU 2026 [A4] | M10: =IF(E10="","sin dato","Sin dato validado") | N10: Solo referencia: no interviene en semáforos, alertas ni gráficos
A11: =IF(Portada!$B$7="","",Portada!$B$7) | B11: ID7 | C11: Porcentaje de estudiantes satisfechos con los programas de bienestar y actividades recreativas, culturales, artísticas y deportivas | D11: % | F11: 70 | G11: 70% | H11: Modelo CONEAU 2026 [A4] | M11: =IF(E11="","sin dato","Sin dato validado") | N11: Solo referencia: no interviene en semáforos, alertas ni gráficos
A12: =IF(Portada!$B$7="","",Portada!$B$7) | B12: ID8 | C12: Porcentaje de estudiantes satisfechos con los procedimientos de los servicios administrativos | D12: % | F12: 60 | G12: 60% | H12: Modelo CONEAU 2026 [A4] | M12: =IF(E12="","sin dato","Sin dato validado") | N12: Solo referencia: no interviene en semáforos, alertas ni gráficos
A13: =IF(Portada!$B$7="","",Portada!$B$7) | B13: ID9 | C13: Porcentaje de estudiantes satisfechos con los servicios de apoyo pedagógico | D13: % | F13: 70 | G13: 70% | H13: Modelo CONEAU 2026 [A4] | M13: =IF(E13="","sin dato","Sin dato validado") | N13: Solo referencia: no interviene en semáforos, alertas ni gráficos
A14: =IF(Portada!$B$7="","",Portada!$B$7) | B14: ID10 | C14: Porcentaje de estudiantes aprobados por asignatura | D14: % | F14: 80 | G14: 80% | H14: Modelo CONEAU 2026 [A4] | M14: =IF(E14="","sin dato","Sin dato validado") | N14: Solo referencia: no interviene en semáforos, alertas ni gráficos
A15: =IF(Portada!$B$7="","",Portada!$B$7) | B15: ID11 | C15: Porcentaje de cumplimiento de los sílabos | D15: % | F15: 90 | G15: 90% | H15: Modelo CONEAU 2026 [A4] | M15: =IF(E15="","sin dato","Sin dato validado") | N15: Solo referencia: no interviene en semáforos, alertas ni gráficos
A16: =IF(Portada!$B$7="","",Portada!$B$7) | B16: ID12 | C16: Porcentaje de docentes satisfechos con el currículo | D16: % | F16: 70 | G16: 70% | H16: Modelo CONEAU 2026 [A4] | M16: =IF(E16="","sin dato","Sin dato validado") | N16: Solo referencia: no interviene en semáforos, alertas ni gráficos
... A33: =IF(Portada!$B$7="","",Portada!$B$7) | B33: ID29 | C33: Porcentaje de empleadores satisfechos con el desempeño de los egresados | D33: % | F33: 70 | G33: 70% | H33: Modelo CONEAU 2026 [A4] | M33: =IF(E33="","sin dato","Sin dato validado") | N33: Solo referencia: no interviene en semáforos, alertas ni gráficos

Sheet Parametros
A1: Parámetros generales del tablero
A2: Los edita el comité de calidad de la Facultad. Si cambias algo, actualiza fecha_parametros: el tablero usa la hoja con la fecha más reciente.
A4: clave | B4: valor | C4: tipo | D4: fuente y nota
A5: version_parametros | B5: 0.3 | C5: texto | D5: Versión de esta hoja. Súbela cuando cambies algo.
A6: fecha_parametros | B6: 2026-10-20 | C6: fecha | D6: Fecha de la última edición. El tablero usa la hoja con la fecha más reciente.
A7: fecha_corte | C7: fecha | D7: Fecha de corte del análisis (AAAA-MM-DD). Vacío = fecha de hoy.
A8: dias_gracia | B8: 30 | C8: número | D8: [CP] Días después del cierre del periodo en que aún no se considera vencido el dato.
A9: n_periodos_tendencia | B9: 2 | C9: número | D9: Periodos seguidos de deterioro que activan la alerta de tendencia (pedido: 2).
A10: banda_poi_verde | B10: 95 | C10: número | D10: Reportes de seguimiento del POI [A14] [A15] [A16]: 95 % o más.
A11: banda_poi_rojo | B11: 75 | C11: número | D11: Reportes de seguimiento del POI [A14] [A15] [A16]: menos de 75 %.
A12: umbral_sobreejecucion | B12: 120 | C12: número | D12: [CP] Ejecutado sobre programado a partir del cual se marca sobreejecución (PE01-P7).
A13: poi_frecuencia | B13: Trimestral | C13: lista | D13: [CP] Con qué frecuencia debería llegar un reporte de seguimiento del POI.
A14: poi_evaluar | B14: Último reporte | C14: lista | D14: Qué reporte del POI evalúan las alertas: Último reporte o Todos.
A15: sin_dato_en_agregado | B15: Cuenta | C15: lista | D15: Cuenta: un indicador sin dato pesa más que uno en meta al fijar el estado de un proceso. Excluye: no pesa.
A16: heredar_alias | B16: Sí | C16: lista | D16: [CP] Un indicador de proceso que mide lo mismo que un indicador SINEACE toma su dato.
A17: evidencia_obligatoria | B17: Sí | C17: lista | D17: Sí: un dato sin evidencia genera alerta.
A18: escuelas_en_implementacion | B18: ENF | C18: texto | D18: Orden de implementación definido por Robert: 1.º Enfermería, 2.º Obstetricia, 3.º Tecnología Médica por áreas. Escuelas (TM, ENF, OBS) que ya deben cargar: solo ellas generan alertas por falta de datos. Una escuela con archivo cargado cuenta como activa. Fechas de cada fase por confirmar.
A19: alcance_inicial | B19: Piloto + 10.2 + SINEACE | C19: lista | D19: [CP] Indicadores que se vigilan por defecto, mientras la escuela no edite su hoja Alcance.

Sheet Reglas_alertas
A1: Reglas de alerta
A2: Se pueden activar, desactivar y cambiar de severidad. Los textos admiten campos entre llaves, por ejemplo {indicador}, {escuela}, {valor}, {meta}, {desde}, {periodo}.
A4: regla_id | B4: nombre | C4: activa | D4: severidad | E4: condición (resumen) | F4: qué ocurre | G4: por qué | H4: decisión o acción sugerida | I4: a quién corresponde
A5: R01 | B5: Indicador en estado crítico | C5: Sí | D5: Crítica | E5: Cumplimiento de lo esperado a la fecha de corte menor que el límite de riesgo (Metas_Umbrales) | F5: {indicador} está en estado Crítico en {escuela}: {valor} frente a {esperado_txt} ({cumpl} % de lo esperado). | G5: El resultado cae por debajo de {rojo_min} {base_txt}, el límite inferior que define {fuente_umbral}. | H5: Revisar causas con el responsable del proceso y abrir una acción correctiva (ME05) con plazo y dueño. | I5: Responsable del indicador; si no hay, coordinación de calidad (por confirmar)
A6: R02 | B6: Indicador en riesgo | C6: Sí | D6: En riesgo | E6: Cumplimiento de lo esperado a la fecha de corte entre el límite de riesgo y el límite de meta (Metas_Umbrales) | F6: {indicador} está En riesgo en {escuela}: {valor} frente a {esperado_txt} ({cumpl} % de lo esperado). | G6: El resultado está entre {rojo_min} y {verde_min} {base_txt}, el rango intermedio que define {fuente_umbral}. | H6: Analizar la brecha antes del siguiente corte y decidir si se refuerza el plan de mejora. | I6: Responsable del indicador; si no hay, coordinación de calidad (por confirmar)
A7: R03 | B7: Sin dato | C7: Sí | D7: Aviso | E7: Ninguna medición cargada de un indicador vigilado | F7: No hay ninguna medición cargada de {indicador} en {escuela}. | G7: Se esperaba al menos el periodo {periodo_esperado} (periodicidad {frecuencia}) y no hay dato con fuente. | H7: Cargar el dato con su fuente y evidencia, o registrar que el indicador no aplica a la escuela. | I7: Responsable del indicador; si no hay, coordinación de calidad (por confirmar)
A8: R04 | B8: Dato vencido | C8: Sí | D8: En riesgo | E8: Último periodo cargado anterior al esperado según la periodicidad más los días de gracia | F8: El último dato de {indicador} en {escuela} es del periodo {periodo} y ya debería existir el periodo {periodo_esperado}. | G8: La periodicidad es {frecuencia} y el plazo de carga (con {gracia} días de gracia) venció el {desde}. | H8: Pedir la carga al responsable de carga y, si no hay medición, dejar constancia del motivo. | I8: Responsable del indicador; si no hay, coordinación de calidad (por confirmar)
A9: R05 | B9: Tendencia desfavorable | C9: Sí | D9: En riesgo | E9: Dos periodos seguidos que se alejan de la meta (parámetro n_periodos_tendencia) | F9: {indicador} se aleja de la meta {n} periodos seguidos en {escuela}: {serie}. | G9: Cada medición es peor que la anterior respecto del sentido del indicador ({sentido}), aunque aún no cruce un umbral. | H9: Anticipar la causa y decidir si se interviene antes de que el indicador cruce a riesgo. | I9: Responsable del indicador; si no hay, coordinación de calidad (por confirmar)
A10: R06 | B10: Dato sin evidencia | C10: Sí | D10: Aviso | E10: La última medición no tiene evidencia (EV ni referencia) | F10: La última medición de {indicador} en {escuela} (periodo {periodo}) no tiene evidencia asociada. | G10: Sin evidencia el dato no se puede verificar ante una auditoría ni ante CONEAU. | H10: Adjuntar o indicar la evidencia (código EV y archivo o enlace) en la hoja de carga. | I10: Responsable del indicador; si no hay, coordinación de calidad (por confirmar)
A11: R07 | B11: Dato sin validar | C11: Sí | D11: Aviso | E11: La última medición está en Borrador u Observado | F11: La última medición de {indicador} en {escuela} (periodo {periodo}) figura como {estado_validacion}. | G11: Un dato sin validar no debería sustentar decisiones ni informes. | H11: Validar el dato (quién valida y fecha) o corregir la observación. | I11: Responsable del indicador; si no hay, coordinación de calidad (por confirmar)
A12: R08 | B12: Avance del POI bajo lo programado | C12: Sí | D12: Por banda | E12: Ejecutado acumulado menor que programado acumulado: por debajo del límite verde del POI | F12: La actividad {aoi} ({actividad}) lleva {avance} % de avance al corte {corte}, con {ejec} ejecutadas de {prog} programadas. | G12: Los reportes del POI consideran en meta desde {verde_min} %; entre {rojo_min} y {verde_min} % es intermedio y bajo {rojo_min} % es crítico. | H12: La UPPR y el responsable de la actividad reprograman o justifican la brecha. La actividad es compartida por la Facultad. | I12: Responsable del indicador; si no hay, coordinación de calidad (por confirmar)
A13: R09 | B13: Bajo la meta, umbral por definir | C13: Sí | D13: Aviso | E13: Hay meta con fuente pero no hay límites de riesgo definidos | F13: {indicador} está por debajo de lo esperado en {escuela}: {valor} frente a {esperado_txt}. | G13: La meta tiene fuente, pero el indicador no tiene límites de riesgo con fuente; por eso no se le asigna semáforo. | H13: Definir los límites de riesgo en Metas_Umbrales con el comité de calidad. | I13: Responsable del indicador; si no hay, coordinación de calidad (por confirmar)
A14: R10 | B14: Escuela sin carga | C14: Sí | D14: Aviso | E14: No se cargó ningún archivo ni dato de la escuela | F14: {escuela} no tiene datos cargados. | G14: El tablero consolida los archivos de carga de cada escuela y no hay ninguno para ella. | H14: Entregar la plantilla a la escuela y acordar el primer corte de carga. | I14: Responsable del indicador; si no hay, coordinación de calidad (por confirmar)
A15: R11 | B15: Dato sin fuente | C15: Sí | D15: Aviso | E15: Fila de carga sin fuente del dato | F15: Hay {n} fila(s) de {escuela} sin fuente del dato; no se muestran como dato. | G15: Todo dato mostrado debe poder rastrearse a su fuente. | H15: Completar la columna fuente_dato de la hoja de carga. | I15: Responsable del indicador; si no hay, coordinación de calidad (por confirmar)
... A18: R14 | B18: Estándar sin evidencia exigida | C18: Sí | D18: En riesgo | E18: Un estándar sin indicadores del modelo (el 10) tiene evidencias exigidas que no están disponibles ni validadas en la hoja Evidencias | F18: El estándar {estandar} de {escuela} no tiene disponibles {n_sin} de las {n_exig} evidencias que exige: {evidencias}. | G18: El modelo CONEAU 2026 [A4] las exige y todavía no hay datos cargados que las sustenten; los {nproc} procesos del criterio 10.2 se vigilan sin ellas hasta que haya datos. | H18: El responsable del estándar y el Comité de Calidad reúnen o generan cada evidencia y la registran en la hoja Evidencias del archivo de carga. | I18: Responsable del indicador; si no hay, coordinación de calidad (por confirmar)

Sheet Metas_Umbrales
A1: Metas y umbrales por indicador
A2: Solo con fuente: modelo CONEAU [A4], PEI/POI [A11] [A12] o documentos institucionales [A8]. Lo demás queda 'Por definir' y se muestra en gris, sin semáforo.
A4: indicador_id | B4: desde_anio | C4: meta | D4: sentido | E4: unidad | F4: fuente_meta | G4: estado_meta | H4: verde_min_pct | I4: rojo_min_pct | J4: base_umbral | K4: fuente_umbral | L4: nota | M4: tipo_avance | N4: regla_cumplimiento | O4: nombre
A5: ID1 | B5: 0 | C5: 60 | D5: Mayor es mejor | E5: % | F5: Valor de referencia del modelo CONEAU 2026, ID1 [A4] | G5: Con fuente | J5: cumplimiento | L5: Referencia del modelo; no equivale a una meta aprobada por la Facultad. | M5: Puntual | N5: Razón al esperado | O5: =IFERROR(INDEX(Catalogo!$C$5:$C$129,MATCH(A5,Catalogo!$A$5:$A$129,0)),"")
A6: ID2 | B6: 0 | C6: 70 | D6: Mayor es mejor | E6: % | F6: Valor de referencia del modelo CONEAU 2026, ID2 [A4] | G6: Con fuente | J6: cumplimiento | L6: Referencia del modelo; no equivale a una meta aprobada por la Facultad. | M6: Puntual | N6: Razón al esperado | O6: =IFERROR(INDEX(Catalogo!$C$5:$C$129,MATCH(A6,Catalogo!$A$5:$A$129,0)),"")
A7: ID3 | B7: 0 | C7: 70 | D7: Mayor es mejor | E7: % | F7: Valor de referencia del modelo CONEAU 2026, ID3 [A4] | G7: Con fuente | J7: cumplimiento | L7: Referencia del modelo; no equivale a una meta aprobada por la Facultad. | M7: Puntual | N7: Razón al esperado | O7: =IFERROR(INDEX(Catalogo!$C$5:$C$129,MATCH(A7,Catalogo!$A$5:$A$129,0)),"")
A8: ID4 | B8: 0 | C8: 60 | D8: Mayor es mejor | E8: % | F8: Valor de referencia del modelo CONEAU 2026, ID4 [A4] | G8: Con fuente | J8: cumplimiento | L8: Referencia del modelo; no equivale a una meta aprobada por la Facultad. | M8: Puntual | N8: Razón al esperado | O8: =IFERROR(INDEX(Catalogo!$C$5:$C$129,MATCH(A8,Catalogo!$A$5:$A$129,0)),"")
A9: ID5 | B9: 0 | C9: 70 | D9: Mayor es mejor | E9: % | F9: Valor de referencia del modelo CONEAU 2026, ID5 [A4] | G9: Con fuente | J9: cumplimiento | L9: Referencia del modelo; no equivale a una meta aprobada por la Facultad. | M9: Puntual | N9: Razón al esperado | O9: =IFERROR(INDEX(Catalogo!$C$5:$C$129,MATCH(A9,Catalogo!$A$5:$A$129,0)),"")
A10: ID6 | B10: 0 | C10: 0 | D10: Mayor es mejor | E10: % | F10: Valor de referencia del modelo CONEAU 2026, ID6 [A4] | G10: Con fuente | J10: cumplimiento | L10: Referencia del modelo; no equivale a una meta aprobada por la Facultad. Cumple si la variación es mayor o igual a 0 (indicación de Robert, 20-10-2026; la ficha del Modelo dice «igual o mayor a 0 %»). | M10: Puntual | N10: Cumple si la variación es mayor o igual a 0 | O10: =IFERROR(INDEX(Catalogo!$C$5:$C$129,MATCH(A10,Catalogo!$A$5:$A$129,0)),"")
A11: ID7 | B11: 0 | C11: 70 | D11: Mayor es mejor | E11: % | F11: Valor de referencia del modelo CONEAU 2026, ID7 [A4] | G11: Con fuente | J11: cumplimiento | L11: Referencia del modelo; no equivale a una meta aprobada por la Facultad. | M11: Puntual | N11: Razón al esperado | O11: =IFERROR(INDEX(Catalogo!$C$5:$C$129,MATCH(A11,Catalogo!$A$5:$A$129,0)),"")
A12: ID8 | B12: 0 | C12: 60 | D12: Mayor es mejor | E12: % | F12: Valor de referencia del modelo CONEAU 2026, ID8 [A4] | G12: Con fuente | J12: cumplimiento | L12: Referencia del modelo; no equivale a una meta aprobada por la Facultad. | M12: Puntual | N12: Razón al esperado | O12: =IFERROR(INDEX(Catalogo!$C$5:$C$129,MATCH(A12,Catalogo!$A$5:$A$129,0)),"")
A13: ID9 | B13: 0 | C13: 70 | D13: Mayor es mejor | E13: % | F13: Valor de referencia del modelo CONEAU 2026, ID9 [A4] | G13: Con fuente | J13: cumplimiento | L13: Referencia del modelo; no equivale a una meta aprobada por la Facultad. | M13: Puntual | N13: Razón al esperado | O13: =IFERROR(INDEX(Catalogo!$C$5:$C$129,MATCH(A13,Catalogo!$A$5:$A$129,0)),"")
A14: ID10 | B14: 0 | C14: 80 | D14: Mayor es mejor | E14: % | F14: Valor de referencia del modelo CONEAU 2026, ID10 [A4] | G14: Con fuente | J14: cumplimiento | L14: Referencia del modelo; no equivale a una meta aprobada por la Facultad. | M14: Puntual | N14: Razón al esperado | O14: =IFERROR(INDEX(Catalogo!$C$5:$C$129,MATCH(A14,Catalogo!$A$5:$A$129,0)),"")
A15: ID11 | B15: 0 | C15: 90 | D15: Mayor es mejor | E15: % | F15: Valor de referencia del modelo CONEAU 2026, ID11 [A4] | G15: Con fuente | J15: cumplimiento | L15: Referencia del modelo; no equivale a una meta aprobada por la Facultad. | M15: Puntual | N15: Razón al esperado | O15: =IFERROR(INDEX(Catalogo!$C$5:$C$129,MATCH(A15,Catalogo!$A$5:$A$129,0)),"")
A16: ID12 | B16: 0 | C16: 70 | D16: Mayor es mejor | E16: % | F16: Valor de referencia del modelo CONEAU 2026, ID12 [A4] | G16: Con fuente | J16: cumplimiento | L16: Referencia del modelo; no equivale a una meta aprobada por la Facultad. | M16: Puntual | N16: Razón al esperado | O16: =IFERROR(INDEX(Catalogo!$C$5:$C$129,MATCH(A16,Catalogo!$A$5:$A$129,0)),"")
... A33: ID29 | B33: 0 | C33: 70 | D33: Mayor es mejor | E33: % | F33: Valor de referencia del modelo CONEAU 2026, ID29 [A4] | G33: Con fuente | J33: cumplimiento | L33: Referencia del modelo; no equivale a una meta aprobada por la Facultad. | M33: Puntual | N33: Razón al esperado | O33: =IFERROR(INDEX(Catalogo!$C$5:$C$129,MATCH(A33,Catalogo!$A$5:$A$129,0)),"")
A34: PS05-I1 | D34: Por definir | E34: % | G34: Por definir | M34: Puntual | N34: Razón al esperado | O34: =IFERROR(INDEX(Catalogo!$C$5:$C$129,MATCH(A34,Catalogo!$A$5:$A$129,0)),"")
A35: PS05-I2 | D35: Por definir | E35: % | G35: Por definir | M35: Puntual | N35: Razón al esperado | O35: =IFERROR(INDEX(Catalogo!$C$5:$C$129,MATCH(A35,Catalogo!$A$5:$A$129,0)),"")
A36: PS05-I3 | D36: Por definir | E36: días | G36: Por definir | M36: Puntual | N36: Razón al esperado | O36: =IFERROR(INDEX(Catalogo!$C$5:$C$129,MATCH(A36,Catalogo!$A$5:$A$129,0)),"")
A37: PS05-I4 | D37: Por definir | E37: % | G37: Por definir | M37: Puntual | N37: Razón al esperado | O37: =IFERROR(INDEX(Catalogo!$C$5:$C$129,MATCH(A37,Catalogo!$A$5:$A$129,0)),"")
A38: ME05-I1 | D38: Por definir | E38: % | G38: Por definir | M38: Puntual | N38: Razón al esperado | O38: =IFERROR(INDEX(Catalogo!$C$5:$C$129,MATCH(A38,Catalogo!$A$5:$A$129,0)),"")
A39: ME05-I2 | D39: Por definir | E39: % | G39: Por definir | M39: Puntual | N39: Razón al esperado | O39: =IFERROR(INDEX(Catalogo!$C$5:$C$129,MATCH(A39,Catalogo!$A$5:$A$129,0)),"")
A40: ME05-I3 | D40: Por definir | E40: % | G40: Por definir | M40: Puntual | N40: Razón al esperado | O40: =IFERROR(INDEX(Catalogo!$C$5:$C$129,MATCH(A40,Catalogo!$A$5:$A$129,0)),"")
A41: ME05-I4 | D41: Por definir | E41: % | G41: Por definir | M41: Puntual | N41: Razón al esperado | O41: =IFERROR(INDEX(Catalogo!$C$5:$C$129,MATCH(A41,Catalogo!$A$5:$A$129,0)),"")
A42: ME04-I1 | D42: Por definir | E42: % | G42: Por definir | M42: Puntual | N42: Razón al esperado | O42: =IFERROR(INDEX(Catalogo!$C$5:$C$129,MATCH(A42,Catalogo!$A$5:$A$129,0)),"")
A43: ME04-I2 | D43: Por definir | E43: % | G43: Por definir | M43: Puntual | N43: Razón al esperado | O43: =IFERROR(INDEX(Catalogo!$C$5:$C$129,MATCH(A43,Catalogo!$A$5:$A$129,0)),"")
A44: ME04-I3 | D44: Por definir | E44: % | G44: Por definir | M44: Puntual | N44: Razón al esperado | O44: =IFERROR(INDEX(Catalogo!$C$5:$C$129,MATCH(A44,Catalogo!$A$5:$A$129,0)),"")
A45: ME04-I4 | D45: Por definir | E45: % | G45: Por definir | M45: Puntual | N45: Razón al esperado | O45: =IFERROR(INDEX(Catalogo!$C$5:$C$129,MATCH(A45,Catalogo!$A$5:$A$129,0)),"")
... A48: PE02-I3 | D48: Por definir | E48: % | G48: Por definir | M48: Puntual | N48: Razón al esperado | O48: =IFERROR(INDEX(Catalogo!$C$5:$C$129,MATCH(A48,Catalogo!$A$5:$A$129,0)),"")
A49: PE02-I4 | B49: 2024 | C49: 20 | D49: Mayor es mejor | E49: % | F49: PE FM AE.01.04: 20 % en 2024 [A11] p. 16 y 28 | G49: Con fuente | J49: cumplimiento | L49: Contradicción 1: el estado informado por la OCAA [A10] y el MAGPROF [A8] no coinciden con el PE FM. | M49: Puntual | N49: Razón al esperado | O49: =IFERROR(INDEX(Catalogo!$C$5:$C$129,MATCH(A49,Catalogo!$A$5:$A$129,0)),"")
A50: PE02-I4 | B50: 2025 | C50: 20 | D50: Mayor es mejor | E50: % | F50: PE FM AE.01.04: 20 % en 2025 [A11] p. 16 y 28 | G50: Con fuente | J50: cumplimiento | L50: Contradicción 1: el estado informado por la OCAA [A10] y el MAGPROF [A8] no coinciden con el PE FM. | M50: Puntual | N50: Razón al esperado | O50: =IFERROR(INDEX(Catalogo!$C$5:$C$129,MATCH(A50,Catalogo!$A$5:$A$129,0)),"")
A51: PE02-I4 | B51: 2026 | C51: 40 | D51: Mayor es mejor | E51: % | F51: PE FM AE.01.04: 40 % en 2026 [A11] p. 28; MAGPROF: 40 % en 2026 [A8] p. 38 | G51: Con fuente | J51: cumplimiento | L51: Contradicción 1: el estado informado por la OCAA [A10] y el MAGPROF [A8] no coinciden con el PE FM. | M51: Puntual | N51: Razón al esperado | O51: =IFERROR(INDEX(Catalogo!$C$5:$C$129,MATCH(A51,Catalogo!$A$5:$A$129,0)),"")
A52: PE02-I4 | B52: 2027 | C52: 40 | D52: Mayor es mejor | E52: % | F52: PE FM AE.01.04: 40 % en 2027 [A11] p. 28 | G52: Con fuente | J52: cumplimiento | L52: Contradicción 1: el estado informado por la OCAA [A10] y el MAGPROF [A8] no coinciden con el PE FM. | M52: Puntual | N52: Razón al esperado | O52: =IFERROR(INDEX(Catalogo!$C$5:$C$129,MATCH(A52,Catalogo!$A$5:$A$129,0)),"")
A53: PE01-I1 | D53: Por definir | E53: % | G53: Por definir | M53: Puntual | N53: Razón al esperado | O53: =IFERROR(INDEX(Catalogo!$C$5:$C$129,MATCH(A53,Catalogo!$A$5:$A$129,0)),"")
A54: PE01-I2 | D54: Por definir | E54: % | G54: Por definir | M54: Puntual | N54: Razón al esperado | O54: =IFERROR(INDEX(Catalogo!$C$5:$C$129,MATCH(A54,Catalogo!$A$5:$A$129,0)),"")
A55: PE01-I3 | B55: 2024 | C55: 87 | D55: Mayor es mejor | E55: % | F55: MAGPROF: 87 % [A8] p. 35 y 36 | G55: Con fuente | J55: cumplimiento | L55: Resultado de los reportes del POI [A14] [A15] [A16]; los reportes truncan el avance a 100 %. | M55: Puntual | N55: Razón al esperado | O55: =IFERROR(INDEX(Catalogo!$C$5:$C$129,MATCH(A55,Catalogo!$A$5:$A$129,0)),"")
A56: PE01-I3 | B56: 2025 | C56: 88 | D56: Mayor es mejor | E56: % | F56: MAGPROF: 88 % [A8] p. 35 y 36 | G56: Con fuente | J56: cumplimiento | L56: Resultado de los reportes del POI [A14] [A15] [A16]; los reportes truncan el avance a 100 %. | M56: Puntual | N56: Razón al esperado | O56: =IFERROR(INDEX(Catalogo!$C$5:$C$129,MATCH(A56,Catalogo!$A$5:$A$129,0)),"")
A57: PE01-I3 | B57: 2026 | C57: 89 | D57: Mayor es mejor | E57: % | F57: MAGPROF: 89 % [A8] p. 35 y 36 | G57: Con fuente | J57: cumplimiento | L57: Resultado de los reportes del POI [A14] [A15] [A16]; los reportes truncan el avance a 100 %. | M57: Puntual | N57: Razón al esperado | O57: =IFERROR(INDEX(Catalogo!$C$5:$C$129,MATCH(A57,Catalogo!$A$5:$A$129,0)),"")
A58: PE03-I1 | D58: Por definir | E58: % | G58: Por definir | M58: Puntual | N58: Razón al esperado | O58: =IFERROR(INDEX(Catalogo!$C$5:$C$129,MATCH(A58,Catalogo!$A$5:$A$129,0)),"")
A59: PE03-I2 | D59: Por definir | E59: % | G59: Por definir | M59: Puntual | N59: Razón al esperado | O59: =IFERROR(INDEX(Catalogo!$C$5:$C$129,MATCH(A59,Catalogo!$A$5:$A$129,0)),"")
A60: PE03-I3 | D60: Por definir | E60: % | G60: Por definir | M60: Puntual | N60: Razón al esperado | O60: =IFERROR(INDEX(Catalogo!$C$5:$C$129,MATCH(A60,Catalogo!$A$5:$A$129,0)),"")
A61: PE04-I1 | D61: Por definir | E61: % | G61: Por definir | M61: Puntual | N61: Razón al esperado | O61: =IFERROR(INDEX(Catalogo!$C$5:$C$129,MATCH(A61,Catalogo!$A$5:$A$129,0)),"")
A62: PE04-I2 | D62: Por definir | E62: % | G62: Por definir | M62: Puntual | N62: Razón al esperado | O62: =IFERROR(INDEX(Catalogo!$C$5:$C$129,MATCH(A62,Catalogo!$A$5:$A$129,0)),"")
A63: PE04-I3 | D63: Por definir | E63: por definir | G63: En conflicto | L63: Las fuentes miden cosas distintas: MAGPROF 61 % en 2026 [A8] p. 41; PE FM, tasas por 100 docentes y por 1000 estudiantes [A11] p. 17. Por confirmar. | M63: Puntual | N63: Razón al esperado | O63: =IFERROR(INDEX(Catalogo!$C$5:$C$129,MATCH(A63,Catalogo!$A$5:$A$129,0)),"")
A64: PM01-I3 | B64: 2024 | C64: 100 | D64: Mayor es mejor | E64: % | F64: PE FM: 100 % de 2024 a 2027 [A11] p. 15 y 25 | G64: Con fuente | J64: cumplimiento | L64: El PEI UNMSM fija 82,35 % en 2026 para el pregrado de toda la universidad [A12] p. 90: referencia distinta, no se usa. | M64: Puntual | N64: Razón al esperado | O64: =IFERROR(INDEX(Catalogo!$C$5:$C$129,MATCH(A64,Catalogo!$A$5:$A$129,0)),"")
A65: PM02-I2 | D65: Por definir | E65: % | G65: Por definir | M65: Puntual | N65: Razón al esperado | O65: =IFERROR(INDEX(Catalogo!$C$5:$C$129,MATCH(A65,Catalogo!$A$5:$A$129,0)),"")
A66: PM02-I3 | B66: 2026 | C66: 69.3 | D66: Mayor es mejor | E66: % | F66: MAGPROF: 69,3 % en 2026 [A8] p. 53 y 54 | G66: Con fuente | J66: cumplimiento | L66: Medición por escuela por documentar. | M66: Puntual | N66: Razón al esperado | O66: =IFERROR(INDEX(Catalogo!$C$5:$C$129,MATCH(A66,Catalogo!$A$5:$A$129,0)),"")
A67: PM03-I4 | B67: 2024 | C67: 75.06 | D67: Mayor es mejor | E67: % | F67: PE FM OE.01: 75,06 % en 2024 [A11] p. 15 | G67: Con fuente | J67: cumplimiento | L67: El MAGPROF fija 81 % en 2026 [A8] p. 44. | M67: Puntual | N67: Razón al esperado | O67: =IFERROR(INDEX(Catalogo!$C$5:$C$129,MATCH(A67,Catalogo!$A$5:$A$129,0)),"")
A68: PM03-I4 | B68: 2025 | C68: 78.03 | D68: Mayor es mejor | E68: % | F68: PE FM OE.01: 78,03 % en 2025 [A11] p. 15 | G68: Con fuente | J68: cumplimiento | L68: El MAGPROF fija 81 % en 2026 [A8] p. 44. | M68: Puntual | N68: Razón al esperado | O68: =IFERROR(INDEX(Catalogo!$C$5:$C$129,MATCH(A68,Catalogo!$A$5:$A$129,0)),"")
A69: PM03-I4 | B69: 2026 | C69: 81.37 | D69: Mayor es mejor | E69: % | F69: PE FM OE.01: 81,37 % en 2026 [A11] p. 15 | G69: Con fuente | J69: cumplimiento | L69: El MAGPROF fija 81 % en 2026 [A8] p. 44. | M69: Puntual | N69: Razón al esperado | O69: =IFERROR(INDEX(Catalogo!$C$5:$C$129,MATCH(A69,Catalogo!$A$5:$A$129,0)),"")
A70: PM03-I4 | B70: 2027 | C70: 83.46 | D70: Mayor es mejor | E70: % | F70: PE FM OE.01: 83,46 % en 2027 [A11] p. 15 | G70: Con fuente | J70: cumplimiento | L70: El MAGPROF fija 81 % en 2026 [A8] p. 44. | M70: Puntual | N70: Razón al esperado | O70: =IFERROR(INDEX(Catalogo!$C$5:$C$129,MATCH(A70,Catalogo!$A$5:$A$129,0)),"")
A71: PM04-I1 | D71: Por definir | E71: % | G71: Por definir | M71: Puntual | N71: Razón al esperado | O71: =IFERROR(INDEX(Catalogo!$C$5:$C$129,MATCH(A71,Catalogo!$A$5:$A$129,0)),"")
A72: PM04-I2 | D72: Por definir | E72: % | G72: Por definir | M72: Puntual | N72: Razón al esperado | O72: =IFERROR(INDEX(Catalogo!$C$5:$C$129,MATCH(A72,Catalogo!$A$5:$A$129,0)),"")
A73: PM04-I3 | D73: Por definir | E73: % | G73: Por definir | M73: Puntual | N73: Razón al esperado | O73: =IFERROR(INDEX(Catalogo!$C$5:$C$129,MATCH(A73,Catalogo!$A$5:$A$129,0)),"")
A74: PM04-I4 | D74: Por definir | E74: % | G74: Por definir | M74: Puntual | N74: Razón al esperado | O74: =IFERROR(INDEX(Catalogo!$C$5:$C$129,MATCH(A74,Catalogo!$A$5:$A$129,0)),"")
A75: PM05-I3 | D75: Por definir | E75: % | G75: Por definir | M75: Puntual | N75: Razón al esperado | O75: =IFERROR(INDEX(Catalogo!$C$5:$C$129,MATCH(A75,Catalogo!$A$5:$A$129,0)),"")
A76: PM05-I4 | D76: Por definir | E76: % | G76: Por definir | M76: Puntual | N76: Razón al esperado | O76: =IFERROR(INDEX(Catalogo!$C$5:$C$129,MATCH(A76,Catalogo!$A$5:$A$129,0)),"")
A77: PM06-I1 | D77: Por definir | E77: % | G77: Por definir | M77: Puntual | N77: Razón al esperado | O77: =IFERROR(INDEX(Catalogo!$C$5:$C$129,MATCH(A77,Catalogo!$A$5:$A$129,0)),"")
A78: PM06-I2 | D78: Por definir | E78: por definir | G78: Por definir | M78: Puntual | N78: Razón al esperado | O78: =IFERROR(INDEX(Catalogo!$C$5:$C$129,MATCH(A78,Catalogo!$A$5:$A$129,0)),"")
A79: PM06-I3 | D79: Por definir | E79: por definir | G79: En conflicto | L79: MAGPROF fija 49 en 2026 [A8] p. 47 y el PE FM 300 publicaciones [A11] p. 18 (contradicción 3 y 14). Por confirmar. | M79: Puntual | N79: Razón al esperado | O79: =IFERROR(INDEX(Catalogo!$C$5:$C$129,MATCH(A79,Catalogo!$A$5:$A$129,0)),"")
A80: PM07-I1 | D80: Por definir | E80: % | G80: Por definir | M80: Puntual | N80: Razón al esperado | O80: =IFERROR(INDEX(Catalogo!$C$5:$C$129,MATCH(A80,Catalogo!$A$5:$A$129,0)),"")
A81: PM07-I2 | D81: Por definir | E81: % | G81: Por definir | M81: Puntual | N81: Razón al esperado | O81: =IFERROR(INDEX(Catalogo!$C$5:$C$129,MATCH(A81,Catalogo!$A$5:$A$129,0)),"")
A82: PM07-I3 | D82: Por definir | E82: % | G82: En conflicto | L82: MAGPROF fija 60 % [A8] p. 50 y el PE FM 97 % [A11] p. 21 (contradicción 2). Por confirmar. | M82: Puntual | N82: Razón al esperado | O82: =IFERROR(INDEX(Catalogo!$C$5:$C$129,MATCH(A82,Catalogo!$A$5:$A$129,0)),"")
A83: ME01-I1 | B83: 2024 | C83: 30 | D83: Mayor es mejor | E83: % | F83: PE FM: al menos 30 % de los estudiantes de los dos últimos años [A11] p. 23 y 26 | G83: Con fuente | J83: cumplimiento | M83: Puntual | N83: Razón al esperado | O83: =IFERROR(INDEX(Catalogo!$C$5:$C$129,MATCH(A83,Catalogo!$A$5:$A$129,0)),"")
A84: ME01-I2 | B84: 2024 | C84: 75.06 | D84: Mayor es mejor | E84: % | F84: PE FM OE.01: 75,06 % en 2024 [A11] p. 15 | G84: Con fuente | J84: cumplimiento | L84: El MAGPROF fija 81 % [A8] p. 44. | M84: Puntual | N84: Razón al esperado | O84: =IFERROR(INDEX(Catalogo!$C$5:$C$129,MATCH(A84,Catalogo!$A$5:$A$129,0)),"")
A85: ME01-I2 | B85: 2025 | C85: 78.03 | D85: Mayor es mejor | E85: % | F85: PE FM OE.01: 78,03 % en 2025 [A11] p. 15 | G85: Con fuente | J85: cumplimiento | L85: El MAGPROF fija 81 % [A8] p. 44. | M85: Puntual | N85: Razón al esperado | O85: =IFERROR(INDEX(Catalogo!$C$5:$C$129,MATCH(A85,Catalogo!$A$5:$A$129,0)),"")
A86: ME01-I2 | B86: 2026 | C86: 81.37 | D86: Mayor es mejor | E86: % | F86: PE FM OE.01: 81,37 % en 2026 [A11] p. 15 | G86: Con fuente | J86: cumplimiento | L86: El MAGPROF fija 81 % [A8] p. 44. | M86: Puntual | N86: Razón al esperado | O86: =IFERROR(INDEX(Catalogo!$C$5:$C$129,MATCH(A86,Catalogo!$A$5:$A$129,0)),"")
A87: ME01-I2 | B87: 2027 | C87: 83.46 | D87: Mayor es mejor | E87: % | F87: PE FM OE.01: 83,46 % en 2027 [A11] p. 15 | G87: Con fuente | J87: cumplimiento | L87: El MAGPROF fija 81 % [A8] p. 44. | M87: Puntual | N87: Razón al esperado | O87: =IFERROR(INDEX(Catalogo!$C$5:$C$129,MATCH(A87,Catalogo!$A$5:$A$129,0)),"")
A88: ME01-I3 | D88: Por definir | E88: % | G88: En conflicto | L88: Una meta por público: estudiantes 60 % (ID8), docentes 75 % (ID18), egresados 70 % (ID21) [A4]. Medir cada público en su ID. | M88: Puntual | N88: Razón al esperado | O88: =IFERROR(INDEX(Catalogo!$C$5:$C$129,MATCH(A88,Catalogo!$A$5:$A$129,0)),"")
A89: ME02-I1 | D89: Por definir | E89: % | G89: Por definir | M89: Puntual | N89: Razón al esperado | O89: =IFERROR(INDEX(Catalogo!$C$5:$C$129,MATCH(A89,Catalogo!$A$5:$A$129,0)),"")
A90: ME02-I3 | D90: Por definir | E90: % | G90: Por definir | M90: Puntual | N90: Razón al esperado | O90: =IFERROR(INDEX(Catalogo!$C$5:$C$129,MATCH(A90,Catalogo!$A$5:$A$129,0)),"")
A91: ME03-I1 | D91: Por definir | E91: % | G91: Por definir | M91: Puntual | N91: Razón al esperado | O91: =IFERROR(INDEX(Catalogo!$C$5:$C$129,MATCH(A91,Catalogo!$A$5:$A$129,0)),"")
A92: ME03-I2 | D92: Por definir | E92: % | G92: Por definir | M92: Puntual | N92: Razón al esperado | O92: =IFERROR(INDEX(Catalogo!$C$5:$C$129,MATCH(A92,Catalogo!$A$5:$A$129,0)),"")
A93: ME03-I3 | D93: Por definir | E93: % | G93: Por definir | M93: Puntual | N93: Razón al esperado | O93: =IFERROR(INDEX(Catalogo!$C$5:$C$129,MATCH(A93,Catalogo!$A$5:$A$129,0)),"")
A94: ME06-I1 | D94: Por definir | E94: % | G94: Por definir | M94: Puntual | N94: Razón al esperado | O94: =IFERROR(INDEX(Catalogo!$C$5:$C$129,MATCH(A94,Catalogo!$A$5:$A$129,0)),"")
A95: ME06-I2 | D95: Por definir | E95: % | G95: Por definir | M95: Puntual | N95: Razón al esperado | O95: =IFERROR(INDEX(Catalogo!$C$5:$C$129,MATCH(A95,Catalogo!$A$5:$A$129,0)),"")
A96: PS02-I1 | D96: Por definir | E96: % | G96: Por definir | M96: Puntual | N96: Razón al esperado | O96: =IFERROR(INDEX(Catalogo!$C$5:$C$129,MATCH(A96,Catalogo!$A$5:$A$129,0)),"")
A97: PS02-I2 | D97: Por definir | E97: % | G97: Por definir | M97: Puntual | N97: Razón al esperado | O97: =IFERROR(INDEX(Catalogo!$C$5:$C$129,MATCH(A97,Catalogo!$A$5:$A$129,0)),"")
A98: PS02-I3 | D98: Por definir | E98: % | G98: En conflicto | L98: Una meta por público: estudiantes 60 % (ID8) y docentes 75 % (ID18) [A4]. Medir cada público en su ID. | M98: Puntual | N98: Razón al esperado | O98: =IFERROR(INDEX(Catalogo!$C$5:$C$129,MATCH(A98,Catalogo!$A$5:$A$129,0)),"")
A99: PS03-I1 | D99: Por definir | E99: % | G99: Por definir | M99: Puntual | N99: Razón al esperado | O99: =IFERROR(INDEX(Catalogo!$C$5:$C$129,MATCH(A99,Catalogo!$A$5:$A$129,0)),"")
A100: PS03-I2 | D100: Por definir | E100: % | G100: Por definir | M100: Puntual | N100: Razón al esperado | O100: =IFERROR(INDEX(Catalogo!$C$5:$C$129,MATCH(A100,Catalogo!$A$5:$A$129,0)),"")
A101: PS04-I1 | D101: Por definir | E101: % | G101: Por definir | M101: Puntual | N101: Razón al esperado | O101: =IFERROR(INDEX(Catalogo!$C$5:$C$129,MATCH(A101,Catalogo!$A$5:$A$129,0)),"")
A102: PS04-I3 | D102: Por definir | E102: % | G102: Por definir | M102: Puntual | N102: Razón al esperado | O102: =IFERROR(INDEX(Catalogo!$C$5:$C$129,MATCH(A102,Catalogo!$A$5:$A$129,0)),"")
A103: PS06-I1 | D103: Por definir | E103: % | G103: Por definir | M103: Puntual | N103: Razón al esperado | O103: =IFERROR(INDEX(Catalogo!$C$5:$C$129,MATCH(A103,Catalogo!$A$5:$A$129,0)),"")
A104: PS06-I2 | D104: Por definir | E104: % | G104: Por definir | M104: Puntual | N104: Razón al esperado | O104: =IFERROR(INDEX(Catalogo!$C$5:$C$129,MATCH(A104,Catalogo!$A$5:$A$129,0)),"")
A105: PS06-I3 | D105: Por definir | E105: % | G105: Por definir | M105: Puntual | N105: Razón al esperado | O105: =IFERROR(INDEX(Catalogo!$C$5:$C$129,MATCH(A105,Catalogo!$A$5:$A$129,0)),"")
A106: PM09-P1 | D106: Por definir | E106: % | G106: Por definir | M106: Puntual | N106: Razón al esperado | O106: =IFERROR(INDEX(Catalogo!$C$5:$C$129,MATCH(A106,Catalogo!$A$5:$A$129,0)),"")
A107: PM09-P2 | D107: Por definir | E107: % | G107: Por definir | M107: Puntual | N107: Razón al esperado | O107: =IFERROR(INDEX(Catalogo!$C$5:$C$129,MATCH(A107,Catalogo!$A$5:$A$129,0)),"")
A108: PM10-P5 | D108: Por definir | E108: % | G108: Por definir | M108: Puntual | N108: Razón al esperado | O108: =IFERROR(INDEX(Catalogo!$C$5:$C$129,MATCH(A108,Catalogo!$A$5:$A$129,0)),"")
A109: PE01-P6 | D109: Por definir | E109: % | G109: Por definir | M109: Puntual | N109: Razón al esperado | O109: =IFERROR(INDEX(Catalogo!$C$5:$C$129,MATCH(A109,Catalogo!$A$5:$A$129,0)),"")
A110: PE01-P7 | D110: Por definir | E110: % | G110: Por definir | M110: Puntual | N110: Razón al esperado | O110: =IFERROR(INDEX(Catalogo!$C$5:$C$129,MATCH(A110,Catalogo!$A$5:$A$129,0)),"")
A111: PE01-P8 | D111: Por definir | E111: % | G111: Por definir | M111: Puntual | N111: Razón al esperado | O111: =IFERROR(INDEX(Catalogo!$C$5:$C$129,MATCH(A111,Catalogo!$A$5:$A$129,0)),"")
A112: PEFM-OE.01 | B112: 2024 | C112: 75.06 | D112: Mayor es mejor | E112: % | F112: PE - INDICADORES FM. 1.xlsx, hoja 'PE MEDICION 2024 - 2025-I', fila 7, columna LOGRO ESPERADO 2024 | G112: Con fuente | J112: cumplimiento | L112: Porcentaje o índice: un valor parcial queda «En seguimiento» [CP]. | M112: Puntual | N112: Razón al esperado | O112: =IFERROR(INDEX(Catalogo!$C$5:$C$129,MATCH(A112,Catalogo!$A$5:$A$129,0)),"")
A113: PEFM-OE.01 | B113: 2025 | C113: 78.03 | D113: Mayor es mejor | E113: % | F113: PE - INDICADORES FM. 1.xlsx, hoja 'PE MEDICION 2024 - 2025-I', fila 7, columna LOGRO ESPERADO 2025 | G113: Con fuente | J113: cumplimiento | L113: Porcentaje o índice: un valor parcial queda «En seguimiento» [CP]. | M113: Puntual | N113: Razón al esperado | O113: =IFERROR(INDEX(Catalogo!$C$5:$C$129,MATCH(A113,Catalogo!$A$5:$A$129,0)),"")
A114: PEFM-OE.01 | B114: 2026 | C114: 81.37 | D114: Mayor es mejor | E114: % | F114: PE FM 2024-2027 [A11], matriz p. 15, código OE.01 | G114: Con fuente | J114: cumplimiento | L114: Porcentaje o índice: un valor parcial queda «En seguimiento» [CP]. | M114: Puntual | N114: Razón al esperado | O114: =IFERROR(INDEX(Catalogo!$C$5:$C$129,MATCH(A114,Catalogo!$A$5:$A$129,0)),"")
A115: PEFM-OE.01 | B115: 2027 | C115: 83.46 | D115: Mayor es mejor | E115: % | F115: PE FM 2024-2027 [A11], matriz p. 15, código OE.01 | G115: Con fuente | J115: cumplimiento | L115: Porcentaje o índice: un valor parcial queda «En seguimiento» [CP]. | M115: Puntual | N115: Razón al esperado | O115: =IFERROR(INDEX(Catalogo!$C$5:$C$129,MATCH(A115,Catalogo!$A$5:$A$129,0)),"")
A116: PEFM-AE.01.01 | B116: 2024 | C116: 354 | D116: Mayor es mejor | E116: número | F116: PE - INDICADORES FM. 1.xlsx, hoja 'PE MEDICION 2024 - 2025-I', fila 10, columna LOGRO ESPERADO 2024 | G116: Con fuente | J116: cumplimiento | L116: Se acumula en el año: se compara con lo esperado a la fecha de corte [CP]. | M116: Acumulado en el año | N116: Razón al esperado | O116: =IFERROR(INDEX(Catalogo!$C$5:$C$129,MATCH(A116,Catalogo!$A$5:$A$129,0)),"")
A117: PEFM-AE.01.01 | B117: 2025 | C117: 398 | D117: Mayor es mejor | E117: número | F117: PE - INDICADORES FM. 1.xlsx, hoja 'PE MEDICION 2024 - 2025-I', fila 10, columna LOGRO ESPERADO 2025 | G117: Con fuente | J117: cumplimiento | L117: Se acumula en el año: se compara con lo esperado a la fecha de corte [CP]. | M117: Acumulado en el año | N117: Razón al esperado | O117: =IFERROR(INDEX(Catalogo!$C$5:$C$129,MATCH(A117,Catalogo!$A$5:$A$129,0)),"")
A118: PEFM-AE.01.01 | B118: 2026 | C118: 428 | D118: Mayor es mejor | E118: número | F118: PE FM 2024-2027 [A11], matriz p. 15, código AE.01.01 | G118: Con fuente | J118: cumplimiento | L118: Se acumula en el año: se compara con lo esperado a la fecha de corte [CP]. | M118: Acumulado en el año | N118: Razón al esperado | O118: =IFERROR(INDEX(Catalogo!$C$5:$C$129,MATCH(A118,Catalogo!$A$5:$A$129,0)),"")
A119: PEFM-AE.01.01 | B119: 2027 | C119: 464 | D119: Mayor es mejor | E119: número | F119: PE FM 2024-2027 [A11], matriz p. 15, código AE.01.01 | G119: Con fuente | J119: cumplimiento | L119: Se acumula en el año: se compara con lo esperado a la fecha de corte [CP]. | M119: Acumulado en el año | N119: Razón al esperado | O119: =IFERROR(INDEX(Catalogo!$C$5:$C$129,MATCH(A119,Catalogo!$A$5:$A$129,0)),"")
...

Sheet Catalogo
A1: Catálogo de indicadores que se cargan
A2: 125 indicadores: 29 del modelo CONEAU 2026 [A4] y 96 indicadores de proceso del tablero v0.2. Los 22 indicadores de proceso que miden lo mismo que un indicador SINEACE no se cargan: toman su dato.
A4: indicador_id | B4: tipo | C4: nombre | D4: fórmula | E4: fuente del dato (catálogo) | F4: frecuencia | G4: unidad | H4: sentido | I4: responsable (por confirmar) | J4: ficha SGC | K4: estándar(es) CONEAU | L4: mide también a
A5: ID1 | B5: SINEACE | C5: Porcentaje de estudiantes satisfechos con el currículo | D5: Según la ficha del indicador en el modelo CONEAU [A4] | E5: Encuestas y registros de la escuela [CP] | F5: Anual | G5: % | H5: Mayor es mejor | I5: Por confirmar | J5: ME01 | K5: E2, E3, E8 | L5: PM01-I1
A6: ID2 | B6: SINEACE | C6: Porcentaje de estudiantes satisfechos con el desempeño docente | D6: Según la ficha del indicador en el modelo CONEAU [A4] | E6: Encuestas y registros de la escuela [CP] | F6: Anual | G6: % | H6: Mayor es mejor | I6: Por confirmar | J6: ME01, PS01 | K6: E4, E8
A7: ID3 | B7: SINEACE | C7: Porcentaje de estudiantes satisfechos con los recursos para la enseñanza-aprendizaje | D7: Según la ficha del indicador en el modelo CONEAU [A4] | E7: Encuestas y registros de la escuela [CP] | F7: Anual | G7: % | H7: Mayor es mejor | I7: Por confirmar | J7: ME01 | K7: E3, E5, E8 | L7: PS03-I3, PS04-I2
A8: ID4 | B8: SINEACE | C8: Porcentaje de estudiantes satisfechos con la evaluación del aprendizaje | D8: Según la ficha del indicador en el modelo CONEAU [A4] | E8: Encuestas y registros de la escuela [CP] | F8: Anual | G8: % | H8: Mayor es mejor | I8: Por confirmar | J8: ME01, ME02 | K8: E3, E4, E8 | L8: PM03-I3
A9: ID5 | B9: SINEACE | C9: Porcentaje de estudiantes satisfechos con la asesoría o tutoría para la obtención del título | D9: Según la ficha del indicador en el modelo CONEAU [A4] | E9: Encuestas y registros de la escuela [CP] | F9: Semestral | G9: % | H9: Mayor es mejor | I9: Por confirmar | J9: ME01, PM05 | K9: E3, E8 | L9: PM05-I1
A10: ID6 | B10: SINEACE | C10: Evolución del porcentaje de postulantes al programa | D10: Según la ficha del indicador en el modelo CONEAU [A4] | E10: Encuestas y registros de la escuela [CP] | F10: Anual | G10: % | H10: Mayor es mejor | I10: Por confirmar | J10: PM02, ME03 | K10: E8 | L10: PM02-I1
A11: ID7 | B11: SINEACE | C11: Porcentaje de estudiantes satisfechos con los programas de bienestar y actividades recreativas, culturales, artísticas y deportivas | D11: Según la ficha del indicador en el modelo CONEAU [A4] | E11: Encuestas y registros de la escuela [CP] | F11: Anual | G11: % | H11: Mayor es mejor | I11: Por confirmar | J11: ME01, PM05 | K11: E7, E8
A12: ID8 | B12: SINEACE | C12: Porcentaje de estudiantes satisfechos con los procedimientos de los servicios administrativos | D12: Según la ficha del indicador en el modelo CONEAU [A4] | E12: Encuestas y registros de la escuela [CP] | F12: Anual | G12: % | H12: Mayor es mejor | I12: Por confirmar | J12: ME01, PS02 | K12: E1, E8
A13: ID9 | B13: SINEACE | C13: Porcentaje de estudiantes satisfechos con los servicios de apoyo pedagógico | D13: Según la ficha del indicador en el modelo CONEAU [A4] | E13: Encuestas y registros de la escuela [CP] | F13: Semestral | G13: % | H13: Mayor es mejor | I13: Por confirmar | J13: ME01, PM05 | K13: E3, E7, E8 | L13: PM05-I2
A14: ID10 | B14: SINEACE | C14: Porcentaje de estudiantes aprobados por asignatura | D14: Según la ficha del indicador en el modelo CONEAU [A4] | E14: Encuestas y registros de la escuela [CP] | F14: Semestral | G14: % | H14: Mayor es mejor | I14: Por confirmar | J14: ME02, PM03 | K14: E3, E6, E8 | L14: PM03-I2, ME02-I2
A15: ID11 | B15: SINEACE | C15: Porcentaje de cumplimiento de los sílabos | D15: Según la ficha del indicador en el modelo CONEAU [A4] | E15: Encuestas y registros de la escuela [CP] | F15: Semestral | G15: % | H15: Mayor es mejor | I15: Por confirmar | J15: PM03, ME03 | K15: E2, E9 | L15: PM03-I1
A16: ID12 | B16: SINEACE | C16: Porcentaje de docentes satisfechos con el currículo | D16: Según la ficha del indicador en el modelo CONEAU [A4] | E16: Encuestas y registros de la escuela [CP] | F16: Anual | G16: % | H16: Mayor es mejor | I16: Por confirmar | J16: ME01 | K16: E2, E8 | L16: PM01-I2
A17: ID13 | B17: SINEACE | C17: Porcentaje de docentes a tiempo completo | D17: Según la ficha del indicador en el modelo CONEAU [A4] | E17: Encuestas y registros de la escuela [CP] | F17: Anual | G17: % | H17: Mayor es mejor | I17: Por confirmar | J17: PS01, ME03 | K17: E4, E8 | L17: PS01-I2
A18: ID14 | B18: SINEACE | C18: Porcentaje de docentes con grado académico de doctor | D18: Según la ficha del indicador en el modelo CONEAU [A4] | E18: Encuestas y registros de la escuela [CP] | F18: Anual | G18: % | H18: Mayor es mejor | I18: Por confirmar | J18: PS01, ME03 | K18: E4, E8 | L18: PS01-I3
A19: ID15 | B19: SINEACE | C19: Porcentaje de docentes con formación, capacitación o especialización en docencia e investigación en los últimos dos años | D19: Según la ficha del indicador en el modelo CONEAU [A4] | E19: Encuestas y registros de la escuela [CP] | F19: Anual | G19: % | H19: Mayor es mejor | I19: Por confirmar | J19: PS01, ME03 | K19: E4, E8 | L19: PS01-I4
A20: ID16 | B20: SINEACE | C20: Porcentaje de docentes satisfechos con las actividades de fortalecimiento de capacidades y desarrollo académico | D20: Según la ficha del indicador en el modelo CONEAU [A4] | E20: Encuestas y registros de la escuela [CP] | F20: Anual | G20: % | H20: Mayor es mejor | I20: Por confirmar | J20: ME01, PS01 | K20: E4, E8
A21: ID17 | B21: SINEACE | C21: Porcentaje de docentes satisfechos con los recursos para la enseñanza-aprendizaje | D21: Según la ficha del indicador en el modelo CONEAU [A4] | E21: Encuestas y registros de la escuela [CP] | F21: Anual | G21: % | H21: Mayor es mejor | I21: Por confirmar | J21: ME01 | K21: E5, E8 | L21: PS03-I4
A22: ID18 | B22: SINEACE | C22: Porcentaje de docentes satisfechos con los procedimientos de los servicios administrativos | D22: Según la ficha del indicador en el modelo CONEAU [A4] | E22: Encuestas y registros de la escuela [CP] | F22: Anual | G22: % | H22: Mayor es mejor | I22: Por confirmar | J22: ME01, PS02 | K22: E1, E8
A23: ID19 | B23: SINEACE | C23: Porcentaje de docentes con desempeño satisfactorio en opinión de los estudiantes | D23: Según la ficha del indicador en el modelo CONEAU [A4] | E23: Encuestas y registros de la escuela [CP] | F23: Semestral | G23: % | H23: Mayor es mejor | I23: Por confirmar | J23: PS01, ME01 | K23: E3, E4, E8 | L23: PS01-I1
A24: ID20 | B24: SINEACE | C24: Porcentaje de egresados satisfechos con la calidad y utilidad de la formación para su empleabilidad | D24: Según la ficha del indicador en el modelo CONEAU [A4] | E24: Encuestas y registros de la escuela [CP] | F24: Anual | G24: % | H24: Mayor es mejor | I24: Por confirmar | J24: PM08, ME01 | K24: E3, E6, E8 | L24: PM10-P3
A25: ID21 | B25: SINEACE | C25: Porcentaje de egresados satisfechos con los procedimientos de los servicios administrativos | D25: Según la ficha del indicador en el modelo CONEAU [A4] | E25: Encuestas y registros de la escuela [CP] | F25: Anual | G25: % | H25: Mayor es mejor | I25: Por confirmar | J25: PM08, ME01 | K25: E1, E8
A26: ID22 | B26: SINEACE | C26: Porcentaje de egresados satisfechos con la calidad de la enseñanza | D26: Según la ficha del indicador en el modelo CONEAU [A4] | E26: Encuestas y registros de la escuela [CP] | F26: Anual | G26: % | H26: Mayor es mejor | I26: Por confirmar | J26: PM08, ME01 | K26: E3, E6, E8
A27: ID23 | B27: SINEACE | C27: Porcentaje de egresados satisfechos con los programas de bienestar y actividades recreativas, culturales, artísticas y deportivas | D27: Según la ficha del indicador en el modelo CONEAU [A4] | E27: Encuestas y registros de la escuela [CP] | F27: Anual | G27: % | H27: Mayor es mejor | I27: Por confirmar | J27: PM08, ME01 | K27: E7, E8
A28: ID24 | B28: SINEACE | C28: Porcentaje de egresados satisfechos con los servicios de apoyo al estudiante | D28: Según la ficha del indicador en el modelo CONEAU [A4] | E28: Encuestas y registros de la escuela [CP] | F28: Anual | G28: % | H28: Mayor es mejor | I28: Por confirmar | J28: PM08, ME01 | K28: E3, E7, E8
A29: ID25 | B29: SINEACE | C29: Tiempo promedio entre egreso y titulación | D29: Según la ficha del indicador en el modelo CONEAU [A4] | E29: Encuestas y registros de la escuela [CP] | F29: Anual | G29: años | H29: Menor es mejor | I29: Por confirmar | J29: PM08, ME03 | K29: E8 | L29: PM08-I2
A30: ID26 | B30: SINEACE | C30: Tiempo promedio entre egreso y primer empleo en el campo profesional | D30: Según la ficha del indicador en el modelo CONEAU [A4] | E30: Encuestas y registros de la escuela [CP] | F30: Anual | G30: años | H30: Menor es mejor | I30: Por confirmar | J30: PM08, ME03 | K30: E6, E8 | L30: PM10-P4
A31: ID27 | B31: SINEACE | C31: Porcentaje de egresados que laboran en su campo profesional | D31: Según la ficha del indicador en el modelo CONEAU [A4] | E31: Encuestas y registros de la escuela [CP] | F31: Anual | G31: % | H31: Mayor es mejor | I31: Por confirmar | J31: PM08, ME03 | K31: E6, E8 | L31: PM08-I3
A32: ID28 | B32: SINEACE | C32: Porcentaje de estudiantes que alcanzan el título profesional dentro de los dos años posteriores al egreso | D32: Según la ficha del indicador en el modelo CONEAU [A4] | E32: Encuestas y registros de la escuela [CP] | F32: Anual | G32: % | H32: Mayor es mejor | I32: Por confirmar | J32: PM08, ME02 | K32: E6, E8 | L32: PM08-I1
A33: ID29 | B33: SINEACE | C33: Porcentaje de empleadores satisfechos con el desempeño de los egresados | D33: Según la ficha del indicador en el modelo CONEAU [A4] | E33: Encuestas y registros de la escuela [CP] | F33: Anual | G33: % | H33: Mayor es mejor | I33: Por confirmar | J33: PM08, ME01 | K33: E6, E8 | L33: PM08-I4
A34: PS05-I1 | B34: Proceso | C34: Documentos del SGC vigentes y con versión actual | D34: Documentos con versión vigente en la lista / documentos listados × 100 | E34: Lista maestra de documentos del SGC | F34: Trimestral | G34: % | H34: Por definir | I34: Coordinador/a de calidad de la facultad (por confirmar) | J34: PS05
A35: PS05-I2 | B35: Proceso | C35: Registros conservados según su plazo | D35: Registros auditados conformes con su plazo y protección / registros auditados × 100 | E35: Informe de auditoría de registros (ME04) y lista de registros | F35: Anual | G35: % | H35: Por definir | I35: Coordinador/a de calidad de la facultad (por confirmar) | J35: PS05
A36: PS05-I3 | B36: Proceso | C36: Tiempo de aprobación de documentos | D36: Promedio de días entre la solicitud de cambio y la aprobación | E36: Solicitudes de cambio y actas de aprobación | F36: Trimestral | G36: días | H36: Por definir | I36: Coordinador/a de calidad de la facultad (por confirmar) | J36: PS05
A37: PS05-I4 | B37: Proceso | C37: Solicitudes de acceso a datos atendidas en plazo | D37: Solicitudes atendidas en el plazo fijado / solicitudes recibidas × 100 | E37: Registro de solicitudes de acceso a datos | F37: Semestral | G37: % | H37: Por definir | I37: Coordinador/a de calidad de la facultad (por confirmar) | J37: PS05
A38: ME05-I1 | B38: Proceso | C38: Acciones correctivas cerradas en plazo | D38: Acciones cerradas en el plazo acordado / acciones con plazo vencido o cumplido × 100 | E38: Registro de acciones correctivas (ME05) | F38: Trimestral | G38: % | H38: Por definir | I38: Dueños de proceso / Comité de Calidad (por confirmar) | J38: ME05
A39: ME05-I2 | B39: Proceso | C39: Acciones verificadas como eficaces | D39: Acciones con eficacia verificada / acciones implementadas × 100 | E39: Registro de acciones correctivas (ME05) | F39: Trimestral | G39: % | H39: Por definir | I39: Dueños de proceso / Comité de Calidad (por confirmar) | J39: ME05
A40: ME05-I3 | B40: Proceso | C40: No conformidades recurrentes | D40: No conformidades repetidas en el siguiente ciclo / no conformidades cerradas × 100 | E40: Registro de acciones correctivas y auditorías (ME05, ME04) | F40: Anual | G40: % | H40: Por definir | I40: Dueños de proceso / Comité de Calidad (por confirmar) | J40: ME05
A41: ME05-I4 | B41: Proceso | C41: Ejecución del plan de mejora | D41: Acciones del plan ejecutadas / acciones programadas × 100 | E41: Plan de mejora de la escuela | F41: Trimestral | G41: % | H41: Por definir | I41: Dueños de proceso / Comité de Calidad (por confirmar) | J41: ME05
A42: ME04-I1 | B42: Proceso | C42: Cumplimiento del programa de auditorías | D42: Auditorías realizadas / auditorías programadas × 100 | E42: Programa e informes de auditoría interna | F42: Anual | G42: % | H42: Por definir | I42: Comité de Calidad / auditores internos (por confirmar) | J42: ME04
A43: ME04-I2 | B43: Proceso | C43: Cobertura de procesos y escuelas en el ciclo | D43: Procesos y escuelas auditados / total × 100 | E43: Programa e informes de auditoría interna | F43: Anual | G43: % | H43: Por definir | I43: Comité de Calidad / auditores internos (por confirmar) | J43: ME04
A44: ME04-I3 | B44: Proceso | C44: Hallazgos con acción en plazo | D44: No conformidades con acción registrada en plazo / no conformidades emitidas × 100 | E44: Informes de auditoría y registro de acciones | F44: Trimestral | G44: % | H44: Por definir | I44: Comité de Calidad / auditores internos (por confirmar) | J44: ME04
A45: ME04-I4 | B45: Proceso | C45: Auditores evaluados con resultado satisfactorio | D45: Auditores con F-08 satisfactoria / auditores evaluados × 100 | E45: Evaluación de auditores (FMH-OCA-03, F-08) | F45: Anual | G45: % | H45: Por definir | I45: Comité de Calidad / auditores internos (por confirmar) | J45: ME04
... A129: PEFM-AE.04.02 | B129: PE FM | C129: Ejecución del presupuesto para infraestructura y equipamiento (%) | D129: Según la matriz del PE FM [A11] y la matriz de medición [A18]; método de cálculo en la columna E de [A18] | E129: Matriz de medición del PE FM [A18], hoja 'PE MEDICION 2024 - 2025-I', fila 49 | F129: Anual | G129: % | H129: Mayor es mejor | I129: Dirección Administrativa | J129: PE FM

Sheet Relaciones
A1: Relaciones entre los 29 indicadores SINEACE, los indicadores de proceso, las fichas del SGC y los 9 procesos del criterio 10.2
A2: Vínculos del tablero v0.3 y de la matriz v0.7 [CP]. Los criterios de ID4, ID10, ID11, ID23, ID27 e ID29 fueron corregidos por Robert el 20-10-2026 contrastando con las fichas del Modelo; ID9 sigue por confirmar.
A4: ID | B4: indicador SINEACE | C4: referencia CONEAU | D4: estándar(es) | E4: indicadores de proceso que lo miden | F4: fichas SGC | G4: procesos 10.2 | H4: criterios del Modelo
A5: ID1 | B5: Porcentaje de estudiantes satisfechos con el currículo | C5: 60% | D5: E2, E3, E8 | E5: PM01-I1 | F5: ME01 | G5: P1 Diseño, evaluación y modificación curricular | H5: 2.1, 3.1, 8.2
A6: ID2 | B6: Porcentaje de estudiantes satisfechos con el desempeño docente | C6: 70% | D6: E4, E8 | E6: Sin indicador de proceso | F6: ME01, PS01 | G6: Ninguno de los nueve | H6: 4.2, 4.3, 4.4, 8.2, 8.3
A7: ID3 | B7: Porcentaje de estudiantes satisfechos con los recursos para la enseñanza-aprendizaje | C7: 70% | D7: E3, E5, E8 | E7: PS03-I3, PS04-I2 | F7: ME01 | G7: P4 Mantenimiento de infraestructura y equipamiento | H7: 3.1, 5.1, 5.2, 5.3, 5.5, 8.2
A8: ID4 | B8: Porcentaje de estudiantes satisfechos con la evaluación del aprendizaje | C8: 60% | D8: E3, E4, E8 | E8: PM03-I3 | F8: ME01, ME02 | G8: P1 Diseño, evaluación y modificación curricular; P3 Enseñanza-aprendizaje; P5 Evaluación del aprendizaje | H8: 3.1, 3.2, 3.3, 3.4, 4.1, 8.2, 8.4 (corregido el 20-10-2026)
A9: ID5 | B9: Porcentaje de estudiantes satisfechos con la asesoría o tutoría para la obtención del título | C9: 70% | D9: E3, E8 | E9: PM05-I1 | F9: ME01, PM05 | G9: P3 Enseñanza-aprendizaje; P7 Relación con las partes interesadas | H9: 3.5, 8.2
A10: ID6 | B10: Evolución del porcentaje de postulantes al programa | C10: 0% (valor referencial del texto) | D10: E8 | E10: PM02-I1 | F10: PM02, ME03 | G10: Ninguno de los nueve | H10: 8.2
A11: ID7 | B11: Porcentaje de estudiantes satisfechos con los programas de bienestar y actividades recreativas, culturales, artísticas y deportivas | C11: 70% | D11: E7, E8 | E11: Sin indicador de proceso | F11: ME01, PM05 | G11: Ninguno de los nueve | H11: 7.4, 8.2
A12: ID8 | B12: Porcentaje de estudiantes satisfechos con los procedimientos de los servicios administrativos | C12: 60% | D12: E1, E8 | E12: ME01-I3, PS02-I3 | F12: ME01, PS02 | G12: P7 Relación con las partes interesadas | H12: 1.5, 8.2
A13: ID9 | B13: Porcentaje de estudiantes satisfechos con los servicios de apoyo pedagógico | C13: 70% | D13: E3, E7, E8 | E13: PM05-I2 | F13: ME01, PM05 | G13: P3 Enseñanza-aprendizaje; P7 Relación con las partes interesadas | H13: 3.5, 7.4, 8.2 (según ficha); por confirmar. Los criterios 3.1, 6.1 y 8.4 que se veían junto a esta ficha corresponden a ID10 según la corrección de Robert del 20-10-2026
A14: ID10 | B14: Porcentaje de estudiantes aprobados por asignatura | C14: 80% | D14: E3, E6, E8 | E14: PM03-I2, ME02-I2 | F14: ME02, PM03 | G14: P1 Diseño, evaluación y modificación curricular; P3 Enseñanza-aprendizaje; P5 Evaluación del aprendizaje | H14: 3.1, 6.1, 8.4 (corregido el 20-10-2026)
A15: ID11 | B15: Porcentaje de cumplimiento de los sílabos | C15: 90% | D15: E2, E9 | E15: PM03-I1 | F15: PM03, ME03 | G15: P1 Diseño, evaluación y modificación curricular; P3 Enseñanza-aprendizaje; P5 Evaluación del aprendizaje | H15: 2.7, 9.3 (corregido el 20-10-2026)
... A33: ID29 | B33: Porcentaje de empleadores satisfechos con el desempeño de los egresados | C33: 70% | D33: E6, E8 | E33: PM08-I4 | F33: PM08, ME01 | G33: P6 Seguimiento y vinculación con egresados | H33: 6.1, 6.2, 6.3, 8.2, 8.5 (corregido el 20-10-2026)

Sheet Listas
A1: periodos | B1: estados_validacion | C1: evidencias | D1: areas | E1: indicadores | F1: escuela_id | G1: escuela_nombre | H1: origen | I1: estado_evidencia | J1: si_no
A2: 2022 | B2: Borrador | C2: EV1 | D2: Radiología | E2: ID1 | F2: ENF | G2: Enfermería | H2: Real | I2: Validada | J2: Sí
A3: 2022-S1 | B3: Observado | C3: EV2 | D3: Terapia Física | E3: ID2 | F3: OBS | G3: Obstetricia | H3: EJEMPLO | I3: Disponible | J3: No
A4: 2022-S2 | B4: Validado | C4: EV3 | D4: Terapia Ocupacional | E4: ID3 | F4: TM | G4: Tecnología Médica | I4: En elaboración | J4: Solo Facultad
A5: 2022-T1 | C5: EV4 | D5: Laboratorio Clínico y Anatomía Patológica | E5: ID4 | F5: FAC | G5: Facultad (marco común) | I5: No iniciada
A6: 2022-T2 | C6: EV5 | E6: ID5 | I6: No aplica
A7: 2022-T3 | C7: EV6 | E7: ID6
A8: 2022-T4 | C8: EV7 | E8: ID7
A9: 2022-01 | C9: EV8 | E9: ID8
A10: 2022-02 | C10: EV9 | E10: ID9
A11: 2022-03 | C11: EV10 | E11: ID10
A12: 2022-04 | C12: EV11 | E12: ID11
A13: 2022-05 | C13: EV12 | E13: ID12
A14: 2022-06 | C14: EV13 | E14: ID13
A15: 2022-07 | C15: EV14 | E15: ID14
A16: 2022-08 | C16: EV15 | E16: ID15
A17: 2022-09 | C17: EV16 | E17: ID16
A18: 2022-10 | C18: EV17 | E18: ID17
... A53: 2024-07 | C53: EV52 | E53: PE04-I1
A54: 2024-08 | E54: PE04-I2
A55: 2024-09 | E55: PE04-I3
A56: 2024-10 | E56: PM01-I3
A57: 2024-11 | E57: PM02-I2
A58: 2024-12 | E58: PM02-I3
A59: 2025 | E59: PM03-I4
A60: 2025-S1 | E60: PM04-I1
A61: 2025-S2 | E61: PM04-I2
A62: 2025-T1 | E62: PM04-I3
A63: 2025-T2 | E63: PM04-I4
A64: 2025-T3 | E64: PM05-I3
A65: 2025-T4 | E65: PM05-I4
... A126: 2028-04 | E126: PEFM-AE.04.02
A127: 2028-05
A128: 2028-06
A129: 2028-07
A130: 2028-08
A131: 2028-09
A132: 2028-10
A133: 2028-11
A134: 2028-12

Sheet Ref_EV
A1: ev_id | B1: estandar | C1: descripcion
A2: EV1 | B2: E1 | C2: Documento(s) que define(n) la organización interna para la gestión del programa de estudios.
A3: EV2 | B3: E1 | C3: Hoja de vida del cuerpo directivo a cargo de la gestión del programa.
A4: EV3 | B4: E1 | C4: Documento que contiene los objetivos académicos del programa.
A5: EV4 | B5: E1 | C5: Publicación de los objetivos académicos, accesible a las partes interesadas.
A6: EV5 | B6: E1 | C6: Planes estratégicos y operativos vigentes de los dos años anteriores a la autoevaluación.
A7: EV6 | B7: E1 | C7: Informes de evaluación de los planes estratégicos y operativos.
A8: EV7 | B8: E1 | C8: Informes sobre quejas, reclamos y denuncias presentadas y las atenciones o soluciones dadas.
A9: EV8 | B9: E2 | C9: Todos los documentos que el criterio 2.1 enuncia como componentes del currículo y su fundamentación.
A10: EV9 | B10: E2 | C10: Sílabos de las asignaturas.
A11: EV10 | B11: E2 | C11: Informe semestral de cumplimiento de sílabos: procedimiento de verificación, porcentajes y acciones.
A12: EV11 | B12: E2 | C12: Documento(s) con el procedimiento de convalidación o reconocimiento de créditos.
... A53: EV52 | B53: E10 | C53: Resultados de evaluación del funcionamiento del SGC y acciones de mejora propuestas e implementadas.
